Workbook

Sheet 0_README
A1: LoanOS India — Tenant Cost & Pricing Model (full loan lifecycle)
A2: Bottom-up unit economics for a multi-tenant, RBI-compliance-first lending platform. Origination, servicing, collections and closure across all 21 journeys and all 115 integrations.
A4: What this model answers
B5: 1. What does it cost to run one tenant for one month, to originate one loan, and to SERVICE it to closure?
B6: 2. How does that change across the 21 journeys? Sheet 14 computes it live.
B7: 3. What must we charge to hit a target gross margin — on origination AND on the book?
B8: 4. At what volume does a tenant break even, and how does year 1 differ from the steady-state book?
A10: Cost classes
B11: Class U — unit cost, fires N times against a countable basis (application, loan-month, EMI, closure, collection event).
B12: Class R — recurring subscription, scales with a QUANTITY driver (devices, branches, seats, partners, feeds).
B13: This class is why a branch-heavy tenant can cost more than a digital one at ten times the volume.
B14: Class P — platform fixed cost, allocated across tenants (cloud, governance, support).
A16: Coverage
B17: All 21 canonical product journeys.
B18: All 115 INT-* integrations: 96 carry an explicit priced driver; 19 are deliberately absorbed by the cloud,
B19: governance or service sheets, or are internal capabilities with no external unit price.
B20: Sheet 16 lists every one of the 115 with its treatment. Nothing is silently omitted.
B21: LOS lifecycle stages 1-12: application_capture through closure.
A23: How to use it
B24: Step 1 Fill only the BLUE cells on 1_Inputs. That includes the quantity drivers that size the recurring class.
B25: Step 2 Replace 2_RateCard_Unit and 3_RateCard_Recurring with signed vendor prices. Nothing else matters as much.
B26: Step 3 Calibrate 6_Funnel_And_Lifetime — conversion, tenor, prepayment, delinquency — to the tenant's own history.
B27: Step 4 Read 12_Tenant_PnL for margin and break-even, and 13_Price_Card for the quote.
B28: Step 5 Use 14_Journey_Economics to price journey by journey. Never quote one blended price across the spread.
A30: Colour legend
B31: BLUE text = hardcoded input or scenario lever. Safe to edit.
B32: BLACK text = formula on this sheet. GREEN text = link to another sheet. Do not overwrite either.
B33: YELLOW fill = key assumption you are expected to challenge.
B34: ORANGE fill = no published price anchor exists; the number is a placeholder pending a vendor quotation.
A36: Honesty note — read before quoting anyone
B37: Every rupee figure here is a PLACEHOLDER ASSUMPTION. Only three priced drivers have a dated public price in
B38: docs/architecture/integration-vendor-procurement-catalog.md (MSG91, Finvu, Cashfree). Every other line there
B39: is explicitly RFQ, which is why most of this rate card is Medium or Low confidence.
B41: The funnel, tenor, prepayment and delinquency profiles are industry-shaped guesses, not measured LoanOS data.
B42: Origination cost scales inversely with the funded rate; servicing cost scales with effective life; collections
B43: cost scales with the delinquency profile. All three are unmeasured. Stand up the usage meter before repricing.
A45: Repo anchors
B46: 21 journeys and maturity docs/product/product-journey-platform-depth.json
B47: LOS lifecycle stages docs/architecture/composed-product-journey-lifecycle.md
B48: All 115 INT-* integrations docs/architecture/platform-module-integration-api-map.md
B49: Vendor prices and RFQ status docs/architecture/integration-vendor-procurement-catalog.md
B50: 4 deployment models, packages/core/src/platform/saas-deployment-blueprints.js
B51: 17 required tenant components
B52: Per-tenant isolated runtime docs/decisions/0003-decision-engine-pure-rust-per-tenant.md (ADR 0003)
B53: Billing gap (no meter yet) INT-ADM-08 / INT-PLT-12 — priced as driver R37

Sheet 1_Inputs
A1: 1 — Deal inputs
A2: Edit BLUE cells only. Everything downstream recalculates from here.
A4: Deal identity
A6: Tenant / regulated entity name | B6: Example NBFC Ltd | C6: Free text — appears on the price card.
A7: Regulated entity type | B7: NBFC-ICC | C7: NBFC / NBFC-MFI / HFC / SFB / Bank / LSP. Drives regulatory scope.
A8: Contract term (months) | B8: 36 | C8: Amortises onboarding cost and fee.
A9: Live tenants on platform | B9: 12 | C9: Denominator for equal-share governance allocation.
A10: Platform annual funded loans (all tenants) | B10: 900000 | C10: Denominator for volume-weighted governance allocation.
A11: Deployment and service
A13: Deployment model | B13: shared_multi_tenant | C13: SAAS_DEPLOYMENT_MODELS in saas-deployment-blueprints.js.
A14: Support tier | B14: Standard | C14: Drives sheet 11.
A15: Governance allocation basis | B15: Blended 50/50 | C15: How platform compliance cost spreads across tenants.
A16: Journey, volume and book
A18: Primary journey | B18: personal_loan | C18: One of the 21 canonical journeys. Price each separately.
A19: Monthly applications STARTED | B19: 4000 | C19: Entering application_capture — not approved or funded loans.
A20: Rate card scenario | B20: Base | C20: Low / Base / High column on both rate cards.
A21: Book maturity | B21: Steady state | C21: Year 1 = ramping book, little servicing cost or revenue. Steady state = originations equal closures. Quote multi-year deals on steady state.
A22: Average ticket override (₹, 0 = journey default) | B22: 0 | C22: Set only if this tenant's ticket differs.
A23: Commercial levers
A25: Target gross margin % | B25: 0.62 | C25: Sheet 13 solves for the per-funded-loan fee that achieves this.
A26: Pass-through handling markup % | B26: 0.08 | C26: Markup on rebilled provider cost. 0% = pure pass-through.
A27: Platform fee (₹ per month) | B27: 350000 | C27: Fixed subscription. Recovers the per-tenant cost floor.
A28: Fee per DECISIONED application (₹) | B28: 12 | C28: Metered at credit_decision — resistant to junk-lead gaming.
A29: Fee per FUNDED loan (₹) | B29: 900 | C29: Origination fee, charged on disbursement.
A30: LMS fee per ACTIVE loan per month (₹) | B30: 14 | C30: Servicing fee on the book — what pays for the loan's whole life.
A31: One-time onboarding fee charged (₹) | B31: 750000 | C31: Compare against modelled onboarding cost on sheet 11.
A33: Quantity drivers — these size the RECURRING cost class (sheet 3)
A34: Recurring cost does not scale with loan volume. It scales with these. A tenant with 25 branches and 120 field devices carries that cost whether it originates 200 loans a month or 20,000.
A36: Basis key | B36: Quantity driver | C36: Quantity | D36: Unit
A37: field_devices_month | B37: Field devices under management | C37: 120 | D37: per device / month
A38: branches_month | B38: Branches / territories | C38: 25 | D38: per branch / month
A39: staff_seats_month | B39: Staff seats (all workspaces) | C39: 260 | D39: per seat / month
A40: bi_seats_month | B40: BI / analytics seats | C40: 15 | D40: per seat / month
A41: partners_month | B41: Active partners / LSPs / DSAs | C41: 40 | D41: per partner / month
A42: vendor_panel_month | B42: Empanelled valuers, advocates, agencies | C42: 35 | D42: per vendor / month
A43: bank_accounts_month | B43: Operating, escrow and collection accounts | C43: 8 | D43: per account / month
A44: languages_year | B44: Approved vernacular languages | C44: 6 | D44: per language / year
A45: reference_feeds_year | B45: Reference data feeds subscribed | C45: 4 | D45: per feed / year
A46: governed_models_year | B46: Governed models under monitoring | C46: 7 | D46: per model / year
A47: vector_gb_month | B47: Agent knowledge index (GB) | C47: 40 | D47: per GB / month
A48: tenant_month | B48: Tenant (flat) | C48: 1 | D48: per tenant / month
A49: tenant_year | B49: Tenant (flat) | C49: 1 | D49: per tenant / year
A51: Derived — do not edit
A52: Deployment model index | B52: =IFERROR(MATCH($B$13,'9_Cloud_Cost'!$C$4:$F$4,0),1)
A53: Support tier index | B53: =IFERROR(MATCH($B$14,'11_Service_Cost'!$B$5:$B$7,0),1)
A54: Rate card scenario index | B54: =IF($B$20="Low",1,IF($B$20="High",3,2))
A55: Journey column index | B55: =IFERROR(MATCH($B$18,'4_Journey_Units_LOS'!$C$3:$W$3,0),1)
A56: Effective average ticket (₹) | B56: =IF($B$22>0,$B$22,INDEX('4_Journey_Units_LOS'!$C$6:$W$6,$B$55))

Sheet 2_RateCard_Unit
A1: 2 — Unit cost rate card (Class U)
A2: One row per per-event cost driver across the whole loan lifecycle, mapped to its INT-* integration ID.
A4: Driver ID | B4: Cost driver | C4: INT ID | D4: Fires at (LOS stage / lifetime basis) | E4: Unit | F4: Low ₹ | G4: Base ₹ | H4: High ₹ | I4: Attempts | J4: Confidence | K4: Pass-through? | L4: Vendor / assumption note | M4: Public price anchor
A5: D01 | B5: Mobile/email OTP + delivery (DLT SMS / WhatsApp) | C5: INT-CUS-01 | D5: application_capture | E5: per OTP sent | F5: 0.16 | G5: 0.2 | H5: 0.3 | I5: 1.6 | J5: High | K5: No | L5: MSG91 public list: Rs 0.25 at 5k/mo, Rs 0.18 at 30k, Rs 0.16 at ~1m, +18% GST. Add DLT/operator charge. | M5: MSG91 published list price (procurement catalogue §C)
A6: D02 | B6: Lead capture, dedupe and CRM sync | C6: INT-CUS-02 | D6: application_capture | E6: per lead | F6: 0 | G6: 0.5 | H6: 2 | I6: 1 | J6: Low | K6: No | L6: Zero if internal-only; priced if an external CRM seat/API is in the path. | M6: RFQ — no public price; placeholder pending vendor quotation
A7: D03 | B7: Document upload + malware/DLP scan | C7: INT-CUS-04 | D7: application_capture | E7: per document | F7: 0.2 | G7: 0.6 | H7: 1.5 | I7: 1.05 | J7: Medium | K7: No | L7: Object storage PUT + AV/DLP scan. Excludes long-run retention (see 6_Cloud_Cost). | M7: RFQ — no public price; placeholder pending vendor quotation
A8: D04 | B8: DigiLocker consent + issued-document fetch | C8: INT-CUS-05 | D8: application_capture | E8: per fetch | F8: 2 | G8: 6 | H8: 12 | I8: 1.2 | J8: Medium | K8: Yes | L8: Aggregator fee. INT-CUS-05 is currently Missing in the integration map. | M8: RFQ — no public price; placeholder pending vendor quotation
A9: D05 | B9: Device / SIM / IP fraud signal | C9: INT-LOS-09 | D9: application_capture | E9: per check | F9: 3 | G9: 7 | H9: 15 | I9: 1.02 | J9: Medium | K9: Yes | L9: Fraud intelligence vendor; priced per device fingerprint lookup. | M9: RFQ — no public price; placeholder pending vendor quotation
A10: D06 | B10: PAN verification (Protean/NSDL) | C10: INT-LOS-01 | D10: kyc_aml | E10: per verification | F10: 1.5 | G10: 3 | H10: 6 | I10: 1.05 | J10: High | K10: Yes | L10: Well-benchmarked; aggregator markup over Protean base. | M10: RFQ — no public price; placeholder pending vendor quotation
A11: D07 | B11: Aadhaar offline XML / QR / KUA eKYC | C11: INT-LOS-01 | D11: kyc_aml | E11: per eKYC | F11: 3 | G11: 8 | H11: 20 | I11: 1.25 | J11: Medium | K11: Yes | L11: UIDAI auth/eKYC fee plus AUA/KUA aggregator markup. Permitted-use only. | M11: RFQ — no public price; placeholder pending vendor quotation
A12: D08 | B12: CKYC search + record download (CERSAI) | C12: INT-LOS-02 | D12: kyc_aml | E12: per record | F12: 0.5 | G12: 1.5 | H12: 3 | I12: 1.1 | J12: Medium | K12: Yes | L12: CERSAI download charge; low unit cost, high volume. | M12: RFQ — no public price; placeholder pending vendor quotation
A13: D09 | B13: V-CIP session (platform + agent handling time) | C13: INT-LOS-03 | D13: kyc_aml | E13: per session | F13: 40 | G13: 85 | H13: 160 | I13: 1.3 | J13: Medium | K13: Yes | L13: Largest single KYC cost. Agent minutes usually exceed the platform fee. | M13: RFQ — no public price; placeholder pending vendor quotation
A14: D10 | B14: Liveness / face match / spoof detection | C14: INT-LOS-03 | D14: kyc_aml | E14: per check | F14: 3 | G14: 7 | H14: 15 | I14: 1.2 | J14: Medium | K14: Yes | L14: Bundled into V-CIP by some vendors — avoid double counting. | M14: RFQ — no public price; placeholder pending vendor quotation
A15: D11 | B15: AML / PEP / sanctions / adverse media screen | C15: INT-LOS-09 | D15: kyc_aml | E15: per screen | F15: 2 | G15: 6 | H15: 15 | I15: 1.02 | J15: Medium | K15: Yes | L15: Per subject screened; joint applicants and UBOs multiply this. | M15: RFQ — no public price; placeholder pending vendor quotation
A16: D12 | B16: KYB — GSTIN / Udyam / MCA entity verification | C16: INT-LOS-04 | D16: kyc_aml | E16: per entity | F16: 5 | G16: 18 | H16: 45 | I16: 1.08 | J16: Low | K16: Yes | L16: INT-LOS-04 is Missing today; assumption is aggregator list price. | M16: RFQ — no public price; placeholder pending vendor quotation
... A67: C09 | B67: Repossession and yard management | C67: INT-COLAT-07 | D67: per_collection_event | E67: per repossession | F67: 3000 | G67: 9000 | H67: 25000 | I67: 1 | J67: Low | K67: Yes | L67: Asset-finance journeys: work order, inventory/condition, movement, yard fees and release. | M67: RFQ — no public price; placeholder pending vendor quotation
B69: Row groups — green = origination (LOS), blue = servicing (LMS/closure), orange = collections and recovery.
B70: SOURCE OF TRUTH: docs/architecture/integration-vendor-procurement-catalog.md carries a dated public price for only three lines below; every other line there is explicitly RFQ. Do not quote from an orange anchor cell.

Sheet 3_RateCard_Recurring
A1: 3 — Recurring cost rate card (Class R)
A2: Subscriptions and per-seat / per-device / per-partner costs. These scale with the QUANTITY DRIVERS on sheet 1, not with loan volume — which is why they decide whether a small tenant is viable.
A4: ID | B4: Recurring cost driver | C4: INT ID(s) | D4: Quantity basis | E4: Qty | F4: Low ₹ | G4: Base ₹ | H4: High ₹ | I4: Confidence | J4: Pass-through? | K4: Periods / yr | L4: ₹ per year | M4: Note
A5: R01 | B5: Mobile device management licence | C5: INT-CUS-06 | D5: field_devices_month | E5: =IFERROR(INDEX('1_Inputs'!$C$37:$C$49,MATCH($D5,'1_Inputs'!$A$37:$A$49,0)),0) | F5: 80 | G5: 150 | H5: 400 | I5: Low | J5: No | K5: 12 | L5: =E5*INDEX($F5:$H5,'1_Inputs'!$B$54)*K5 | M5: Per enrolled field device per month. MDM enrol/attest/compliance/wipe. Live adapter missing today.
A6: R02 | B6: Device attestation and certificate lifecycle | C6: INT-PLT-13 | D6: field_devices_month | E6: =IFERROR(INDEX('1_Inputs'!$C$37:$C$49,MATCH($D6,'1_Inputs'!$A$37:$A$49,0)),0) | F6: 20 | G6: 35 | H6: 90 | I6: Low | J6: No | K6: 12 | L6: =E6*INDEX($F6:$H6,'1_Inputs'!$B$54)*K6 | M6: Certificate issue/rotate/revoke per managed device. Often bundled with R01 — check before adding both.
A7: R03 | B7: Branch, agent and territory master sync | C7: INT-CUS-03 | D7: branches_month | E7: =IFERROR(INDEX('1_Inputs'!$C$37:$C$49,MATCH($D7,'1_Inputs'!$A$37:$A$49,0)),0) | F7: 100 | G7: 250 | H7: 700 | I7: Low | J7: No | K7: 12 | L7: =E7*INDEX($F7:$H7,'1_Inputs'!$B$54)*K7 | M7: Agent/branch/territory/credential/capacity master sync with change and revoke totals.
A8: R04 | B8: Vernacular content production and approval | C8: INT-CUS-08 | D8: languages_year | E8: =IFERROR(INDEX('1_Inputs'!$C$37:$C$49,MATCH($D8,'1_Inputs'!$A$37:$A$49,0)),0) | F8: 15000 | G8: 35000 | H8: 90000 | I8: Low | J8: No | K8: 1 | L8: =E8*INDEX($F8:$H8,'1_Inputs'!$B$54)*K8 | M8: Per approved language per product version per year. RBI requires KFS and key notices in a language the borrower understands — this is a regulatory cost, not a UX nicety. Dispatch is separately metered (D27).
A9: R05 | B9: Reference data feeds (benchmarks, calendars, indices) | C9: INT-RSK-06 | D9: reference_feeds_year | E9: =IFERROR(INDEX('1_Inputs'!$C$37:$C$49,MATCH($D9,'1_Inputs'!$A$37:$A$49,0)),0) | F9: 50000 | G9: 150000 | H9: 450000 | I9: Low | J9: Yes | K9: 1 | L9: =E9*INDEX($F9:$H9,'1_Inputs'!$B$54)*K9 | M9: Benchmark rates, business calendars, geography, industry and collateral indices with effective date and checksum.
A10: R06 | B10: Model operations: drift, bias and performance feeds | C10: INT-RSK-05 | D10: governed_models_year | E10: =IFERROR(INDEX('1_Inputs'!$C$37:$C$49,MATCH($D10,'1_Inputs'!$A$37:$A$49,0)),0) | F10: 40000 | G10: 90000 | H10: 250000 | I10: Low | J10: No | K10: 1 | L10: =E10*INDEX($F10:$H10,'1_Inputs'!$B$54)*K10 | M10: Per governed model per year. Registry/artifact/feature feed plus drift and bias metrics.
A11: R07 | B11: Agent knowledge index storage and refresh | C11: INT-RSK-08 | D11: vector_gb_month | E11: =IFERROR(INDEX('1_Inputs'!$C$37:$C$49,MATCH($D11,'1_Inputs'!$A$37:$A$49,0)),0) | F11: 150 | G11: 300 | H11: 800 | I11: Low | J11: No | K11: 12 | L11: =E11*INDEX($F11:$H11,'1_Inputs'!$B$54)*K11 | M11: Per GB-month of approved knowledge index, including re-embedding on source change.
A12: R08 | B12: HRMS worker, position and JML feed | C12: INT-LWS-01 | D12: staff_seats_month | E12: =IFERROR(INDEX('1_Inputs'!$C$37:$C$49,MATCH($D12,'1_Inputs'!$A$37:$A$49,0)),0) | F12: 15 | G12: 30 | H12: 80 | I12: Low | J12: No | K12: 12 | L12: =E12*INDEX($F12:$H12,'1_Inputs'!$B$54)*K12 | M12: Worker/position/manager/branch/leave/delegation deltas that drive staff authority and routing.
A13: R09 | B13: Enterprise IdP and SCIM provisioning | C13: INT-LWS-02 | D13: staff_seats_month | E13: =IFERROR(INDEX('1_Inputs'!$C$37:$C$49,MATCH($D13,'1_Inputs'!$A$37:$A$49,0)),0) | F13: 40 | G13: 110 | H13: 300 | I13: Medium | J13: No | K13: 12 | L13: =E13*INDEX($F13:$H13,'1_Inputs'!$B$54)*K13 | M13: Per active user per month, plus MFA/conditional-access and governance tier. Procurement catalogue marks this RFQ.
A14: R10 | B14: Task and escalation notifications (staff) | C14: INT-LWS-03 | D14: staff_seats_month | E14: =IFERROR(INDEX('1_Inputs'!$C$37:$C$49,MATCH($D14,'1_Inputs'!$A$37:$A$49,0)),0) | F14: 10 | G14: 20 | H14: 60 | I14: Low | J14: No | K14: 12 | L14: =E14*INDEX($F14:$H14,'1_Inputs'!$B$54)*K14 | M14: Email/SMS/WhatsApp/voice/pager to staff, with delivery callbacks. Distinct from borrower communications.
A15: R11 | B15: Evidence, committee and minutes vault | C15: INT-LWS-04 | D15: staff_seats_month | E15: =IFERROR(INDEX('1_Inputs'!$C$37:$C$49,MATCH($D15,'1_Inputs'!$A$37:$A$49,0)),0) | F15: 20 | G15: 40 | H15: 120 | I15: Low | J15: No | K15: 12 | L15: =E15*INDEX($F15:$H15,'1_Inputs'!$B$54)*K15 | M15: DMS upload/version/download, legal hold, signed minutes and manifest.
A16: R12 | B16: External work-order routing platform | C16: INT-LWS-05 | D16: vendor_panel_month | E16: =IFERROR(INDEX('1_Inputs'!$C$37:$C$49,MATCH($D16,'1_Inputs'!$A$37:$A$49,0)),0) | F16: 100 | G16: 200 | H16: 600 | I16: Low | J16: No | K16: 12 | L16: =E16*INDEX($F16:$H16,'1_Inputs'!$B$54)*K16 | M16: Per empanelled valuer/advocate/agency/custodian/insurer per month. The orders themselves are metered elsewhere.
... A41: R37 | B41: Tenant billing: meter, invoice, tax, payment | C41: INT-PLT-12, INT-ADM-08 | D41: tenant_month | E41: =IFERROR(INDEX('1_Inputs'!$C$37:$C$49,MATCH($D41,'1_Inputs'!$A$37:$A$49,0)),0) | F41: 6000 | G41: 12000 | H41: 35000 | I41: Low | J41: No | K41: 12 | L41: =E41*INDEX($F41:$H41,'1_Inputs'!$B$54)*K41 | M41: DOES NOT EXIST YET. INT-ADM-08 records 'Commercial controls only; no billing/tax/payment provider'. This line is what it will cost to run the meter this whole model depends on.
B42: TOTAL recurring ₹ per year | L42: =SUM(L5:L41)
B43: of which pass-through | L43: =SUMIF($J$5:$J$41,"Yes",L5:L41)
B44: of which platform-borne | L44: =SUMIF($J$5:$J$41,"No",L5:L41)
A46: One-time admission cost (INT-ADM-*) — flows into onboarding
A47: ID | B47: Admission cost driver | C47: INT ID | F47: Low ₹ | G47: Base ₹ | H47: High ₹ | I47: Confidence | L47: ₹ one-time | M47: Note
A48: A01 | B48: Signup contact verification and invitations | C48: INT-ADM-01 | F48: 500 | G48: 1200 | H48: 4000 | I48: Low | L48: =INDEX($F48:$H48,'1_Inputs'!$B$54) | M48: Work-email and mobile OTP, invite/expiry, DLT template, delivery/bounce.
A49: A02 | B49: Legal-entity and tax identity verification | C49: INT-ADM-02 | F49: 2000 | G49: 4500 | H49: 12000 | I49: Low | L49: =INDEX($F49:$H49,'1_Inputs'!$B$54) | M49: MCA company/LLP master, CIN/LLPIN, directors/signatories, GSTIN, PAN/TAN, Udyam status and change evidence.
A50: A03 | B50: Regulated-entity authority verification | C50: INT-ADM-03 | F50: 1000 | G50: 2500 | H50: 8000 | I50: Low | L50: =INDEX($F50:$H50,'1_Inputs'!$B$54) | M50: RBI and other-authority current/cancelled lists, licence/CoR category and layer.
A51: A04 | B51: Representative authority and signature validation | C51: INT-ADM-04 | F51: 3000 | G51: 7000 | H51: 20000 | I51: Low | L51: =INDEX($F51:$H51,'1_Inputs'!$B$54) | M51: Director/DIN/signatory match, board resolution, DSC/eSign chain, CRL/OCSP and long-term validation.
A52: A05 | B52: Corporate domain and contact assurance | C52: INT-ADM-05 | F52: 500 | G52: 1200 | H52: 4000 | I52: Low | L52: =INDEX($F52:$H52,'1_Inputs'!$B$54) | M52: DNS TXT challenge, RDAP/WHOIS, MX/mailbox, domain age and reputation.
A53: A06 | B53: Signup abuse and fraud defence | C53: INT-ADM-06 | F53: 200 | G53: 600 | H53: 2500 | I53: Low | L53: =INDEX($F53:$H53,'1_Inputs'!$B$54) | M53: WAF/rate-limit/bot challenge, IP/device/email/phone/SIM and velocity intelligence at admission.
A54: A07 | B54: Contract and outsourcing due diligence | C54: INT-ADM-07 | F54: 15000 | G54: 35000 | H54: 90000 | I54: Low | L54: =INDEX($F54:$H54,'1_Inputs'!$B$54) | M54: NDA/MSA/DPA/SLA/order-form eSign, questionnaire and evidence exchange, subprocessor/BCP/DR/exit approval.
B55: TOTAL admission ₹ (one time) | L55: =SUM(L48:L54)

Sheet 4_Journey_Units_LOS
A1: 4 — Journey unit matrix: origination
A2: Units consumed per APPLICATION STARTED, before funnel attrition. This is where the 21 journeys stop being one product and become 21 different cost structures.
A3: Driver ID | B3: Cost driver | C3: personal_loan | D3: co_lending_programme | E3: msme_working_capital | F3: msme_term_loan | G3: professional_practice_loan | H3: secured_business_loan | I3: loan_against_property | J3: home_loan | K3: equipment_machinery_finance | L3: green_equipment_finance | M3: personal_vehicle_loan | N3: commercial_vehicle_finance | O3: gold_loan | P3: education_loan | Q3: agriculture_allied_finance | R3: microfinance_group_lending | S3: consumer_durable_finance | T3: invoice_discounting | U3: purchase_order_finance | V3: supply_chain_finance | W3: trade_finance_workflow
B4: Archetype | C4: unsecured_term | D4: co_lending | E4: revolving_working_capital | F4: business_term | G4: business_term | H4: property_secured | I4: property_secured | J4: property_secured | K4: asset_finance | L4: asset_finance | M4: asset_finance | N4: asset_finance | O4: gold_custody | P4: priority_term | Q4: seasonal_field | R4: group_field | S4: merchant_pos | T4: trade_receivables | U4: trade_receivables | V4: trade_receivables | W4: trade_receivables
B5: Funnel preset | C5: Digital_Unsecured | D5: Digital_Unsecured | E5: MSME_Business | F5: MSME_Business | G5: MSME_Business | H5: Secured_HighTouch | I5: Secured_HighTouch | J5: Secured_HighTouch | K5: MSME_Business | L5: MSME_Business | M5: Digital_Unsecured | N5: MSME_Business | O5: Field_Group | P5: Secured_HighTouch | Q5: Field_Group | R5: Field_Group | S5: POS_Instant | T5: MSME_Business | U5: MSME_Business | V5: MSME_Business | W5: MSME_Business
B6: Avg ticket (₹) | C6: 250000 | D6: 300000 | E6: 1500000 | F6: 1200000 | G6: 1500000 | H6: 5000000 | I6: 6000000 | J6: 4500000 | K6: 2500000 | L6: 3000000 | M6: 800000 | N6: 1800000 | O6: 150000 | P6: 1000000 | Q6: 200000 | R6: 45000 | S6: 35000 | T6: 800000 | U6: 1500000 | V6: 1000000 | W6: 3000000
B7: Units per application started ▼
A8: D01 | B8: Mobile/email OTP + delivery (DLT SMS / WhatsApp) | C8: 1 | D8: 1 | E8: 2 | F8: 2 | G8: 2 | H8: 2 | I8: 2 | J8: 2 | K8: 2 | L8: 2 | M8: 1 | N8: 2 | O8: 1 | P8: 2 | Q8: 1 | R8: 1 | S8: 1 | T8: 2 | U8: 2 | V8: 2 | W8: 2
A9: D02 | B9: Lead capture, dedupe and CRM sync | C9: 1 | D9: 1 | E9: 1 | F9: 1 | G9: 1 | H9: 1 | I9: 1 | J9: 1 | K9: 1 | L9: 1 | M9: 1 | N9: 1 | O9: 1 | P9: 1 | Q9: 1 | R9: 1 | S9: 1 | T9: 1 | U9: 1 | V9: 1 | W9: 1
A10: D03 | B10: Document upload + malware/DLP scan | C10: 4 | D10: 5 | E10: 16 | F10: 14 | G10: 10 | H10: 18 | I10: 18 | J10: 20 | K10: 16 | L10: 18 | M10: 6 | N10: 14 | O10: 2 | P10: 14 | Q10: 6 | R10: 3 | S10: 2 | T10: 12 | U10: 14 | V10: 8 | W10: 24
A11: D04 | B11: DigiLocker consent + issued-document fetch | C11: 1 | D11: 1 | E11: 1 | F11: 1 | G11: 1 | H11: 1 | I11: 1 | J11: 1 | K11: 1 | L11: 1 | M11: 1 | N11: 1 | O11: 0 | P11: 1 | Q11: 1 | R11: 0 | S11: 0 | T11: 0 | U11: 0 | V11: 0 | W11: 0
A12: D05 | B12: Device / SIM / IP fraud signal | C12: 1 | D12: 1 | E12: 1 | F12: 1 | G12: 1 | H12: 1 | I12: 1 | J12: 1 | K12: 1 | L12: 1 | M12: 1 | N12: 1 | O12: 0 | P12: 1 | Q12: 0 | R12: 0 | S12: 1 | T12: 1 | U12: 1 | V12: 1 | W12: 1
A13: D06 | B13: PAN verification (Protean/NSDL) | C13: 1 | D13: 1 | E13: 3 | F13: 3 | G13: 2 | H13: 3 | I13: 2 | J13: 2 | K13: 3 | L13: 3 | M13: 1 | N13: 2 | O13: 1 | P13: 2 | Q13: 1 | R13: 0.6 | S13: 1 | T13: 2 | U13: 2 | V13: 2 | W13: 2
A14: D07 | B14: Aadhaar offline XML / QR / KUA eKYC | C14: 1 | D14: 1 | E14: 2 | F14: 2 | G14: 1 | H14: 2 | I14: 2 | J14: 2 | K14: 2 | L14: 2 | M14: 1 | N14: 2 | O14: 1 | P14: 2 | Q14: 1 | R14: 1 | S14: 1 | T14: 1 | U14: 1 | V14: 1 | W14: 1
A15: D08 | B15: CKYC search + record download (CERSAI) | C15: 1 | D15: 1 | E15: 2 | F15: 2 | G15: 1 | H15: 2 | I15: 2 | J15: 2 | K15: 2 | L15: 2 | M15: 1 | N15: 2 | O15: 1 | P15: 2 | Q15: 1 | R15: 1 | S15: 1 | T15: 1 | U15: 1 | V15: 1 | W15: 1
A16: D09 | B16: V-CIP session (platform + agent handling time) | C16: 1 | D16: 1 | E16: 2 | F16: 2 | G16: 1 | H16: 2 | I16: 2 | J16: 2 | K16: 2 | L16: 2 | M16: 1 | N16: 1 | O16: 0 | P16: 2 | Q16: 0 | R16: 0 | S16: 0 | T16: 1 | U16: 1 | V16: 1 | W16: 1
A17: D10 | B17: Liveness / face match / spoof detection | C17: 1 | D17: 1 | E17: 2 | F17: 2 | G17: 1 | H17: 2 | I17: 2 | J17: 2 | K17: 2 | L17: 2 | M17: 1 | N17: 1 | O17: 1 | P17: 2 | Q17: 1 | R17: 1 | S17: 1 | T17: 1 | U17: 1 | V17: 1 | W17: 1
A18: D11 | B18: AML / PEP / sanctions / adverse media screen | C18: 1 | D18: 1 | E18: 4 | F18: 4 | G18: 2 | H18: 4 | I18: 3 | J18: 3 | K18: 4 | L18: 4 | M18: 1 | N18: 3 | O18: 1 | P18: 2 | Q18: 1 | R18: 1 | S18: 1 | T18: 4 | U18: 4 | V18: 3 | W18: 6
A19: D12 | B19: KYB — GSTIN / Udyam / MCA entity verification | C19: 0 | D19: 0 | E19: 1 | F19: 1 | G19: 1 | H19: 1 | I19: 0 | J19: 0 | K19: 1 | L19: 1 | M19: 0 | N19: 1 | O19: 0 | P19: 0 | Q19: 0 | R19: 0 | S19: 0 | T19: 2 | U19: 2 | V19: 2 | W19: 2
... A45: D38 | B45: Agent knowledge retrieval (vector query) | C45: 0 | D45: 0 | E45: 0 | F45: 0 | G45: 0 | H45: 0 | I45: 0 | J45: 0 | K45: 0 | L45: 0 | M45: 0 | N45: 0 | O45: 0 | P45: 0 | Q45: 0 | R45: 0 | S45: 0 | T45: 0 | U45: 0 | V45: 0 | W45: 0

Sheet 5_Journey_Units_Service
A1: 5 — Journey unit matrix: servicing, closure and collections
A2: Servicing units are per basis-unit (loan-month, EMI, loan-year, closure). Collections rows are APPLICABILITY multipliers — repossession and auction simply do not exist for an unsecured personal loan.
A3: Driver ID | B3: Cost driver | C3: personal_loan | D3: co_lending_programme | E3: msme_working_capital | F3: msme_term_loan | G3: professional_practice_loan | H3: secured_business_loan | I3: loan_against_property | J3: home_loan | K3: equipment_machinery_finance | L3: green_equipment_finance | M3: personal_vehicle_loan | N3: commercial_vehicle_finance | O3: gold_loan | P3: education_loan | Q3: agriculture_allied_finance | R3: microfinance_group_lending | S3: consumer_durable_finance | T3: invoice_discounting | U3: purchase_order_finance | V3: supply_chain_finance | W3: trade_finance_workflow
B5: Servicing units per basis-unit ▼
A6: S01 | B6: CBS / GL posting and acknowledgement | C6: 1 | D6: 1 | E6: 1 | F6: 1 | G6: 1 | H6: 1 | I6: 1 | J6: 1 | K6: 1 | L6: 1 | M6: 1 | N6: 1 | O6: 1 | P6: 1 | Q6: 1 | R6: 1 | S6: 1 | T6: 1 | U6: 1 | V6: 1 | W6: 1
A7: S02 | B7: NACH / eNACH presentment | C7: 1 | D7: 1 | E7: 1 | F7: 1 | G7: 1 | H7: 1 | I7: 1 | J7: 1 | K7: 1 | L7: 1 | M7: 1 | N7: 1 | O7: 1 | P7: 1 | Q7: 1 | R7: 1 | S7: 1 | T7: 1 | U7: 1 | V7: 1 | W7: 1
A8: S03 | B8: Bounce / return handling | C8: 1 | D8: 1 | E8: 1 | F8: 1 | G8: 1 | H8: 1 | I8: 1 | J8: 1 | K8: 1 | L8: 1 | M8: 1 | N8: 1 | O8: 1 | P8: 1 | Q8: 1 | R8: 1 | S8: 1 | T8: 1 | U8: 1 | V8: 1 | W8: 1
A9: S04 | B9: Receipt matching and reconciliation (UTR) | C9: 1 | D9: 1 | E9: 1 | F9: 1 | G9: 1 | H9: 1 | I9: 1 | J9: 1 | K9: 1 | L9: 1 | M9: 1 | N9: 1 | O9: 1 | P9: 1 | Q9: 1 | R9: 1 | S9: 1 | T9: 1 | U9: 1 | V9: 1 | W9: 1
A10: S05 | B10: Servicing notices (EMI, rate, penal, statement) | C10: 1 | D10: 1 | E10: 1 | F10: 1 | G10: 1 | H10: 1 | I10: 1 | J10: 1 | K10: 1 | L10: 1 | M10: 1 | N10: 1 | O10: 1 | P10: 1 | Q10: 1 | R10: 1 | S10: 1 | T10: 1 | U10: 1 | V10: 1 | W10: 1
A11: S06 | B11: Statement render, vault store and retention | C11: 1 | D11: 1 | E11: 1 | F11: 1 | G11: 1 | H11: 1 | I11: 1 | J11: 1 | K11: 1 | L11: 1 | M11: 1 | N11: 1 | O11: 1 | P11: 1 | Q11: 1 | R11: 0.3 | S11: 1 | T11: 1 | U11: 1 | V11: 1 | W11: 1
A12: S07 | B12: CIC credit furnishing (monthly submission) | C12: 1 | D12: 1 | E12: 1 | F12: 1 | G12: 1 | H12: 1 | I12: 1 | J12: 1 | K12: 1 | L12: 1 | M12: 1 | N12: 1 | O12: 1 | P12: 1 | Q12: 1 | R12: 1 | S12: 1 | T12: 1 | U12: 1 | V12: 1 | W12: 1
A13: S08 | B13: Ongoing KYC refresh / AA re-consent | C13: 1 | D13: 1 | E13: 1 | F13: 1 | G13: 1 | H13: 1 | I13: 1 | J13: 1 | K13: 1 | L13: 1 | M13: 1 | N13: 1 | O13: 1 | P13: 1 | Q13: 1 | R13: 1 | S13: 0.3 | T13: 1 | U13: 1 | V13: 1 | W13: 1
A14: S09 | B14: Portfolio bureau review | C14: 1 | D14: 1 | E14: 1 | F14: 1 | G14: 1 | H14: 1 | I14: 1 | J14: 1 | K14: 1 | L14: 1 | M14: 1 | N14: 1 | O14: 0.3 | P14: 1 | Q14: 1 | R14: 1 | S14: 1 | T14: 1 | U14: 1 | V14: 1 | W14: 1
A15: S10 | B15: Ongoing AML rescreen | C15: 1 | D15: 1 | E15: 1 | F15: 1 | G15: 1 | H15: 1 | I15: 1 | J15: 1 | K15: 1 | L15: 1 | M15: 1 | N15: 1 | O15: 1 | P15: 1 | Q15: 1 | R15: 1 | S15: 1 | T15: 1 | U15: 1 | V15: 1 | W15: 1
A16: S11 | B16: Insurance renewal / collateral revaluation | C16: 0 | D16: 0 | E16: 0.5 | F16: 0.4 | G16: 0 | H16: 1 | I16: 1 | J16: 1 | K16: 1 | L16: 1 | M16: 1 | N16: 1 | O16: 0 | P16: 0.4 | Q16: 0.5 | R16: 0 | S16: 0 | T16: 0 | U16: 0 | V16: 0 | W16: 0.3
A17: S12 | B17: Refund / excess / failed-disbursement reversal | C17: 1 | D17: 1 | E17: 1 | F17: 1 | G17: 1 | H17: 1 | I17: 1 | J17: 1 | K17: 1 | L17: 1 | M17: 1 | N17: 1 | O17: 1 | P17: 1 | Q17: 1 | R17: 1 | S17: 1 | T17: 1 | U17: 1 | V17: 1 | W17: 1
... A21: S16 | B21: Custody return and release acknowledgement | C21: 0 | D21: 0 | E21: 0 | F21: 0 | G21: 0 | H21: 0 | I21: 0 | J21: 0 | K21: 0 | L21: 0 | M21: 0 | N21: 0 | O21: 1 | P21: 0 | Q21: 0 | R21: 0 | S21: 0 | T21: 0 | U21: 0 | V21: 0 | W21: 0
B23: Collections applicability multiplier ▼
A24: C01 | B24: Tele-collections (dialer, IVR, agent, recording) | C24: 1 | D24: 1 | E24: 1 | F24: 1 | G24: 1 | H24: 1 | I24: 1 | J24: 1 | K24: 1 | L24: 1 | M24: 1 | N24: 1 | O24: 1 | P24: 1 | Q24: 1 | R24: 1 | S24: 1 | T24: 1 | U24: 1 | V24: 1 | W24: 1
A25: C02 | B25: Digital collection retry (UPI / link / NACH) | C25: 1 | D25: 1 | E25: 1 | F25: 1 | G25: 1 | H25: 1 | I25: 1 | J25: 1 | K25: 1 | L25: 1 | M25: 1 | N25: 1 | O25: 1 | P25: 1 | Q25: 1 | R25: 1 | S25: 1 | T25: 1 | U25: 1 | V25: 1 | W25: 1
A26: C03 | B26: Field collection visit | C26: 1 | D26: 1 | E26: 1 | F26: 1 | G26: 1 | H26: 1 | I26: 1 | J26: 1 | K26: 1 | L26: 1 | M26: 1 | N26: 1 | O26: 0.2 | P26: 1 | Q26: 1 | R26: 1.5 | S26: 0.3 | T26: 1 | U26: 1 | V26: 1 | W26: 1
A27: C04 | B27: Agency oversight, roster and invoice handling | C27: 1 | D27: 1 | E27: 1 | F27: 1 | G27: 1 | H27: 1 | I27: 1 | J27: 1 | K27: 1 | L27: 1 | M27: 1 | N27: 1 | O27: 1 | P27: 1 | Q27: 1 | R27: 1 | S27: 1 | T27: 1 | U27: 1 | V27: 1 | W27: 1
A28: C05 | B28: Legal case filing and eCourts tracking | C28: 1 | D28: 1 | E28: 1 | F28: 1 | G28: 1 | H28: 1 | I28: 1 | J28: 1 | K28: 1 | L28: 1 | M28: 1 | N28: 1 | O28: 0.1 | P28: 1 | Q28: 1 | R28: 0.1 | S28: 0.2 | T28: 1 | U28: 1 | V28: 1 | W28: 1
A29: C06 | B29: Security enforcement (notice, possession, custodian) | C29: 0 | D29: 0 | E29: 0.5 | F29: 0.4 | G29: 0 | H29: 1 | I29: 1 | J29: 1 | K29: 0.5 | L29: 0.5 | M29: 0 | N29: 0.3 | O29: 0 | P29: 0.3 | Q29: 0.2 | R29: 0 | S29: 0 | T29: 0.3 | U29: 0.3 | V29: 0.2 | W29: 0.4
A30: C07 | B30: Auction (publish, bidder KYC, certificate) | C30: 0 | D30: 0 | E30: 0.3 | F30: 0.3 | G30: 0 | H30: 1 | I30: 1 | J30: 1 | K30: 1 | L30: 1 | M30: 1 | N30: 1 | O30: 1 | P30: 0.3 | Q30: 0.2 | R30: 0 | S30: 0 | T30: 0 | U30: 0 | V30: 0 | W30: 0.2
A31: C08 | B31: Recovery proceeds handling and GL posting | C31: 1 | D31: 1 | E31: 1 | F31: 1 | G31: 1 | H31: 1 | I31: 1 | J31: 1 | K31: 1 | L31: 1 | M31: 1 | N31: 1 | O31: 1 | P31: 1 | Q31: 1 | R31: 1 | S31: 1 | T31: 1 | U31: 1 | V31: 1 | W31: 1
A32: C09 | B32: Repossession and yard management | C32: 0 | D32: 0 | E32: 0 | F32: 0 | G32: 0 | H32: 0 | I32: 0 | J32: 0 | K32: 1 | L32: 1 | M32: 1 | N32: 1 | O32: 0 | P32: 0 | Q32: 0 | R32: 0 | S32: 0 | T32: 0 | U32: 0 | V32: 0 | W32: 0

Sheet 6_Funnel_And_Lifetime
A1: 6 — Funnel, loan lifetime and derived quantities
A2: The three assumption sets that move the answer most: origination conversion, effective loan life, and the delinquency profile. Everything below the profile blocks is derived — do not edit it.
A4: Seq | B4: LOS stage | C4: Digital_Unsecured | D4: MSME_Business | E4: Secured_HighTouch | F4: Field_Group | G4: POS_Instant | H4: Note
A5: 1 | B5: application_capture | C5: 1 | D5: 1 | E5: 1 | F5: 1 | G5: 1 | H5: Everything that starts. Junk leads live here — never meter revenue on this.
A6: 2 | B6: kyc_aml | C6: 0.78 | D6: 0.85 | E6: 0.92 | F6: 0.95 | G6: 0.94 | H6: Drop-off from abandoned KYC, failed liveness and AML referrals.
A7: 3 | B7: specialist_assessment | C7: 0.68 | D7: 0.76 | E7: 0.88 | F7: 0.92 | G7: 0.9 | H7: Where bureau, AA and BSA cost is incurred — on files that may never fund.
A8: 4 | B8: credit_decision | C8: 0.62 | D8: 0.7 | E8: 0.82 | F8: 0.9 | G8: 0.88 | H8: Recommended revenue meter #1: real engine work, hard to game.
A9: 5 | B9: kfs_acceptance | C9: 0.4 | D9: 0.48 | E9: 0.62 | F9: 0.8 | G9: 0.75 | H9: The approval cliff. The gap from credit_decision is your approval rate.
A10: 6 | B10: contracting | C10: 0.35 | D10: 0.43 | E10: 0.56 | F10: 0.76 | G10: 0.7 | H10: eSign and eStamp drop-off.
A11: 7 | B11: disbursement | C11: 0.32 | D11: 0.4 | E11: 0.52 | F11: 0.74 | G11: 0.68 | H11: FUNDED RATE. Origination cost per funded loan scales inversely with this.
A12: 8 | B12: multiple | C12: 0.75 | D12: 0.8 | E12: 0.9 | F12: 0.93 | G12: 0.92 | H12: Blended reach for drivers firing across several stages (AI/agent tokens, retrieval).
B14: Funded rate (= disbursement reach) | C14: =C11 | D14: =D11 | E14: =E11 | F14: =F11 | G14: =G11
B15: Applications per funded loan | C15: =IFERROR(1/C11,0) | D15: =IFERROR(1/D11,0) | E15: =IFERROR(1/E11,0) | F15: =IFERROR(1/F11,0) | G15: =IFERROR(1/G11,0) | H15: You pay verification cost on every one of these, but bill an origination fee on only the one that funds.
A18: LOS driver reach lookup (derived)
A19: Driver ID | B19: LOS stage | C19: Digital_Unsecured | D19: MSME_Business | E19: Secured_HighTouch | F19: Field_Group | G19: POS_Instant
A20: D01 | B20: application_capture | C20: =INDEX(C$5:C$12,MATCH($B20,$B$5:$B$12,0)) | D20: =INDEX(D$5:D$12,MATCH($B20,$B$5:$B$12,0)) | E20: =INDEX(E$5:E$12,MATCH($B20,$B$5:$B$12,0)) | F20: =INDEX(F$5:F$12,MATCH($B20,$B$5:$B$12,0)) | G20: =INDEX(G$5:G$12,MATCH($B20,$B$5:$B$12,0))
A21: D02 | B21: application_capture | C21: =INDEX(C$5:C$12,MATCH($B21,$B$5:$B$12,0)) | D21: =INDEX(D$5:D$12,MATCH($B21,$B$5:$B$12,0)) | E21: =INDEX(E$5:E$12,MATCH($B21,$B$5:$B$12,0)) | F21: =INDEX(F$5:F$12,MATCH($B21,$B$5:$B$12,0)) | G21: =INDEX(G$5:G$12,MATCH($B21,$B$5:$B$12,0))
A22: D03 | B22: application_capture | C22: =INDEX(C$5:C$12,MATCH($B22,$B$5:$B$12,0)) | D22: =INDEX(D$5:D$12,MATCH($B22,$B$5:$B$12,0)) | E22: =INDEX(E$5:E$12,MATCH($B22,$B$5:$B$12,0)) | F22: =INDEX(F$5:F$12,MATCH($B22,$B$5:$B$12,0)) | G22: =INDEX(G$5:G$12,MATCH($B22,$B$5:$B$12,0))
A23: D04 | B23: application_capture | C23: =INDEX(C$5:C$12,MATCH($B23,$B$5:$B$12,0)) | D23: =INDEX(D$5:D$12,MATCH($B23,$B$5:$B$12,0)) | E23: =INDEX(E$5:E$12,MATCH($B23,$B$5:$B$12,0)) | F23: =INDEX(F$5:F$12,MATCH($B23,$B$5:$B$12,0)) | G23: =INDEX(G$5:G$12,MATCH($B23,$B$5:$B$12,0))
A24: D05 | B24: application_capture | C24: =INDEX(C$5:C$12,MATCH($B24,$B$5:$B$12,0)) | D24: =INDEX(D$5:D$12,MATCH($B24,$B$5:$B$12,0)) | E24: =INDEX(E$5:E$12,MATCH($B24,$B$5:$B$12,0)) | F24: =INDEX(F$5:F$12,MATCH($B24,$B$5:$B$12,0)) | G24: =INDEX(G$5:G$12,MATCH($B24,$B$5:$B$12,0))
A25: D06 | B25: kyc_aml | C25: =INDEX(C$5:C$12,MATCH($B25,$B$5:$B$12,0)) | D25: =INDEX(D$5:D$12,MATCH($B25,$B$5:$B$12,0)) | E25: =INDEX(E$5:E$12,MATCH($B25,$B$5:$B$12,0)) | F25: =INDEX(F$5:F$12,MATCH($B25,$B$5:$B$12,0)) | G25: =INDEX(G$5:G$12,MATCH($B25,$B$5:$B$12,0))
A26: D07 | B26: kyc_aml | C26: =INDEX(C$5:C$12,MATCH($B26,$B$5:$B$12,0)) | D26: =INDEX(D$5:D$12,MATCH($B26,$B$5:$B$12,0)) | E26: =INDEX(E$5:E$12,MATCH($B26,$B$5:$B$12,0)) | F26: =INDEX(F$5:F$12,MATCH($B26,$B$5:$B$12,0)) | G26: =INDEX(G$5:G$12,MATCH($B26,$B$5:$B$12,0))
A27: D08 | B27: kyc_aml | C27: =INDEX(C$5:C$12,MATCH($B27,$B$5:$B$12,0)) | D27: =INDEX(D$5:D$12,MATCH($B27,$B$5:$B$12,0)) | E27: =INDEX(E$5:E$12,MATCH($B27,$B$5:$B$12,0)) | F27: =INDEX(F$5:F$12,MATCH($B27,$B$5:$B$12,0)) | G27: =INDEX(G$5:G$12,MATCH($B27,$B$5:$B$12,0))
A28: D09 | B28: kyc_aml | C28: =INDEX(C$5:C$12,MATCH($B28,$B$5:$B$12,0)) | D28: =INDEX(D$5:D$12,MATCH($B28,$B$5:$B$12,0)) | E28: =INDEX(E$5:E$12,MATCH($B28,$B$5:$B$12,0)) | F28: =INDEX(F$5:F$12,MATCH($B28,$B$5:$B$12,0)) | G28: =INDEX(G$5:G$12,MATCH($B28,$B$5:$B$12,0))
A29: D10 | B29: kyc_aml | C29: =INDEX(C$5:C$12,MATCH($B29,$B$5:$B$12,0)) | D29: =INDEX(D$5:D$12,MATCH($B29,$B$5:$B$12,0)) | E29: =INDEX(E$5:E$12,MATCH($B29,$B$5:$B$12,0)) | F29: =INDEX(F$5:F$12,MATCH($B29,$B$5:$B$12,0)) | G29: =INDEX(G$5:G$12,MATCH($B29,$B$5:$B$12,0))
A30: D11 | B30: kyc_aml | C30: =INDEX(C$5:C$12,MATCH($B30,$B$5:$B$12,0)) | D30: =INDEX(D$5:D$12,MATCH($B30,$B$5:$B$12,0)) | E30: =INDEX(E$5:E$12,MATCH($B30,$B$5:$B$12,0)) | F30: =INDEX(F$5:F$12,MATCH($B30,$B$5:$B$12,0)) | G30: =INDEX(G$5:G$12,MATCH($B30,$B$5:$B$12,0))
A31: D12 | B31: kyc_aml | C31: =INDEX(C$5:C$12,MATCH($B31,$B$5:$B$12,0)) | D31: =INDEX(D$5:D$12,MATCH($B31,$B$5:$B$12,0)) | E31: =INDEX(E$5:E$12,MATCH($B31,$B$5:$B$12,0)) | F31: =INDEX(F$5:F$12,MATCH($B31,$B$5:$B$12,0)) | G31: =INDEX(G$5:G$12,MATCH($B31,$B$5:$B$12,0))
... A57: D38 | B57: multiple | C57: =INDEX(C$5:C$12,MATCH($B57,$B$5:$B$12,0)) | D57: =INDEX(D$5:D$12,MATCH($B57,$B$5:$B$12,0)) | E57: =INDEX(E$5:E$12,MATCH($B57,$B$5:$B$12,0)) | F57: =INDEX(F$5:F$12,MATCH($B57,$B$5:$B$12,0)) | G57: =INDEX(G$5:G$12,MATCH($B57,$B$5:$B$12,0))
A61: Loan lifetime profile — tenor, prepayment and delinquency (EDIT the blue cells)
A62: Journey | B62: Archetype | C62: Tenor (months) | D62: Life factor | E62: Effective life (months) | F62: Effective life (years) | G62: EMI per year | H62: EMI count | I62: Bounce rate | J62: Bounced EMIs | K62: DPD 1-30 | L62: DPD 31-90 | M62: DPD 90+ | N62: Delinq months 1-30 | O62: Delinq months 31-90 | P62: Delinq months 90+ | Q62: per_loan_month | R62: per_emi | S62: per_bounced_emi | T62: per_loan_year | U62: per_closure
A63: personal_loan | B63: unsecured_term | C63: 36 | D63: 0.85 | E63: =C63*D63 | F63: =E63/12 | G63: 12 | H63: =F63*G63 | I63: 0.055 | J63: =H63*I63 | K63: 0.04 | L63: 0.015 | M63: 0.025 | N63: =$E63*K63 | O63: =$E63*L63 | P63: =$E63*M63 | Q63: =E63 | R63: =H63 | S63: =J63 | T63: =F63 | U63: 1
A64: co_lending_programme | B64: co_lending | C64: 36 | D64: 0.85 | E64: =C64*D64 | F64: =E64/12 | G64: 12 | H64: =F64*G64 | I64: 0.055 | J64: =H64*I64 | K64: 0.042 | L64: 0.016 | M64: 0.026 | N64: =$E64*K64 | O64: =$E64*L64 | P64: =$E64*M64 | Q64: =E64 | R64: =H64 | S64: =J64 | T64: =F64 | U64: 1
A65: msme_working_capital | B65: revolving_working_capital | C65: 12 | D65: 1 | E65: =C65*D65 | F65: =E65/12 | G65: 12 | H65: =F65*G65 | I65: 0.06 | J65: =H65*I65 | K65: 0.05 | L65: 0.02 | M65: 0.03 | N65: =$E65*K65 | O65: =$E65*L65 | P65: =$E65*M65 | Q65: =E65 | R65: =H65 | S65: =J65 | T65: =F65 | U65: 1
A66: msme_term_loan | B66: business_term | C66: 48 | D66: 0.8 | E66: =C66*D66 | F66: =E66/12 | G66: 12 | H66: =F66*G66 | I66: 0.06 | J66: =H66*I66 | K66: 0.05 | L66: 0.02 | M66: 0.03 | N66: =$E66*K66 | O66: =$E66*L66 | P66: =$E66*M66 | Q66: =E66 | R66: =H66 | S66: =J66 | T66: =F66 | U66: 1
A67: professional_practice_loan | B67: business_term | C67: 60 | D67: 0.75 | E67: =C67*D67 | F67: =E67/12 | G67: 12 | H67: =F67*G67 | I67: 0.04 | J67: =H67*I67 | K67: 0.03 | L67: 0.012 | M67: 0.018 | N67: =$E67*K67 | O67: =$E67*L67 | P67: =$E67*M67 | Q67: =E67 | R67: =H67 | S67: =J67 | T67: =F67 | U67: 1
A68: secured_business_loan | B68: property_secured | C68: 120 | D68: 0.55 | E68: =C68*D68 | F68: =E68/12 | G68: 12 | H68: =F68*G68 | I68: 0.045 | J68: =H68*I68 | K68: 0.035 | L68: 0.014 | M68: 0.022 | N68: =$E68*K68 | O68: =$E68*L68 | P68: =$E68*M68 | Q68: =E68 | R68: =H68 | S68: =J68 | T68: =F68 | U68: 1
A69: loan_against_property | B69: property_secured | C69: 144 | D69: 0.5 | E69: =C69*D69 | F69: =E69/12 | G69: 12 | H69: =F69*G69 | I69: 0.04 | J69: =H69*I69 | K69: 0.03 | L69: 0.012 | M69: 0.02 | N69: =$E69*K69 | O69: =$E69*L69 | P69: =$E69*M69 | Q69: =E69 | R69: =H69 | S69: =J69 | T69: =F69 | U69: 1
A70: home_loan | B70: property_secured | C70: 240 | D70: 0.45 | E70: =C70*D70 | F70: =E70/12 | G70: 12 | H70: =F70*G70 | I70: 0.02 | J70: =H70*I70 | K70: 0.015 | L70: 0.005 | M70: 0.008 | N70: =$E70*K70 | O70: =$E70*L70 | P70: =$E70*M70 | Q70: =E70 | R70: =H70 | S70: =J70 | T70: =F70 | U70: 1
A71: equipment_machinery_finance | B71: asset_finance | C71: 60 | D71: 0.75 | E71: =C71*D71 | F71: =E71/12 | G71: 12 | H71: =F71*G71 | I71: 0.055 | J71: =H71*I71 | K71: 0.045 | L71: 0.018 | M71: 0.028 | N71: =$E71*K71 | O71: =$E71*L71 | P71: =$E71*M71 | Q71: =E71 | R71: =H71 | S71: =J71 | T71: =F71 | U71: 1
A72: green_equipment_finance | B72: asset_finance | C72: 60 | D72: 0.75 | E72: =C72*D72 | F72: =E72/12 | G72: 12 | H72: =F72*G72 | I72: 0.05 | J72: =H72*I72 | K72: 0.04 | L72: 0.016 | M72: 0.024 | N72: =$E72*K72 | O72: =$E72*L72 | P72: =$E72*M72 | Q72: =E72 | R72: =H72 | S72: =J72 | T72: =F72 | U72: 1
A73: personal_vehicle_loan | B73: asset_finance | C73: 60 | D73: 0.7 | E73: =C73*D73 | F73: =E73/12 | G73: 12 | H73: =F73*G73 | I73: 0.05 | J73: =H73*I73 | K73: 0.04 | L73: 0.016 | M73: 0.024 | N73: =$E73*K73 | O73: =$E73*L73 | P73: =$E73*M73 | Q73: =E73 | R73: =H73 | S73: =J73 | T73: =F73 | U73: 1
A74: commercial_vehicle_finance | B74: asset_finance | C74: 48 | D74: 0.75 | E74: =C74*D74 | F74: =E74/12 | G74: 12 | H74: =F74*G74 | I74: 0.08 | J74: =H74*I74 | K74: 0.07 | L74: 0.03 | M74: 0.04 | N74: =$E74*K74 | O74: =$E74*L74 | P74: =$E74*M74 | Q74: =E74 | R74: =H74 | S74: =J74 | T74: =F74 | U74: 1
... A83: trade_finance_workflow | B83: trade_receivables | C83: 6 | D83: 1 | E83: =C83*D83 | F83: =E83/12 | G83: 2 | H83: =F83*G83 | I83: 0.045 | J83: =H83*I83 | K83: 0.035 | L83: 0.015 | M83: 0.022 | N83: =$E83*K83 | O83: =$E83*L83 | P83: =$E83*M83 | Q83: =E83 | R83: =H83 | S83: =J83 | T83: =F83 | U83: 1
A85: Life factor = the share of contractual tenor a loan actually survives, after prepayment and foreclosure. A 240-month home loan that typically closes in year 8-10 has a life factor near 0.45. Servicing cost and servicing revenue both scale with effective life, so this number cuts both ways.
A88: Collection attempts per delinquent loan-month, by bucket (EDIT)
A89: Driver ID | B89: Collections driver | C89: 1-30 DPD | D89: 31-90 DPD | E89: 90+ DPD
A90: C01 | B90: Tele-collections (dialer, IVR, agent, recording) | C90: 2.5 | D90: 4 | E90: 3
A91: C02 | B91: Digital collection retry (UPI / link / NACH) | C91: 1.8 | D91: 2.2 | E91: 1.5
A92: C03 | B92: Field collection visit | C92: 0.05 | D92: 0.6 | E92: 0.9
A93: C04 | B93: Agency oversight, roster and invoice handling | C93: 0.2 | D93: 1 | E93: 1
A94: C05 | B94: Legal case filing and eCourts tracking | C94: 0 | D94: 0 | E94: 0.02
A95: C06 | B95: Security enforcement (notice, possession, custodian) | C95: 0 | D95: 0 | E95: 0.015
A96: C07 | B96: Auction (publish, bidder KYC, certificate) | C96: 0 | D96: 0 | E96: 0.008
A97: C08 | B97: Recovery proceeds handling and GL posting | C97: 0.1 | D97: 0.25 | E97: 0.3
A98: C09 | B98: Repossession and yard management | C98: 0 | D98: 0 | E98: 0.012
A99: One shared playbook across journeys. The journey-specific part is the delinquency distribution and the applicability multiplier on sheet 5, not the collections playbook itself.
A102: Servicing basis quantity per driver per journey (derived — do not edit)
A103: Driver ID | B103: Basis | C103: personal_loan | D103: co_lending_programme | E103: msme_working_capital | F103: msme_term_loan | G103: professional_practice_loan | H103: secured_business_loan | I103: loan_against_property | J103: home_loan | K103: equipment_machinery_finance | L103: green_equipment_finance | M103: personal_vehicle_loan | N103: commercial_vehicle_finance | O103: gold_loan | P103: education_loan | Q103: agriculture_allied_finance | R103: microfinance_group_lending | S103: consumer_durable_finance | T103: invoice_discounting | U103: purchase_order_finance | V103: supply_chain_finance | W103: trade_finance_workflow
A104: S01 | B104: per_loan_month | C104: =IFERROR(INDEX($Q$63:$U$83,MATCH(C$103,$A$63:$A$83,0),MATCH($B104,$Q$62:$U$62,0)),0) | D104: =IFERROR(INDEX($Q$63:$U$83,MATCH(D$103,$A$63:$A$83,0),MATCH($B104,$Q$62:$U$62,0)),0) | E104: =IFERROR(INDEX($Q$63:$U$83,MATCH(E$103,$A$63:$A$83,0),MATCH($B104,$Q$62:$U$62,0)),0) | F104: =IFERROR(INDEX($Q$63:$U$83,MATCH(F$103,$A$63:$A$83,0),MATCH($B104,$Q$62:$U$62,0)),0) | G104: =IFERROR(INDEX($Q$63:$U$83,MATCH(G$103,$A$63:$A$83,0),MATCH($B104,$Q$62:$U$62,0)),0) | H104: =IFERROR(INDEX($Q$63:$U$83,MATCH(H$103,$A$63:$A$83,0),MATCH($B104,$Q$62:$U$62,0)),0) | I104: =IFERROR(INDEX($Q$63:$U$83,MATCH(I$103,$A$63:$A$83,0),MATCH($B104,$Q$62:$U$62,0)),0) | J104: =IFERROR(INDEX($Q$63:$U$83,MATCH(J$103,$A$63:$A$83,0),MATCH($B104,$Q$62:$U$62,0)),0) | ... W104: =IFERROR(INDEX($Q$63:$U$83,MATCH(W$103,$A$63:$A$83,0),MATCH($B104,$Q$62:$U$62,0)),0)
A105: S02 | B105: per_emi | C105: =IFERROR(INDEX($Q$63:$U$83,MATCH(C$103,$A$63:$A$83,0),MATCH($B105,$Q$62:$U$62,0)),0) | D105: =IFERROR(INDEX($Q$63:$U$83,MATCH(D$103,$A$63:$A$83,0),MATCH($B105,$Q$62:$U$62,0)),0) | E105: =IFERROR(INDEX($Q$63:$U$83,MATCH(E$103,$A$63:$A$83,0),MATCH($B105,$Q$62:$U$62,0)),0) | F105: =IFERROR(INDEX($Q$63:$U$83,MATCH(F$103,$A$63:$A$83,0),MATCH($B105,$Q$62:$U$62,0)),0) | G105: =IFERROR(INDEX($Q$63:$U$83,MATCH(G$103,$A$63:$A$83,0),MATCH($B105,$Q$62:$U$62,0)),0) | H105: =IFERROR(INDEX($Q$63:$U$83,MATCH(H$103,$A$63:$A$83,0),MATCH($B105,$Q$62:$U$62,0)),0) | I105: =IFERROR(INDEX($Q$63:$U$83,MATCH(I$103,$A$63:$A$83,0),MATCH($B105,$Q$62:$U$62,0)),0) | J105: =IFERROR(INDEX($Q$63:$U$83,MATCH(J$103,$A$63:$A$83,0),MATCH($B105,$Q$62:$U$62,0)),0) | ... W105: =IFERROR(INDEX($Q$63:$U$83,MATCH(W$103,$A$63:$A$83,0),MATCH($B105,$Q$62:$U$62,0)),0)
A106: S03 | B106: per_bounced_emi | C106: =IFERROR(INDEX($Q$63:$U$83,MATCH(C$103,$A$63:$A$83,0),MATCH($B106,$Q$62:$U$62,0)),0) | D106: =IFERROR(INDEX($Q$63:$U$83,MATCH(D$103,$A$63:$A$83,0),MATCH($B106,$Q$62:$U$62,0)),0) | E106: =IFERROR(INDEX($Q$63:$U$83,MATCH(E$103,$A$63:$A$83,0),MATCH($B106,$Q$62:$U$62,0)),0) | F106: =IFERROR(INDEX($Q$63:$U$83,MATCH(F$103,$A$63:$A$83,0),MATCH($B106,$Q$62:$U$62,0)),0) | G106: =IFERROR(INDEX($Q$63:$U$83,MATCH(G$103,$A$63:$A$83,0),MATCH($B106,$Q$62:$U$62,0)),0) | H106: =IFERROR(INDEX($Q$63:$U$83,MATCH(H$103,$A$63:$A$83,0),MATCH($B106,$Q$62:$U$62,0)),0) | I106: =IFERROR(INDEX($Q$63:$U$83,MATCH(I$103,$A$63:$A$83,0),MATCH($B106,$Q$62:$U$62,0)),0) | J106: =IFERROR(INDEX($Q$63:$U$83,MATCH(J$103,$A$63:$A$83,0),MATCH($B106,$Q$62:$U$62,0)),0) | ... W106: =IFERROR(INDEX($Q$63:$U$83,MATCH(W$103,$A$63:$A$83,0),MATCH($B106,$Q$62:$U$62,0)),0)
A107: S04 | B107: per_emi | C107: =IFERROR(INDEX($Q$63:$U$83,MATCH(C$103,$A$63:$A$83,0),MATCH($B107,$Q$62:$U$62,0)),0) | D107: =IFERROR(INDEX($Q$63:$U$83,MATCH(D$103,$A$63:$A$83,0),MATCH($B107,$Q$62:$U$62,0)),0) | E107: =IFERROR(INDEX($Q$63:$U$83,MATCH(E$103,$A$63:$A$83,0),MATCH($B107,$Q$62:$U$62,0)),0) | F107: =IFERROR(INDEX($Q$63:$U$83,MATCH(F$103,$A$63:$A$83,0),MATCH($B107,$Q$62:$U$62,0)),0) | G107: =IFERROR(INDEX($Q$63:$U$83,MATCH(G$103,$A$63:$A$83,0),MATCH($B107,$Q$62:$U$62,0)),0) | H107: =IFERROR(INDEX($Q$63:$U$83,MATCH(H$103,$A$63:$A$83,0),MATCH($B107,$Q$62:$U$62,0)),0) | I107: =IFERROR(INDEX($Q$63:$U$83,MATCH(I$103,$A$63:$A$83,0),MATCH($B107,$Q$62:$U$62,0)),0) | J107: =IFERROR(INDEX($Q$63:$U$83,MATCH(J$103,$A$63:$A$83,0),MATCH($B107,$Q$62:$U$62,0)),0) | ... W107: =IFERROR(INDEX($Q$63:$U$83,MATCH(W$103,$A$63:$A$83,0),MATCH($B107,$Q$62:$U$62,0)),0)
A108: S05 | B108: per_loan_month | C108: =IFERROR(INDEX($Q$63:$U$83,MATCH(C$103,$A$63:$A$83,0),MATCH($B108,$Q$62:$U$62,0)),0) | D108: =IFERROR(INDEX($Q$63:$U$83,MATCH(D$103,$A$63:$A$83,0),MATCH($B108,$Q$62:$U$62,0)),0) | E108: =IFERROR(INDEX($Q$63:$U$83,MATCH(E$103,$A$63:$A$83,0),MATCH($B108,$Q$62:$U$62,0)),0) | F108: =IFERROR(INDEX($Q$63:$U$83,MATCH(F$103,$A$63:$A$83,0),MATCH($B108,$Q$62:$U$62,0)),0) | G108: =IFERROR(INDEX($Q$63:$U$83,MATCH(G$103,$A$63:$A$83,0),MATCH($B108,$Q$62:$U$62,0)),0) | H108: =IFERROR(INDEX($Q$63:$U$83,MATCH(H$103,$A$63:$A$83,0),MATCH($B108,$Q$62:$U$62,0)),0) | I108: =IFERROR(INDEX($Q$63:$U$83,MATCH(I$103,$A$63:$A$83,0),MATCH($B108,$Q$62:$U$62,0)),0) | J108: =IFERROR(INDEX($Q$63:$U$83,MATCH(J$103,$A$63:$A$83,0),MATCH($B108,$Q$62:$U$62,0)),0) | ... W108: =IFERROR(INDEX($Q$63:$U$83,MATCH(W$103,$A$63:$A$83,0),MATCH($B108,$Q$62:$U$62,0)),0)
A109: S06 | B109: per_loan_month | C109: =IFERROR(INDEX($Q$63:$U$83,MATCH(C$103,$A$63:$A$83,0),MATCH($B109,$Q$62:$U$62,0)),0) | D109: =IFERROR(INDEX($Q$63:$U$83,MATCH(D$103,$A$63:$A$83,0),MATCH($B109,$Q$62:$U$62,0)),0) | E109: =IFERROR(INDEX($Q$63:$U$83,MATCH(E$103,$A$63:$A$83,0),MATCH($B109,$Q$62:$U$62,0)),0) | F109: =IFERROR(INDEX($Q$63:$U$83,MATCH(F$103,$A$63:$A$83,0),MATCH($B109,$Q$62:$U$62,0)),0) | G109: =IFERROR(INDEX($Q$63:$U$83,MATCH(G$103,$A$63:$A$83,0),MATCH($B109,$Q$62:$U$62,0)),0) | H109: =IFERROR(INDEX($Q$63:$U$83,MATCH(H$103,$A$63:$A$83,0),MATCH($B109,$Q$62:$U$62,0)),0) | I109: =IFERROR(INDEX($Q$63:$U$83,MATCH(I$103,$A$63:$A$83,0),MATCH($B109,$Q$62:$U$62,0)),0) | J109: =IFERROR(INDEX($Q$63:$U$83,MATCH(J$103,$A$63:$A$83,0),MATCH($B109,$Q$62:$U$62,0)),0) | ... W109: =IFERROR(INDEX($Q$63:$U$83,MATCH(W$103,$A$63:$A$83,0),MATCH($B109,$Q$62:$U$62,0)),0)
A110: S07 | B110: per_loan_month | C110: =IFERROR(INDEX($Q$63:$U$83,MATCH(C$103,$A$63:$A$83,0),MATCH($B110,$Q$62:$U$62,0)),0) | D110: =IFERROR(INDEX($Q$63:$U$83,MATCH(D$103,$A$63:$A$83,0),MATCH($B110,$Q$62:$U$62,0)),0) | E110: =IFERROR(INDEX($Q$63:$U$83,MATCH(E$103,$A$63:$A$83,0),MATCH($B110,$Q$62:$U$62,0)),0) | F110: =IFERROR(INDEX($Q$63:$U$83,MATCH(F$103,$A$63:$A$83,0),MATCH($B110,$Q$62:$U$62,0)),0) | G110: =IFERROR(INDEX($Q$63:$U$83,MATCH(G$103,$A$63:$A$83,0),MATCH($B110,$Q$62:$U$62,0)),0) | H110: =IFERROR(INDEX($Q$63:$U$83,MATCH(H$103,$A$63:$A$83,0),MATCH($B110,$Q$62:$U$62,0)),0) | I110: =IFERROR(INDEX($Q$63:$U$83,MATCH(I$103,$A$63:$A$83,0),MATCH($B110,$Q$62:$U$62,0)),0) | J110: =IFERROR(INDEX($Q$63:$U$83,MATCH(J$103,$A$63:$A$83,0),MATCH($B110,$Q$62:$U$62,0)),0) | ... W110: =IFERROR(INDEX($Q$63:$U$83,MATCH(W$103,$A$63:$A$83,0),MATCH($B110,$Q$62:$U$62,0)),0)
A111: S08 | B111: per_loan_year | C111: =IFERROR(INDEX($Q$63:$U$83,MATCH(C$103,$A$63:$A$83,0),MATCH($B111,$Q$62:$U$62,0)),0) | D111: =IFERROR(INDEX($Q$63:$U$83,MATCH(D$103,$A$63:$A$83,0),MATCH($B111,$Q$62:$U$62,0)),0) | E111: =IFERROR(INDEX($Q$63:$U$83,MATCH(E$103,$A$63:$A$83,0),MATCH($B111,$Q$62:$U$62,0)),0) | F111: =IFERROR(INDEX($Q$63:$U$83,MATCH(F$103,$A$63:$A$83,0),MATCH($B111,$Q$62:$U$62,0)),0) | G111: =IFERROR(INDEX($Q$63:$U$83,MATCH(G$103,$A$63:$A$83,0),MATCH($B111,$Q$62:$U$62,0)),0) | H111: =IFERROR(INDEX($Q$63:$U$83,MATCH(H$103,$A$63:$A$83,0),MATCH($B111,$Q$62:$U$62,0)),0) | I111: =IFERROR(INDEX($Q$63:$U$83,MATCH(I$103,$A$63:$A$83,0),MATCH($B111,$Q$62:$U$62,0)),0) | J111: =IFERROR(INDEX($Q$63:$U$83,MATCH(J$103,$A$63:$A$83,0),MATCH($B111,$Q$62:$U$62,0)),0) | ... W111: =IFERROR(INDEX($Q$63:$U$83,MATCH(W$103,$A$63:$A$83,0),MATCH($B111,$Q$62:$U$62,0)),0)
A112: S09 | B112: per_loan_year | C112: =IFERROR(INDEX($Q$63:$U$83,MATCH(C$103,$A$63:$A$83,0),MATCH($B112,$Q$62:$U$62,0)),0) | D112: =IFERROR(INDEX($Q$63:$U$83,MATCH(D$103,$A$63:$A$83,0),MATCH($B112,$Q$62:$U$62,0)),0) | E112: =IFERROR(INDEX($Q$63:$U$83,MATCH(E$103,$A$63:$A$83,0),MATCH($B112,$Q$62:$U$62,0)),0) | F112: =IFERROR(INDEX($Q$63:$U$83,MATCH(F$103,$A$63:$A$83,0),MATCH($B112,$Q$62:$U$62,0)),0) | G112: =IFERROR(INDEX($Q$63:$U$83,MATCH(G$103,$A$63:$A$83,0),MATCH($B112,$Q$62:$U$62,0)),0) | H112: =IFERROR(INDEX($Q$63:$U$83,MATCH(H$103,$A$63:$A$83,0),MATCH($B112,$Q$62:$U$62,0)),0) | I112: =IFERROR(INDEX($Q$63:$U$83,MATCH(I$103,$A$63:$A$83,0),MATCH($B112,$Q$62:$U$62,0)),0) | J112: =IFERROR(INDEX($Q$63:$U$83,MATCH(J$103,$A$63:$A$83,0),MATCH($B112,$Q$62:$U$62,0)),0) | ... W112: =IFERROR(INDEX($Q$63:$U$83,MATCH(W$103,$A$63:$A$83,0),MATCH($B112,$Q$62:$U$62,0)),0)
A113: S10 | B113: per_loan_year | C113: =IFERROR(INDEX($Q$63:$U$83,MATCH(C$103,$A$63:$A$83,0),MATCH($B113,$Q$62:$U$62,0)),0) | D113: =IFERROR(INDEX($Q$63:$U$83,MATCH(D$103,$A$63:$A$83,0),MATCH($B113,$Q$62:$U$62,0)),0) | E113: =IFERROR(INDEX($Q$63:$U$83,MATCH(E$103,$A$63:$A$83,0),MATCH($B113,$Q$62:$U$62,0)),0) | F113: =IFERROR(INDEX($Q$63:$U$83,MATCH(F$103,$A$63:$A$83,0),MATCH($B113,$Q$62:$U$62,0)),0) | G113: =IFERROR(INDEX($Q$63:$U$83,MATCH(G$103,$A$63:$A$83,0),MATCH($B113,$Q$62:$U$62,0)),0) | H113: =IFERROR(INDEX($Q$63:$U$83,MATCH(H$103,$A$63:$A$83,0),MATCH($B113,$Q$62:$U$62,0)),0) | I113: =IFERROR(INDEX($Q$63:$U$83,MATCH(I$103,$A$63:$A$83,0),MATCH($B113,$Q$62:$U$62,0)),0) | J113: =IFERROR(INDEX($Q$63:$U$83,MATCH(J$103,$A$63:$A$83,0),MATCH($B113,$Q$62:$U$62,0)),0) | ... W113: =IFERROR(INDEX($Q$63:$U$83,MATCH(W$103,$A$63:$A$83,0),MATCH($B113,$Q$62:$U$62,0)),0)
A114: S11 | B114: per_loan_year | C114: =IFERROR(INDEX($Q$63:$U$83,MATCH(C$103,$A$63:$A$83,0),MATCH($B114,$Q$62:$U$62,0)),0) | D114: =IFERROR(INDEX($Q$63:$U$83,MATCH(D$103,$A$63:$A$83,0),MATCH($B114,$Q$62:$U$62,0)),0) | E114: =IFERROR(INDEX($Q$63:$U$83,MATCH(E$103,$A$63:$A$83,0),MATCH($B114,$Q$62:$U$62,0)),0) | F114: =IFERROR(INDEX($Q$63:$U$83,MATCH(F$103,$A$63:$A$83,0),MATCH($B114,$Q$62:$U$62,0)),0) | G114: =IFERROR(INDEX($Q$63:$U$83,MATCH(G$103,$A$63:$A$83,0),MATCH($B114,$Q$62:$U$62,0)),0) | H114: =IFERROR(INDEX($Q$63:$U$83,MATCH(H$103,$A$63:$A$83,0),MATCH($B114,$Q$62:$U$62,0)),0) | I114: =IFERROR(INDEX($Q$63:$U$83,MATCH(I$103,$A$63:$A$83,0),MATCH($B114,$Q$62:$U$62,0)),0) | J114: =IFERROR(INDEX($Q$63:$U$83,MATCH(J$103,$A$63:$A$83,0),MATCH($B114,$Q$62:$U$62,0)),0) | ... W114: =IFERROR(INDEX($Q$63:$U$83,MATCH(W$103,$A$63:$A$83,0),MATCH($B114,$Q$62:$U$62,0)),0)
A115: S12 | B115: per_loan_year | C115: =IFERROR(INDEX($Q$63:$U$83,MATCH(C$103,$A$63:$A$83,0),MATCH($B115,$Q$62:$U$62,0)),0) | D115: =IFERROR(INDEX($Q$63:$U$83,MATCH(D$103,$A$63:$A$83,0),MATCH($B115,$Q$62:$U$62,0)),0) | E115: =IFERROR(INDEX($Q$63:$U$83,MATCH(E$103,$A$63:$A$83,0),MATCH($B115,$Q$62:$U$62,0)),0) | F115: =IFERROR(INDEX($Q$63:$U$83,MATCH(F$103,$A$63:$A$83,0),MATCH($B115,$Q$62:$U$62,0)),0) | G115: =IFERROR(INDEX($Q$63:$U$83,MATCH(G$103,$A$63:$A$83,0),MATCH($B115,$Q$62:$U$62,0)),0) | H115: =IFERROR(INDEX($Q$63:$U$83,MATCH(H$103,$A$63:$A$83,0),MATCH($B115,$Q$62:$U$62,0)),0) | I115: =IFERROR(INDEX($Q$63:$U$83,MATCH(I$103,$A$63:$A$83,0),MATCH($B115,$Q$62:$U$62,0)),0) | J115: =IFERROR(INDEX($Q$63:$U$83,MATCH(J$103,$A$63:$A$83,0),MATCH($B115,$Q$62:$U$62,0)),0) | ... W115: =IFERROR(INDEX($Q$63:$U$83,MATCH(W$103,$A$63:$A$83,0),MATCH($B115,$Q$62:$U$62,0)),0)
... A119: S16 | B119: per_closure | C119: =IFERROR(INDEX($Q$63:$U$83,MATCH(C$103,$A$63:$A$83,0),MATCH($B119,$Q$62:$U$62,0)),0) | D119: =IFERROR(INDEX($Q$63:$U$83,MATCH(D$103,$A$63:$A$83,0),MATCH($B119,$Q$62:$U$62,0)),0) | E119: =IFERROR(INDEX($Q$63:$U$83,MATCH(E$103,$A$63:$A$83,0),MATCH($B119,$Q$62:$U$62,0)),0) | F119: =IFERROR(INDEX($Q$63:$U$83,MATCH(F$103,$A$63:$A$83,0),MATCH($B119,$Q$62:$U$62,0)),0) | G119: =IFERROR(INDEX($Q$63:$U$83,MATCH(G$103,$A$63:$A$83,0),MATCH($B119,$Q$62:$U$62,0)),0) | H119: =IFERROR(INDEX($Q$63:$U$83,MATCH(H$103,$A$63:$A$83,0),MATCH($B119,$Q$62:$U$62,0)),0) | I119: =IFERROR(INDEX($Q$63:$U$83,MATCH(I$103,$A$63:$A$83,0),MATCH($B119,$Q$62:$U$62,0)),0) | J119: =IFERROR(INDEX($Q$63:$U$83,MATCH(J$103,$A$63:$A$83,0),MATCH($B119,$Q$62:$U$62,0)),0) | ... W119: =IFERROR(INDEX($Q$63:$U$83,MATCH(W$103,$A$63:$A$83,0),MATCH($B119,$Q$62:$U$62,0)),0)
A122: Collection events per funded loan per driver per journey (derived — do not edit)
A123: Driver ID | B123: Collections driver | C123: personal_loan | D123: co_lending_programme | E123: msme_working_capital | F123: msme_term_loan | G123: professional_practice_loan | H123: secured_business_loan | I123: loan_against_property | J123: home_loan | K123: equipment_machinery_finance | L123: green_equipment_finance | M123: personal_vehicle_loan | N123: commercial_vehicle_finance | O123: gold_loan | P123: education_loan | Q123: agriculture_allied_finance | R123: microfinance_group_lending | S123: consumer_durable_finance | T123: invoice_discounting | U123: purchase_order_finance | V123: supply_chain_finance | W123: trade_finance_workflow
A124: C01 | B124: Tele-collections (dialer, IVR, agent, recording) | C124: =IFERROR('5_Journey_Units_Service'!C24*SUMPRODUCT(INDEX($N$63:$P$83,MATCH(C$123,$A$63:$A$83,0),0),$C$90:$E$90),0) | D124: =IFERROR('5_Journey_Units_Service'!D24*SUMPRODUCT(INDEX($N$63:$P$83,MATCH(D$123,$A$63:$A$83,0),0),$C$90:$E$90),0) | E124: =IFERROR('5_Journey_Units_Service'!E24*SUMPRODUCT(INDEX($N$63:$P$83,MATCH(E$123,$A$63:$A$83,0),0),$C$90:$E$90),0) | F124: =IFERROR('5_Journey_Units_Service'!F24*SUMPRODUCT(INDEX($N$63:$P$83,MATCH(F$123,$A$63:$A$83,0),0),$C$90:$E$90),0) | G124: =IFERROR('5_Journey_Units_Service'!G24*SUMPRODUCT(INDEX($N$63:$P$83,MATCH(G$123,$A$63:$A$83,0),0),$C$90:$E$90),0) | H124: =IFERROR('5_Journey_Units_Service'!H24*SUMPRODUCT(INDEX($N$63:$P$83,MATCH(H$123,$A$63:$A$83,0),0),$C$90:$E$90),0) | I124: =IFERROR('5_Journey_Units_Service'!I24*SUMPRODUCT(INDEX($N$63:$P$83,MATCH(I$123,$A$63:$A$83,0),0),$C$90:$E$90),0) | J124: =IFERROR('5_Journey_Units_Service'!J24*SUMPRODUCT(INDEX($N$63:$P$83,MATCH(J$123,$A$63:$A$83,0),0),$C$90:$E$90),0) | ... W124: =IFERROR('5_Journey_Units_Service'!W24*SUMPRODUCT(INDEX($N$63:$P$83,MATCH(W$123,$A$63:$A$83,0),0),$C$90:$E$90),0)
A125: C02 | B125: Digital collection retry (UPI / link / NACH) | C125: =IFERROR('5_Journey_Units_Service'!C25*SUMPRODUCT(INDEX($N$63:$P$83,MATCH(C$123,$A$63:$A$83,0),0),$C$91:$E$91),0) | D125: =IFERROR('5_Journey_Units_Service'!D25*SUMPRODUCT(INDEX($N$63:$P$83,MATCH(D$123,$A$63:$A$83,0),0),$C$91:$E$91),0) | E125: =IFERROR('5_Journey_Units_Service'!E25*SUMPRODUCT(INDEX($N$63:$P$83,MATCH(E$123,$A$63:$A$83,0),0),$C$91:$E$91),0) | F125: =IFERROR('5_Journey_Units_Service'!F25*SUMPRODUCT(INDEX($N$63:$P$83,MATCH(F$123,$A$63:$A$83,0),0),$C$91:$E$91),0) | G125: =IFERROR('5_Journey_Units_Service'!G25*SUMPRODUCT(INDEX($N$63:$P$83,MATCH(G$123,$A$63:$A$83,0),0),$C$91:$E$91),0) | H125: =IFERROR('5_Journey_Units_Service'!H25*SUMPRODUCT(INDEX($N$63:$P$83,MATCH(H$123,$A$63:$A$83,0),0),$C$91:$E$91),0) | I125: =IFERROR('5_Journey_Units_Service'!I25*SUMPRODUCT(INDEX($N$63:$P$83,MATCH(I$123,$A$63:$A$83,0),0),$C$91:$E$91),0) | J125: =IFERROR('5_Journey_Units_Service'!J25*SUMPRODUCT(INDEX($N$63:$P$83,MATCH(J$123,$A$63:$A$83,0),0),$C$91:$E$91),0) | ... W125: =IFERROR('5_Journey_Units_Service'!W25*SUMPRODUCT(INDEX($N$63:$P$83,MATCH(W$123,$A$63:$A$83,0),0),$C$91:$E$91),0)
A126: C03 | B126: Field collection visit | C126: =IFERROR('5_Journey_Units_Service'!C26*SUMPRODUCT(INDEX($N$63:$P$83,MATCH(C$123,$A$63:$A$83,0),0),$C$92:$E$92),0) | D126: =IFERROR('5_Journey_Units_Service'!D26*SUMPRODUCT(INDEX($N$63:$P$83,MATCH(D$123,$A$63:$A$83,0),0),$C$92:$E$92),0) | E126: =IFERROR('5_Journey_Units_Service'!E26*SUMPRODUCT(INDEX($N$63:$P$83,MATCH(E$123,$A$63:$A$83,0),0),$C$92:$E$92),0) | F126: =IFERROR('5_Journey_Units_Service'!F26*SUMPRODUCT(INDEX($N$63:$P$83,MATCH(F$123,$A$63:$A$83,0),0),$C$92:$E$92),0) | G126: =IFERROR('5_Journey_Units_Service'!G26*SUMPRODUCT(INDEX($N$63:$P$83,MATCH(G$123,$A$63:$A$83,0),0),$C$92:$E$92),0) | H126: =IFERROR('5_Journey_Units_Service'!H26*SUMPRODUCT(INDEX($N$63:$P$83,MATCH(H$123,$A$63:$A$83,0),0),$C$92:$E$92),0) | I126: =IFERROR('5_Journey_Units_Service'!I26*SUMPRODUCT(INDEX($N$63:$P$83,MATCH(I$123,$A$63:$A$83,0),0),$C$92:$E$92),0) | J126: =IFERROR('5_Journey_Units_Service'!J26*SUMPRODUCT(INDEX($N$63:$P$83,MATCH(J$123,$A$63:$A$83,0),0),$C$92:$E$92),0) | ... W126: =IFERROR('5_Journey_Units_Service'!W26*SUMPRODUCT(INDEX($N$63:$P$83,MATCH(W$123,$A$63:$A$83,0),0),$C$92:$E$92),0)
A127: C04 | B127: Agency oversight, roster and invoice handling | C127: =IFERROR('5_Journey_Units_Service'!C27*SUMPRODUCT(INDEX($N$63:$P$83,MATCH(C$123,$A$63:$A$83,0),0),$C$93:$E$93),0) | D127: =IFERROR('5_Journey_Units_Service'!D27*SUMPRODUCT(INDEX($N$63:$P$83,MATCH(D$123,$A$63:$A$83,0),0),$C$93:$E$93),0) | E127: =IFERROR('5_Journey_Units_Service'!E27*SUMPRODUCT(INDEX($N$63:$P$83,MATCH(E$123,$A$63:$A$83,0),0),$C$93:$E$93),0) | F127: =IFERROR('5_Journey_Units_Service'!F27*SUMPRODUCT(INDEX($N$63:$P$83,MATCH(F$123,$A$63:$A$83,0),0),$C$93:$E$93),0) | G127: =IFERROR('5_Journey_Units_Service'!G27*SUMPRODUCT(INDEX($N$63:$P$83,MATCH(G$123,$A$63:$A$83,0),0),$C$93:$E$93),0) | H127: =IFERROR('5_Journey_Units_Service'!H27*SUMPRODUCT(INDEX($N$63:$P$83,MATCH(H$123,$A$63:$A$83,0),0),$C$93:$E$93),0) | I127: =IFERROR('5_Journey_Units_Service'!I27*SUMPRODUCT(INDEX($N$63:$P$83,MATCH(I$123,$A$63:$A$83,0),0),$C$93:$E$93),0) | J127: =IFERROR('5_Journey_Units_Service'!J27*SUMPRODUCT(INDEX($N$63:$P$83,MATCH(J$123,$A$63:$A$83,0),0),$C$93:$E$93),0) | ... W127: =IFERROR('5_Journey_Units_Service'!W27*SUMPRODUCT(INDEX($N$63:$P$83,MATCH(W$123,$A$63:$A$83,0),0),$C$93:$E$93),0)
A128: C05 | B128: Legal case filing and eCourts tracking | C128: =IFERROR('5_Journey_Units_Service'!C28*SUMPRODUCT(INDEX($N$63:$P$83,MATCH(C$123,$A$63:$A$83,0),0),$C$94:$E$94),0) | D128: =IFERROR('5_Journey_Units_Service'!D28*SUMPRODUCT(INDEX($N$63:$P$83,MATCH(D$123,$A$63:$A$83,0),0),$C$94:$E$94),0) | E128: =IFERROR('5_Journey_Units_Service'!E28*SUMPRODUCT(INDEX($N$63:$P$83,MATCH(E$123,$A$63:$A$83,0),0),$C$94:$E$94),0) | F128: =IFERROR('5_Journey_Units_Service'!F28*SUMPRODUCT(INDEX($N$63:$P$83,MATCH(F$123,$A$63:$A$83,0),0),$C$94:$E$94),0) | G128: =IFERROR('5_Journey_Units_Service'!G28*SUMPRODUCT(INDEX($N$63:$P$83,MATCH(G$123,$A$63:$A$83,0),0),$C$94:$E$94),0) | H128: =IFERROR('5_Journey_Units_Service'!H28*SUMPRODUCT(INDEX($N$63:$P$83,MATCH(H$123,$A$63:$A$83,0),0),$C$94:$E$94),0) | I128: =IFERROR('5_Journey_Units_Service'!I28*SUMPRODUCT(INDEX($N$63:$P$83,MATCH(I$123,$A$63:$A$83,0),0),$C$94:$E$94),0) | J128: =IFERROR('5_Journey_Units_Service'!J28*SUMPRODUCT(INDEX($N$63:$P$83,MATCH(J$123,$A$63:$A$83,0),0),$C$94:$E$94),0) | ... W128: =IFERROR('5_Journey_Units_Service'!W28*SUMPRODUCT(INDEX($N$63:$P$83,MATCH(W$123,$A$63:$A$83,0),0),$C$94:$E$94),0)
A129: C06 | B129: Security enforcement (notice, possession, custodian) | C129: =IFERROR('5_Journey_Units_Service'!C29*SUMPRODUCT(INDEX($N$63:$P$83,MATCH(C$123,$A$63:$A$83,0),0),$C$95:$E$95),0) | D129: =IFERROR('5_Journey_Units_Service'!D29*SUMPRODUCT(INDEX($N$63:$P$83,MATCH(D$123,$A$63:$A$83,0),0),$C$95:$E$95),0) | E129: =IFERROR('5_Journey_Units_Service'!E29*SUMPRODUCT(INDEX($N$63:$P$83,MATCH(E$123,$A$63:$A$83,0),0),$C$95:$E$95),0) | F129: =IFERROR('5_Journey_Units_Service'!F29*SUMPRODUCT(INDEX($N$63:$P$83,MATCH(F$123,$A$63:$A$83,0),0),$C$95:$E$95),0) | G129: =IFERROR('5_Journey_Units_Service'!G29*SUMPRODUCT(INDEX($N$63:$P$83,MATCH(G$123,$A$63:$A$83,0),0),$C$95:$E$95),0) | H129: =IFERROR('5_Journey_Units_Service'!H29*SUMPRODUCT(INDEX($N$63:$P$83,MATCH(H$123,$A$63:$A$83,0),0),$C$95:$E$95),0) | I129: =IFERROR('5_Journey_Units_Service'!I29*SUMPRODUCT(INDEX($N$63:$P$83,MATCH(I$123,$A$63:$A$83,0),0),$C$95:$E$95),0) | J129: =IFERROR('5_Journey_Units_Service'!J29*SUMPRODUCT(INDEX($N$63:$P$83,MATCH(J$123,$A$63:$A$83,0),0),$C$95:$E$95),0) | ... W129: =IFERROR('5_Journey_Units_Service'!W29*SUMPRODUCT(INDEX($N$63:$P$83,MATCH(W$123,$A$63:$A$83,0),0),$C$95:$E$95),0)
A130: C07 | B130: Auction (publish, bidder KYC, certificate) | C130: =IFERROR('5_Journey_Units_Service'!C30*SUMPRODUCT(INDEX($N$63:$P$83,MATCH(C$123,$A$63:$A$83,0),0),$C$96:$E$96),0) | D130: =IFERROR('5_Journey_Units_Service'!D30*SUMPRODUCT(INDEX($N$63:$P$83,MATCH(D$123,$A$63:$A$83,0),0),$C$96:$E$96),0) | E130: =IFERROR('5_Journey_Units_Service'!E30*SUMPRODUCT(INDEX($N$63:$P$83,MATCH(E$123,$A$63:$A$83,0),0),$C$96:$E$96),0) | F130: =IFERROR('5_Journey_Units_Service'!F30*SUMPRODUCT(INDEX($N$63:$P$83,MATCH(F$123,$A$63:$A$83,0),0),$C$96:$E$96),0) | G130: =IFERROR('5_Journey_Units_Service'!G30*SUMPRODUCT(INDEX($N$63:$P$83,MATCH(G$123,$A$63:$A$83,0),0),$C$96:$E$96),0) | H130: =IFERROR('5_Journey_Units_Service'!H30*SUMPRODUCT(INDEX($N$63:$P$83,MATCH(H$123,$A$63:$A$83,0),0),$C$96:$E$96),0) | I130: =IFERROR('5_Journey_Units_Service'!I30*SUMPRODUCT(INDEX($N$63:$P$83,MATCH(I$123,$A$63:$A$83,0),0),$C$96:$E$96),0) | J130: =IFERROR('5_Journey_Units_Service'!J30*SUMPRODUCT(INDEX($N$63:$P$83,MATCH(J$123,$A$63:$A$83,0),0),$C$96:$E$96),0) | ... W130: =IFERROR('5_Journey_Units_Service'!W30*SUMPRODUCT(INDEX($N$63:$P$83,MATCH(W$123,$A$63:$A$83,0),0),$C$96:$E$96),0)
A131: C08 | B131: Recovery proceeds handling and GL posting | C131: =IFERROR('5_Journey_Units_Service'!C31*SUMPRODUCT(INDEX($N$63:$P$83,MATCH(C$123,$A$63:$A$83,0),0),$C$97:$E$97),0) | D131: =IFERROR('5_Journey_Units_Service'!D31*SUMPRODUCT(INDEX($N$63:$P$83,MATCH(D$123,$A$63:$A$83,0),0),$C$97:$E$97),0) | E131: =IFERROR('5_Journey_Units_Service'!E31*SUMPRODUCT(INDEX($N$63:$P$83,MATCH(E$123,$A$63:$A$83,0),0),$C$97:$E$97),0) | F131: =IFERROR('5_Journey_Units_Service'!F31*SUMPRODUCT(INDEX($N$63:$P$83,MATCH(F$123,$A$63:$A$83,0),0),$C$97:$E$97),0) | G131: =IFERROR('5_Journey_Units_Service'!G31*SUMPRODUCT(INDEX($N$63:$P$83,MATCH(G$123,$A$63:$A$83,0),0),$C$97:$E$97),0) | H131: =IFERROR('5_Journey_Units_Service'!H31*SUMPRODUCT(INDEX($N$63:$P$83,MATCH(H$123,$A$63:$A$83,0),0),$C$97:$E$97),0) | I131: =IFERROR('5_Journey_Units_Service'!I31*SUMPRODUCT(INDEX($N$63:$P$83,MATCH(I$123,$A$63:$A$83,0),0),$C$97:$E$97),0) | J131: =IFERROR('5_Journey_Units_Service'!J31*SUMPRODUCT(INDEX($N$63:$P$83,MATCH(J$123,$A$63:$A$83,0),0),$C$97:$E$97),0) | ... W131: =IFERROR('5_Journey_Units_Service'!W31*SUMPRODUCT(INDEX($N$63:$P$83,MATCH(W$123,$A$63:$A$83,0),0),$C$97:$E$97),0)
A132: C09 | B132: Repossession and yard management | C132: =IFERROR('5_Journey_Units_Service'!C32*SUMPRODUCT(INDEX($N$63:$P$83,MATCH(C$123,$A$63:$A$83,0),0),$C$98:$E$98),0) | D132: =IFERROR('5_Journey_Units_Service'!D32*SUMPRODUCT(INDEX($N$63:$P$83,MATCH(D$123,$A$63:$A$83,0),0),$C$98:$E$98),0) | E132: =IFERROR('5_Journey_Units_Service'!E32*SUMPRODUCT(INDEX($N$63:$P$83,MATCH(E$123,$A$63:$A$83,0),0),$C$98:$E$98),0) | F132: =IFERROR('5_Journey_Units_Service'!F32*SUMPRODUCT(INDEX($N$63:$P$83,MATCH(F$123,$A$63:$A$83,0),0),$C$98:$E$98),0) | G132: =IFERROR('5_Journey_Units_Service'!G32*SUMPRODUCT(INDEX($N$63:$P$83,MATCH(G$123,$A$63:$A$83,0),0),$C$98:$E$98),0) | H132: =IFERROR('5_Journey_Units_Service'!H32*SUMPRODUCT(INDEX($N$63:$P$83,MATCH(H$123,$A$63:$A$83,0),0),$C$98:$E$98),0) | I132: =IFERROR('5_Journey_Units_Service'!I32*SUMPRODUCT(INDEX($N$63:$P$83,MATCH(I$123,$A$63:$A$83,0),0),$C$98:$E$98),0) | J132: =IFERROR('5_Journey_Units_Service'!J32*SUMPRODUCT(INDEX($N$63:$P$83,MATCH(J$123,$A$63:$A$83,0),0),$C$98:$E$98),0) | ... W132: =IFERROR('5_Journey_Units_Service'!W32*SUMPRODUCT(INDEX($N$63:$P$83,MATCH(W$123,$A$63:$A$83,0),0),$C$98:$E$98),0)

Sheet 7_Cost_Origination
A1: 7 — Origination cost engine
A2: Effective units = units per application x attempts per success x reach at the stage where the driver fires.
A3: Journey | B3: ='1_Inputs'!$B$18
A4: Journey column index | B4: ='1_Inputs'!$B$55
A5: Funnel preset | B5: =INDEX('4_Journey_Units_LOS'!$C$5:$W$5,$B$4)
A6: Funnel column index | B6: =IFERROR(MATCH($B$5,'6_Funnel_And_Lifetime'!$C$4:$G$4,0),1)
A7: Average ticket (₹) | B7: ='1_Inputs'!$B$56
A8: Rate card scenario index | B8: ='1_Inputs'!$B$54
A9: Funded rate | B9: =INDEX('6_Funnel_And_Lifetime'!$C$11:$G$11,$B$6)
A10: Decisioned rate | B10: =INDEX('6_Funnel_And_Lifetime'!$C$8:$G$8,$B$6)
A12: Driver ID | B12: Cost driver | C12: INT ID | D12: Fires at stage | E12: Units per app | F12: Attempts | G12: Stage reach | H12: Effective units / app | I12: Unit cost ₹ | J12: ₹ per application | K12: ₹ per FUNDED loan | L12: Pass-through?
A13: D01 | B13: Mobile/email OTP + delivery (DLT SMS / WhatsApp) | C13: INT-CUS-01 | D13: application_capture | E13: =INDEX('4_Journey_Units_LOS'!$C$8:$W$8,$B$4) | F13: ='2_RateCard_Unit'!$I$5 | G13: =INDEX('6_Funnel_And_Lifetime'!$C$20:$G$20,$B$6) | H13: =E13*F13*G13 | I13: =INDEX('2_RateCard_Unit'!$F$5:$H$5,$B$8) | J13: =H13*I13 | K13: =IFERROR(J13/$B$9,0) | L13: ='2_RateCard_Unit'!$K$5
A14: D02 | B14: Lead capture, dedupe and CRM sync | C14: INT-CUS-02 | D14: application_capture | E14: =INDEX('4_Journey_Units_LOS'!$C$9:$W$9,$B$4) | F14: ='2_RateCard_Unit'!$I$6 | G14: =INDEX('6_Funnel_And_Lifetime'!$C$21:$G$21,$B$6) | H14: =E14*F14*G14 | I14: =INDEX('2_RateCard_Unit'!$F$6:$H$6,$B$8) | J14: =H14*I14 | K14: =IFERROR(J14/$B$9,0) | L14: ='2_RateCard_Unit'!$K$6
A15: D03 | B15: Document upload + malware/DLP scan | C15: INT-CUS-04 | D15: application_capture | E15: =INDEX('4_Journey_Units_LOS'!$C$10:$W$10,$B$4) | F15: ='2_RateCard_Unit'!$I$7 | G15: =INDEX('6_Funnel_And_Lifetime'!$C$22:$G$22,$B$6) | H15: =E15*F15*G15 | I15: =INDEX('2_RateCard_Unit'!$F$7:$H$7,$B$8) | J15: =H15*I15 | K15: =IFERROR(J15/$B$9,0) | L15: ='2_RateCard_Unit'!$K$7
A16: D04 | B16: DigiLocker consent + issued-document fetch | C16: INT-CUS-05 | D16: application_capture | E16: =INDEX('4_Journey_Units_LOS'!$C$11:$W$11,$B$4) | F16: ='2_RateCard_Unit'!$I$8 | G16: =INDEX('6_Funnel_And_Lifetime'!$C$23:$G$23,$B$6) | H16: =E16*F16*G16 | I16: =INDEX('2_RateCard_Unit'!$F$8:$H$8,$B$8) | J16: =H16*I16 | K16: =IFERROR(J16/$B$9,0) | L16: ='2_RateCard_Unit'!$K$8
A17: D05 | B17: Device / SIM / IP fraud signal | C17: INT-LOS-09 | D17: application_capture | E17: =INDEX('4_Journey_Units_LOS'!$C$12:$W$12,$B$4) | F17: ='2_RateCard_Unit'!$I$9 | G17: =INDEX('6_Funnel_And_Lifetime'!$C$24:$G$24,$B$6) | H17: =E17*F17*G17 | I17: =INDEX('2_RateCard_Unit'!$F$9:$H$9,$B$8) | J17: =H17*I17 | K17: =IFERROR(J17/$B$9,0) | L17: ='2_RateCard_Unit'!$K$9
A18: D06 | B18: PAN verification (Protean/NSDL) | C18: INT-LOS-01 | D18: kyc_aml | E18: =INDEX('4_Journey_Units_LOS'!$C$13:$W$13,$B$4) | F18: ='2_RateCard_Unit'!$I$10 | G18: =INDEX('6_Funnel_And_Lifetime'!$C$25:$G$25,$B$6) | H18: =E18*F18*G18 | I18: =INDEX('2_RateCard_Unit'!$F$10:$H$10,$B$8) | J18: =H18*I18 | K18: =IFERROR(J18/$B$9,0) | L18: ='2_RateCard_Unit'!$K$10
A19: D07 | B19: Aadhaar offline XML / QR / KUA eKYC | C19: INT-LOS-01 | D19: kyc_aml | E19: =INDEX('4_Journey_Units_LOS'!$C$14:$W$14,$B$4) | F19: ='2_RateCard_Unit'!$I$11 | G19: =INDEX('6_Funnel_And_Lifetime'!$C$26:$G$26,$B$6) | H19: =E19*F19*G19 | I19: =INDEX('2_RateCard_Unit'!$F$11:$H$11,$B$8) | J19: =H19*I19 | K19: =IFERROR(J19/$B$9,0) | L19: ='2_RateCard_Unit'!$K$11
A20: D08 | B20: CKYC search + record download (CERSAI) | C20: INT-LOS-02 | D20: kyc_aml | E20: =INDEX('4_Journey_Units_LOS'!$C$15:$W$15,$B$4) | F20: ='2_RateCard_Unit'!$I$12 | G20: =INDEX('6_Funnel_And_Lifetime'!$C$27:$G$27,$B$6) | H20: =E20*F20*G20 | I20: =INDEX('2_RateCard_Unit'!$F$12:$H$12,$B$8) | J20: =H20*I20 | K20: =IFERROR(J20/$B$9,0) | L20: ='2_RateCard_Unit'!$K$12
A21: D09 | B21: V-CIP session (platform + agent handling time) | C21: INT-LOS-03 | D21: kyc_aml | E21: =INDEX('4_Journey_Units_LOS'!$C$16:$W$16,$B$4) | F21: ='2_RateCard_Unit'!$I$13 | G21: =INDEX('6_Funnel_And_Lifetime'!$C$28:$G$28,$B$6) | H21: =E21*F21*G21 | I21: =INDEX('2_RateCard_Unit'!$F$13:$H$13,$B$8) | J21: =H21*I21 | K21: =IFERROR(J21/$B$9,0) | L21: ='2_RateCard_Unit'!$K$13
A22: D10 | B22: Liveness / face match / spoof detection | C22: INT-LOS-03 | D22: kyc_aml | E22: =INDEX('4_Journey_Units_LOS'!$C$17:$W$17,$B$4) | F22: ='2_RateCard_Unit'!$I$14 | G22: =INDEX('6_Funnel_And_Lifetime'!$C$29:$G$29,$B$6) | H22: =E22*F22*G22 | I22: =INDEX('2_RateCard_Unit'!$F$14:$H$14,$B$8) | J22: =H22*I22 | K22: =IFERROR(J22/$B$9,0) | L22: ='2_RateCard_Unit'!$K$14
A23: D11 | B23: AML / PEP / sanctions / adverse media screen | C23: INT-LOS-09 | D23: kyc_aml | E23: =INDEX('4_Journey_Units_LOS'!$C$18:$W$18,$B$4) | F23: ='2_RateCard_Unit'!$I$15 | G23: =INDEX('6_Funnel_And_Lifetime'!$C$30:$G$30,$B$6) | H23: =E23*F23*G23 | I23: =INDEX('2_RateCard_Unit'!$F$15:$H$15,$B$8) | J23: =H23*I23 | K23: =IFERROR(J23/$B$9,0) | L23: ='2_RateCard_Unit'!$K$15
A24: D12 | B24: KYB — GSTIN / Udyam / MCA entity verification | C24: INT-LOS-04 | D24: kyc_aml | E24: =INDEX('4_Journey_Units_LOS'!$C$19:$W$19,$B$4) | F24: ='2_RateCard_Unit'!$I$16 | G24: =INDEX('6_Funnel_And_Lifetime'!$C$31:$G$31,$B$6) | H24: =E24*F24*G24 | I24: =INDEX('2_RateCard_Unit'!$F$16:$H$16,$B$8) | J24: =H24*I24 | K24: =IFERROR(J24/$B$9,0) | L24: ='2_RateCard_Unit'!$K$16
A25: D13 | B25: Director / signatory / UBO verification | C25: INT-LOS-04 | D25: kyc_aml | E25: =INDEX('4_Journey_Units_LOS'!$C$20:$W$20,$B$4) | F25: ='2_RateCard_Unit'!$I$17 | G25: =INDEX('6_Funnel_And_Lifetime'!$C$32:$G$32,$B$6) | H25: =E25*F25*G25 | I25: =INDEX('2_RateCard_Unit'!$F$17:$H$17,$B$8) | J25: =H25*I25 | K25: =IFERROR(J25/$B$9,0) | L25: ='2_RateCard_Unit'!$K$17
A26: D14 | B26: Credit bureau — consumer (CIBIL/Experian/Equifax/CRIF) | C26: INT-LOS-06 | D26: specialist_assessment | E26: =INDEX('4_Journey_Units_LOS'!$C$21:$W$21,$B$4) | F26: ='2_RateCard_Unit'!$I$18 | G26: =INDEX('6_Funnel_And_Lifetime'!$C$33:$G$33,$B$6) | H26: =E26*F26*G26 | I26: =INDEX('2_RateCard_Unit'!$F$18:$H$18,$B$8) | J26: =H26*I26 | K26: =IFERROR(J26/$B$9,0) | L26: ='2_RateCard_Unit'!$K$18
A27: D15 | B27: Credit bureau — commercial (CMR / CCR) | C27: INT-LOS-06 | D27: specialist_assessment | E27: =INDEX('4_Journey_Units_LOS'!$C$22:$W$22,$B$4) | F27: ='2_RateCard_Unit'!$I$19 | G27: =INDEX('6_Funnel_And_Lifetime'!$C$34:$G$34,$B$6) | H27: =E27*F27*G27 | I27: =INDEX('2_RateCard_Unit'!$F$19:$H$19,$B$8) | J27: =H27*I27 | K27: =IFERROR(J27/$B$9,0) | L27: ='2_RateCard_Unit'!$K$19
A28: D16 | B28: Account Aggregator consent + FI data fetch | C28: INT-LOS-07 | D28: specialist_assessment | E28: =INDEX('4_Journey_Units_LOS'!$C$23:$W$23,$B$4) | F28: ='2_RateCard_Unit'!$I$20 | G28: =INDEX('6_Funnel_And_Lifetime'!$C$35:$G$35,$B$6) | H28: =E28*F28*G28 | I28: =INDEX('2_RateCard_Unit'!$F$20:$H$20,$B$8) | J28: =H28*I28 | K28: =IFERROR(J28/$B$9,0) | L28: ='2_RateCard_Unit'!$K$20
A29: D17 | B29: Bank statement analysis (parse, tamper, categorise) | C29: INT-LOS-08 | D29: specialist_assessment | E29: =INDEX('4_Journey_Units_LOS'!$C$24:$W$24,$B$4) | F29: ='2_RateCard_Unit'!$I$21 | G29: =INDEX('6_Funnel_And_Lifetime'!$C$36:$G$36,$B$6) | H29: =E29*F29*G29 | I29: =INDEX('2_RateCard_Unit'!$F$21:$H$21,$B$8) | J29: =H29*I29 | K29: =IFERROR(J29/$B$9,0) | L29: ='2_RateCard_Unit'!$K$21
A30: D18 | B30: Income / employment evidence (EPFO, ITR, 26AS, GST) | C30: INT-LOS-05 | D30: specialist_assessment | E30: =INDEX('4_Journey_Units_LOS'!$C$25:$W$25,$B$4) | F30: ='2_RateCard_Unit'!$I$22 | G30: =INDEX('6_Funnel_And_Lifetime'!$C$37:$G$37,$B$6) | H30: =E30*F30*G30 | I30: =INDEX('2_RateCard_Unit'!$F$22:$H$22,$B$8) | J30: =H30*I30 | K30: =IFERROR(J30/$B$9,0) | L30: ='2_RateCard_Unit'!$K$22
A31: D19 | B31: OCR / document extraction + authenticity | C31: INT-LOS-10 | D31: specialist_assessment | E31: =INDEX('4_Journey_Units_LOS'!$C$26:$W$26,$B$4) | F31: ='2_RateCard_Unit'!$I$23 | G31: =INDEX('6_Funnel_And_Lifetime'!$C$38:$G$38,$B$6) | H31: =E31*F31*G31 | I31: =INDEX('2_RateCard_Unit'!$F$23:$H$23,$B$8) | J31: =H31*I31 | K31: =IFERROR(J31/$B$9,0) | L31: ='2_RateCard_Unit'!$K$23
A32: D20 | B32: Field investigation / personal discussion visit | C32: - | D32: specialist_assessment | E32: =INDEX('4_Journey_Units_LOS'!$C$27:$W$27,$B$4) | F32: ='2_RateCard_Unit'!$I$24 | G32: =INDEX('6_Funnel_And_Lifetime'!$C$39:$G$39,$B$6) | H32: =E32*F32*G32 | I32: =INDEX('2_RateCard_Unit'!$F$24:$H$24,$B$8) | J32: =H32*I32 | K32: =IFERROR(J32/$B$9,0) | L32: ='2_RateCard_Unit'!$K$24
A33: D21 | B33: Property valuation report | C33: INT-LOS-13 | D33: specialist_assessment | E33: =INDEX('4_Journey_Units_LOS'!$C$28:$W$28,$B$4) | F33: ='2_RateCard_Unit'!$I$25 | G33: =INDEX('6_Funnel_And_Lifetime'!$C$40:$G$40,$B$6) | H33: =E33*F33*G33 | I33: =INDEX('2_RateCard_Unit'!$F$25:$H$25,$B$8) | J33: =H33*I33 | K33: =IFERROR(J33/$B$9,0) | L33: ='2_RateCard_Unit'!$K$25
A34: D22 | B34: Legal / title search report | C34: INT-LOS-13 | D34: specialist_assessment | E34: =INDEX('4_Journey_Units_LOS'!$C$29:$W$29,$B$4) | F34: ='2_RateCard_Unit'!$I$26 | G34: =INDEX('6_Funnel_And_Lifetime'!$C$41:$G$41,$B$6) | H34: =E34*F34*G34 | I34: =INDEX('2_RateCard_Unit'!$F$26:$H$26,$B$8) | J34: =H34*I34 | K34: =IFERROR(J34/$B$9,0) | L34: ='2_RateCard_Unit'!$K$26
A35: D23 | B35: Asset / vehicle inspection and valuation | C35: INT-LOS-13 | D35: specialist_assessment | E35: =INDEX('4_Journey_Units_LOS'!$C$30:$W$30,$B$4) | F35: ='2_RateCard_Unit'!$I$27 | G35: =INDEX('6_Funnel_And_Lifetime'!$C$42:$G$42,$B$6) | H35: =E35*F35*G35 | I35: =INDEX('2_RateCard_Unit'!$F$27:$H$27,$B$8) | J35: =H35*I35 | K35: =IFERROR(J35/$B$9,0) | L35: ='2_RateCard_Unit'!$K$27
A36: D24 | B36: Gold assay + dual-control custody handling | C36: INT-LOS-13 | D36: specialist_assessment | E36: =INDEX('4_Journey_Units_LOS'!$C$31:$W$31,$B$4) | F36: ='2_RateCard_Unit'!$I$28 | G36: =INDEX('6_Funnel_And_Lifetime'!$C$43:$G$43,$B$6) | H36: =E36*F36*G36 | I36: =INDEX('2_RateCard_Unit'!$F$28:$H$28,$B$8) | J36: =H36*I36 | K36: =IFERROR(J36/$B$9,0) | L36: ='2_RateCard_Unit'!$K$28
A37: D25 | B37: Decision engine evaluation (per-tenant Rust runtime) | C37: - | D37: credit_decision | E37: =INDEX('4_Journey_Units_LOS'!$C$32:$W$32,$B$4) | F37: ='2_RateCard_Unit'!$I$29 | G37: =INDEX('6_Funnel_And_Lifetime'!$C$44:$G$44,$B$6) | H37: =E37*F37*G37 | I37: =INDEX('2_RateCard_Unit'!$F$29:$H$29,$B$8) | J37: =H37*I37 | K37: =IFERROR(J37/$B$9,0) | L37: ='2_RateCard_Unit'!$K$29
A38: D26 | B38: Governed AI / agent tokens and actions | C38: INT-RSK-07 | D38: multiple | E38: =INDEX('4_Journey_Units_LOS'!$C$33:$W$33,$B$4) | F38: ='2_RateCard_Unit'!$I$30 | G38: =INDEX('6_Funnel_And_Lifetime'!$C$45:$G$45,$B$6) | H38: =E38*F38*G38 | I38: =INDEX('2_RateCard_Unit'!$F$30:$H$30,$B$8) | J38: =H38*I38 | K38: =IFERROR(J38/$B$9,0) | L38: ='2_RateCard_Unit'!$K$30
A39: D27 | B39: KFS + sanction letter generation and dispatch | C39: INT-LOS-17 | D39: kfs_acceptance | E39: =INDEX('4_Journey_Units_LOS'!$C$34:$W$34,$B$4) | F39: ='2_RateCard_Unit'!$I$31 | G39: =INDEX('6_Funnel_And_Lifetime'!$C$46:$G$46,$B$6) | H39: =E39*F39*G39 | I39: =INDEX('2_RateCard_Unit'!$F$31:$H$31,$B$8) | J39: =H39*I39 | K39: =IFERROR(J39/$B$9,0) | L39: ='2_RateCard_Unit'!$K$31
A40: D28 | B40: eSign signature (Aadhaar eSign / DSC) | C40: INT-LOS-11 | D40: contracting | E40: =INDEX('4_Journey_Units_LOS'!$C$35:$W$35,$B$4) | F40: ='2_RateCard_Unit'!$I$32 | G40: =INDEX('6_Funnel_And_Lifetime'!$C$47:$G$47,$B$6) | H40: =E40*F40*G40 | I40: =INDEX('2_RateCard_Unit'!$F$32:$H$32,$B$8) | J40: =H40*I40 | K40: =IFERROR(J40/$B$9,0) | L40: ='2_RateCard_Unit'!$K$32
A41: D29 | B41: eStamp facilitation fee (duty itself excluded) | C41: INT-LOS-11 | D41: contracting | E41: =INDEX('4_Journey_Units_LOS'!$C$36:$W$36,$B$4) | F41: ='2_RateCard_Unit'!$I$33 | G41: =INDEX('6_Funnel_And_Lifetime'!$C$48:$G$48,$B$6) | H41: =E41*F41*G41 | I41: =INDEX('2_RateCard_Unit'!$F$33:$H$33,$B$8) | J41: =H41*I41 | K41: =IFERROR(J41/$B$9,0) | L41: ='2_RateCard_Unit'!$K$33
A42: D30 | B42: CERSAI security-interest registration | C42: INT-LOS-14 | D42: contracting | E42: =INDEX('4_Journey_Units_LOS'!$C$37:$W$37,$B$4) | F42: ='2_RateCard_Unit'!$I$34 | G42: =INDEX('6_Funnel_And_Lifetime'!$C$49:$G$49,$B$6) | H42: =E42*F42*G42 | I42: =INDEX('2_RateCard_Unit'!$F$34:$H$34,$B$8) | J42: =H42*I42 | K42: =IFERROR(J42/$B$9,0) | L42: ='2_RateCard_Unit'!$K$34
A43: D31 | B43: Insurance bind / policy issuance handling | C43: INT-LOS-14 | D43: contracting | E43: =INDEX('4_Journey_Units_LOS'!$C$38:$W$38,$B$4) | F43: ='2_RateCard_Unit'!$I$35 | G43: =INDEX('6_Funnel_And_Lifetime'!$C$50:$G$50,$B$6) | H43: =E43*F43*G43 | I43: =INDEX('2_RateCard_Unit'!$F$35:$H$35,$B$8) | J43: =H43*I43 | K43: =IFERROR(J43/$B$9,0) | L43: ='2_RateCard_Unit'!$K$35
A44: D32 | B44: Penny-drop / penny-less bank account verification | C44: INT-LOS-12 | D44: disbursement | E44: =INDEX('4_Journey_Units_LOS'!$C$39:$W$39,$B$4) | F44: ='2_RateCard_Unit'!$I$36 | G44: =INDEX('6_Funnel_And_Lifetime'!$C$51:$G$51,$B$6) | H44: =E44*F44*G44 | I44: =INDEX('2_RateCard_Unit'!$F$36:$H$36,$B$8) | J44: =H44*I44 | K44: =IFERROR(J44/$B$9,0) | L44: ='2_RateCard_Unit'!$K$36
A45: D33 | B45: Disbursement payout (NEFT / RTGS / IMPS API) | C45: INT-LOS-15 | D45: disbursement | E45: =INDEX('4_Journey_Units_LOS'!$C$40:$W$40,$B$4) | F45: ='2_RateCard_Unit'!$I$37 | G45: =INDEX('6_Funnel_And_Lifetime'!$C$52:$G$52,$B$6) | H45: =E45*F45*G45 | I45: =INDEX('2_RateCard_Unit'!$F$37:$H$37,$B$8) | J45: =H45*I45 | K45: =IFERROR(J45/$B$9,0) | L45: ='2_RateCard_Unit'!$K$37
A46: D34 | B46: Escrow / co-lending funding instruction | C46: INT-LOS-16 | D46: disbursement | E46: =INDEX('4_Journey_Units_LOS'!$C$41:$W$41,$B$4) | F46: ='2_RateCard_Unit'!$I$38 | G46: =INDEX('6_Funnel_And_Lifetime'!$C$53:$G$53,$B$6) | H46: =E46*F46*G46 | I46: =INDEX('2_RateCard_Unit'!$F$38:$H$38,$B$8) | J46: =H46*I46 | K46: =IFERROR(J46/$B$9,0) | L46: ='2_RateCard_Unit'!$K$38
A47: D35 | B47: eNACH / eMandate registration (UMRN) | C47: INT-LMS-02 | D47: disbursement | E47: =INDEX('4_Journey_Units_LOS'!$C$42:$W$42,$B$4) | F47: ='2_RateCard_Unit'!$I$39 | G47: =INDEX('6_Funnel_And_Lifetime'!$C$54:$G$54,$B$6) | H47: =E47*F47*G47 | I47: =INDEX('2_RateCard_Unit'!$F$39:$H$39,$B$8) | J47: =H47*I47 | K47: =IFERROR(J47/$B$9,0) | L47: ='2_RateCard_Unit'!$K$39
A48: D36 | B48: Offline field work-pack sync and replay | C48: INT-CUS-07 | D48: application_capture | E48: =INDEX('4_Journey_Units_LOS'!$C$43:$W$43,$B$4) | F48: ='2_RateCard_Unit'!$I$40 | G48: =INDEX('6_Funnel_And_Lifetime'!$C$55:$G$55,$B$6) | H48: =E48*F48*G48 | I48: =INDEX('2_RateCard_Unit'!$F$40:$H$40,$B$8) | J48: =H48*I48 | K48: =IFERROR(J48/$B$9,0) | L48: ='2_RateCard_Unit'!$K$40
A49: D37 | B49: Asset registry verification (VAHAN/RC, depository lien) | C49: INT-COLAT-01 | D49: specialist_assessment | E49: =INDEX('4_Journey_Units_LOS'!$C$44:$W$44,$B$4) | F49: ='2_RateCard_Unit'!$I$41 | G49: =INDEX('6_Funnel_And_Lifetime'!$C$56:$G$56,$B$6) | H49: =E49*F49*G49 | I49: =INDEX('2_RateCard_Unit'!$F$41:$H$41,$B$8) | J49: =H49*I49 | K49: =IFERROR(J49/$B$9,0) | L49: ='2_RateCard_Unit'!$K$41
A50: D38 | B50: Agent knowledge retrieval (vector query) | C50: INT-RSK-08 | D50: multiple | E50: =INDEX('4_Journey_Units_LOS'!$C$45:$W$45,$B$4) | F50: ='2_RateCard_Unit'!$I$42 | G50: =INDEX('6_Funnel_And_Lifetime'!$C$57:$G$57,$B$6) | H50: =E50*F50*G50 | I50: =INDEX('2_RateCard_Unit'!$F$42:$H$42,$B$8) | J50: =H50*I50 | K50: =IFERROR(J50/$B$9,0) | L50: ='2_RateCard_Unit'!$K$42
B52: TOTAL ORIGINATION EXTERNAL COST | J52: =SUM(J13:J50) | K52: =SUM(K13:K50)
B53: of which platform-borne | J53: =SUMIF($L$13:$L$50,"No",J13:J50) | K53: =SUMIF($L$13:$L$50,"No",K13:K50)
B54: of which pass-through | J54: =SUMIF($L$13:$L$50,"Yes",J13:J50) | K54: =SUMIF($L$13:$L$50,"Yes",K13:K50)
B56: Origination cost per funded loan as bps of ticket | K56: =IFERROR(K52/$B$7*10000,0)
B57: Largest single driver | D57: =INDEX($B$13:$B$50,MATCH(MAX(K13:K50),K13:K50,0)) | K57: =MAX(K13:K50)
B59: The gap between column J and column K is the funnel tax: verification you pay for on applications that never fund.

Sheet 8_Cost_Servicing
A1: 8 — Servicing, closure and collections cost engine
A2: Cost per funded loan over its WHOLE LIFE. Servicing units are multiplied by the basis quantity the loan generates (loan-months, EMIs, loan-years, one closure); collections events come from the delinquency profile.
A3: Journey | B3: ='1_Inputs'!$B$18
A4: Journey column index | B4: ='1_Inputs'!$B$55
A5: Lifetime row index | B5: =IFERROR(MATCH($B$3,'6_Funnel_And_Lifetime'!$A$63:$A$83,0),1)
A6: Rate card scenario index | B6: ='1_Inputs'!$B$54
A7: Effective life (months) | B7: =INDEX('6_Funnel_And_Lifetime'!$E$63:$E$83,$B$5)
A8: Effective life (years) | B8: =INDEX('6_Funnel_And_Lifetime'!$F$63:$F$83,$B$5)
A9: EMI count over life | B9: =INDEX('6_Funnel_And_Lifetime'!$H$63:$H$83,$B$5)
A10: Bounced EMIs over life | B10: =INDEX('6_Funnel_And_Lifetime'!$J$63:$J$83,$B$5)
A11: Delinquent loan-months (all buckets) | B11: =INDEX('6_Funnel_And_Lifetime'!$N$63:$N$83,$B$5)+INDEX('6_Funnel_And_Lifetime'!$O$63:$O$83,$B$5)+INDEX('6_Funnel_And_Lifetime'!$P$63:$P$83,$B$5)
A14: Driver ID | B14: Cost driver | C14: INT ID | D14: Basis | E14: Units per basis-unit | F14: Basis qty over life | G14: Attempts | H14: Unit cost ₹ | I14: ₹ per FUNDED loan (lifetime) | J14: Pass-through?
A15: S01 | B15: CBS / GL posting and acknowledgement | C15: INT-LMS-01 | D15: per_loan_month | E15: =INDEX('5_Journey_Units_Service'!$C$6:$W$6,$B$4) | F15: =INDEX('6_Funnel_And_Lifetime'!$C$104:$W$104,$B$4) | G15: ='2_RateCard_Unit'!$I$43 | H15: =INDEX('2_RateCard_Unit'!$F$43:$H$43,$B$6) | I15: =E15*F15*G15*H15 | J15: ='2_RateCard_Unit'!$K$43
A16: S02 | B16: NACH / eNACH presentment | C16: INT-LMS-03 | D16: per_emi | E16: =INDEX('5_Journey_Units_Service'!$C$7:$W$7,$B$4) | F16: =INDEX('6_Funnel_And_Lifetime'!$C$105:$W$105,$B$4) | G16: ='2_RateCard_Unit'!$I$44 | H16: =INDEX('2_RateCard_Unit'!$F$44:$H$44,$B$6) | I16: =E16*F16*G16*H16 | J16: ='2_RateCard_Unit'!$K$44
A17: S03 | B17: Bounce / return handling | C17: INT-LMS-03 | D17: per_bounced_emi | E17: =INDEX('5_Journey_Units_Service'!$C$8:$W$8,$B$4) | F17: =INDEX('6_Funnel_And_Lifetime'!$C$106:$W$106,$B$4) | G17: ='2_RateCard_Unit'!$I$45 | H17: =INDEX('2_RateCard_Unit'!$F$45:$H$45,$B$6) | I17: =E17*F17*G17*H17 | J17: ='2_RateCard_Unit'!$K$45
A18: S04 | B18: Receipt matching and reconciliation (UTR) | C18: INT-LMS-04 | D18: per_emi | E18: =INDEX('5_Journey_Units_Service'!$C$9:$W$9,$B$4) | F18: =INDEX('6_Funnel_And_Lifetime'!$C$107:$W$107,$B$4) | G18: ='2_RateCard_Unit'!$I$46 | H18: =INDEX('2_RateCard_Unit'!$F$46:$H$46,$B$6) | I18: =E18*F18*G18*H18 | J18: ='2_RateCard_Unit'!$K$46
A19: S05 | B19: Servicing notices (EMI, rate, penal, statement) | C19: INT-LMS-06 | D19: per_loan_month | E19: =INDEX('5_Journey_Units_Service'!$C$10:$W$10,$B$4) | F19: =INDEX('6_Funnel_And_Lifetime'!$C$108:$W$108,$B$4) | G19: ='2_RateCard_Unit'!$I$47 | H19: =INDEX('2_RateCard_Unit'!$F$47:$H$47,$B$6) | I19: =E19*F19*G19*H19 | J19: ='2_RateCard_Unit'!$K$47
A20: S06 | B20: Statement render, vault store and retention | C20: INT-LMS-07 | D20: per_loan_month | E20: =INDEX('5_Journey_Units_Service'!$C$11:$W$11,$B$4) | F20: =INDEX('6_Funnel_And_Lifetime'!$C$109:$W$109,$B$4) | G20: ='2_RateCard_Unit'!$I$48 | H20: =INDEX('2_RateCard_Unit'!$F$48:$H$48,$B$6) | I20: =E20*F20*G20*H20 | J20: ='2_RateCard_Unit'!$K$48
A21: S07 | B21: CIC credit furnishing (monthly submission) | C21: INT-LMS-08 | D21: per_loan_month | E21: =INDEX('5_Journey_Units_Service'!$C$12:$W$12,$B$4) | F21: =INDEX('6_Funnel_And_Lifetime'!$C$110:$W$110,$B$4) | G21: ='2_RateCard_Unit'!$I$49 | H21: =INDEX('2_RateCard_Unit'!$F$49:$H$49,$B$6) | I21: =E21*F21*G21*H21 | J21: ='2_RateCard_Unit'!$K$49
A22: S08 | B22: Ongoing KYC refresh / AA re-consent | C22: INT-LMS-09 | D22: per_loan_year | E22: =INDEX('5_Journey_Units_Service'!$C$13:$W$13,$B$4) | F22: =INDEX('6_Funnel_And_Lifetime'!$C$111:$W$111,$B$4) | G22: ='2_RateCard_Unit'!$I$50 | H22: =INDEX('2_RateCard_Unit'!$F$50:$H$50,$B$6) | I22: =E22*F22*G22*H22 | J22: ='2_RateCard_Unit'!$K$50
A23: S09 | B23: Portfolio bureau review | C23: INT-LMS-09 | D23: per_loan_year | E23: =INDEX('5_Journey_Units_Service'!$C$14:$W$14,$B$4) | F23: =INDEX('6_Funnel_And_Lifetime'!$C$112:$W$112,$B$4) | G23: ='2_RateCard_Unit'!$I$51 | H23: =INDEX('2_RateCard_Unit'!$F$51:$H$51,$B$6) | I23: =E23*F23*G23*H23 | J23: ='2_RateCard_Unit'!$K$51
A24: S10 | B24: Ongoing AML rescreen | C24: INT-LMS-09 | D24: per_loan_year | E24: =INDEX('5_Journey_Units_Service'!$C$15:$W$15,$B$4) | F24: =INDEX('6_Funnel_And_Lifetime'!$C$113:$W$113,$B$4) | G24: ='2_RateCard_Unit'!$I$52 | H24: =INDEX('2_RateCard_Unit'!$F$52:$H$52,$B$6) | I24: =E24*F24*G24*H24 | J24: ='2_RateCard_Unit'!$K$52
A25: S11 | B25: Insurance renewal / collateral revaluation | C25: INT-LMS-10 | D25: per_loan_year | E25: =INDEX('5_Journey_Units_Service'!$C$16:$W$16,$B$4) | F25: =INDEX('6_Funnel_And_Lifetime'!$C$114:$W$114,$B$4) | G25: ='2_RateCard_Unit'!$I$53 | H25: =INDEX('2_RateCard_Unit'!$F$53:$H$53,$B$6) | I25: =E25*F25*G25*H25 | J25: ='2_RateCard_Unit'!$K$53
A26: S12 | B26: Refund / excess / failed-disbursement reversal | C26: INT-LMS-05 | D26: per_loan_year | E26: =INDEX('5_Journey_Units_Service'!$C$17:$W$17,$B$4) | F26: =INDEX('6_Funnel_And_Lifetime'!$C$115:$W$115,$B$4) | G26: ='2_RateCard_Unit'!$I$54 | H26: =INDEX('2_RateCard_Unit'!$F$54:$H$54,$B$6) | I26: =E26*F26*G26*H26 | J26: ='2_RateCard_Unit'!$K$54
A27: S13 | B27: Restructure / transfer instruction | C27: INT-LMS-11 | D27: per_loan_year | E27: =INDEX('5_Journey_Units_Service'!$C$18:$W$18,$B$4) | F27: =INDEX('6_Funnel_And_Lifetime'!$C$116:$W$116,$B$4) | G27: ='2_RateCard_Unit'!$I$55 | H27: =INDEX('2_RateCard_Unit'!$F$55:$H$55,$B$6) | I27: =E27*F27*G27*H27 | J27: ='2_RateCard_Unit'!$K$55
A28: S14 | B28: Closure: mandate cancel, NOC generation and delivery | C28: INT-LMS-12 | D28: per_closure | E28: =INDEX('5_Journey_Units_Service'!$C$19:$W$19,$B$4) | F28: =INDEX('6_Funnel_And_Lifetime'!$C$117:$W$117,$B$4) | G28: ='2_RateCard_Unit'!$I$56 | H28: =INDEX('2_RateCard_Unit'!$F$56:$H$56,$B$6) | I28: =E28*F28*G28*H28 | J28: ='2_RateCard_Unit'!$K$56
A29: S15 | B29: Security registry satisfaction (CERSAI / ROC / RTO) | C29: INT-COLAT-04 | D29: per_closure | E29: =INDEX('5_Journey_Units_Service'!$C$20:$W$20,$B$4) | F29: =INDEX('6_Funnel_And_Lifetime'!$C$118:$W$118,$B$4) | G29: ='2_RateCard_Unit'!$I$57 | H29: =INDEX('2_RateCard_Unit'!$F$57:$H$57,$B$6) | I29: =E29*F29*G29*H29 | J29: ='2_RateCard_Unit'!$K$57
A30: S16 | B30: Custody return and release acknowledgement | C30: INT-COLAT-06 | D30: per_closure | E30: =INDEX('5_Journey_Units_Service'!$C$21:$W$21,$B$4) | F30: =INDEX('6_Funnel_And_Lifetime'!$C$119:$W$119,$B$4) | G30: ='2_RateCard_Unit'!$I$58 | H30: =INDEX('2_RateCard_Unit'!$F$58:$H$58,$B$6) | I30: =E30*F30*G30*H30 | J30: ='2_RateCard_Unit'!$K$58
B31: Lifetime SERVICING cost per funded loan | I31: =SUM(I15:I30)
A33: Driver ID | B33: Collections driver | C33: INT ID | D33: Basis | E33: Applicability | F33: Events per funded loan | G33: Attempts | H33: Unit cost ₹ | I33: ₹ per FUNDED loan (lifetime) | J33: Pass-through?
A34: C01 | B34: Tele-collections (dialer, IVR, agent, recording) | C34: INT-COL-01 | D34: per_collection_event | E34: =INDEX('5_Journey_Units_Service'!$C$24:$W$24,$B$4) | F34: =INDEX('6_Funnel_And_Lifetime'!$C$124:$W$124,$B$4) | G34: ='2_RateCard_Unit'!$I$59 | H34: =INDEX('2_RateCard_Unit'!$F$59:$H$59,$B$6) | I34: =F34*G34*H34 | J34: ='2_RateCard_Unit'!$K$59
A35: C02 | B35: Digital collection retry (UPI / link / NACH) | C35: INT-COL-02 | D35: per_collection_event | E35: =INDEX('5_Journey_Units_Service'!$C$25:$W$25,$B$4) | F35: =INDEX('6_Funnel_And_Lifetime'!$C$125:$W$125,$B$4) | G35: ='2_RateCard_Unit'!$I$60 | H35: =INDEX('2_RateCard_Unit'!$F$60:$H$60,$B$6) | I35: =F35*G35*H35 | J35: ='2_RateCard_Unit'!$K$60
A36: C03 | B36: Field collection visit | C36: INT-COL-03 | D36: per_collection_event | E36: =INDEX('5_Journey_Units_Service'!$C$26:$W$26,$B$4) | F36: =INDEX('6_Funnel_And_Lifetime'!$C$126:$W$126,$B$4) | G36: ='2_RateCard_Unit'!$I$61 | H36: =INDEX('2_RateCard_Unit'!$F$61:$H$61,$B$6) | I36: =F36*G36*H36 | J36: ='2_RateCard_Unit'!$K$61
A37: C04 | B37: Agency oversight, roster and invoice handling | C37: INT-COL-04 | D37: per_collection_event | E37: =INDEX('5_Journey_Units_Service'!$C$27:$W$27,$B$4) | F37: =INDEX('6_Funnel_And_Lifetime'!$C$127:$W$127,$B$4) | G37: ='2_RateCard_Unit'!$I$62 | H37: =INDEX('2_RateCard_Unit'!$F$62:$H$62,$B$6) | I37: =F37*G37*H37 | J37: ='2_RateCard_Unit'!$K$62
A38: C05 | B38: Legal case filing and eCourts tracking | C38: INT-COL-05 | D38: per_collection_event | E38: =INDEX('5_Journey_Units_Service'!$C$28:$W$28,$B$4) | F38: =INDEX('6_Funnel_And_Lifetime'!$C$128:$W$128,$B$4) | G38: ='2_RateCard_Unit'!$I$63 | H38: =INDEX('2_RateCard_Unit'!$F$63:$H$63,$B$6) | I38: =F38*G38*H38 | J38: ='2_RateCard_Unit'!$K$63
A39: C06 | B39: Security enforcement (notice, possession, custodian) | C39: INT-COL-06 | D39: per_collection_event | E39: =INDEX('5_Journey_Units_Service'!$C$29:$W$29,$B$4) | F39: =INDEX('6_Funnel_And_Lifetime'!$C$129:$W$129,$B$4) | G39: ='2_RateCard_Unit'!$I$64 | H39: =INDEX('2_RateCard_Unit'!$F$64:$H$64,$B$6) | I39: =F39*G39*H39 | J39: ='2_RateCard_Unit'!$K$64
A40: C07 | B40: Auction (publish, bidder KYC, certificate) | C40: INT-COL-07 | D40: per_collection_event | E40: =INDEX('5_Journey_Units_Service'!$C$30:$W$30,$B$4) | F40: =INDEX('6_Funnel_And_Lifetime'!$C$130:$W$130,$B$4) | G40: ='2_RateCard_Unit'!$I$65 | H40: =INDEX('2_RateCard_Unit'!$F$65:$H$65,$B$6) | I40: =F40*G40*H40 | J40: ='2_RateCard_Unit'!$K$65
A41: C08 | B41: Recovery proceeds handling and GL posting | C41: INT-COL-08 | D41: per_collection_event | E41: =INDEX('5_Journey_Units_Service'!$C$31:$W$31,$B$4) | F41: =INDEX('6_Funnel_And_Lifetime'!$C$131:$W$131,$B$4) | G41: ='2_RateCard_Unit'!$I$66 | H41: =INDEX('2_RateCard_Unit'!$F$66:$H$66,$B$6) | I41: =F41*G41*H41 | J41: ='2_RateCard_Unit'!$K$66
A42: C09 | B42: Repossession and yard management | C42: INT-COLAT-07 | D42: per_collection_event | E42: =INDEX('5_Journey_Units_Service'!$C$32:$W$32,$B$4) | F42: =INDEX('6_Funnel_And_Lifetime'!$C$132:$W$132,$B$4) | G42: ='2_RateCard_Unit'!$I$67 | H42: =INDEX('2_RateCard_Unit'!$F$67:$H$67,$B$6) | I42: =F42*G42*H42 | J42: ='2_RateCard_Unit'!$K$67
B43: Lifetime COLLECTIONS cost per funded loan | E43: Applicability is shown for information; it is already baked into the events column. | I43: =SUM(I34:I42)
B45: TOTAL POST-ORIGINATION COST PER FUNDED LOAN | I45: =I31+I43
B46: of which platform-borne | I46: =SUMIF($J$15:$J$30,"No",I15:I30)+SUMIF($J$34:$J$42,"No",I34:I42)
B47: of which pass-through | I47: =SUMIF($J$15:$J$30,"Yes",I15:I30)+SUMIF($J$34:$J$42,"Yes",I34:I42)
B48: Cost per ACTIVE LOAN-MONTH | I48: =IFERROR(I45/$B$7,0)
B50: Compare the per-active-loan-month figure against the LMS fee on sheet 1. A servicing fee below this number means every month the loan stays on the book destroys value — and long-tenor journeys stay a long time.

Sheet 9_Cloud_Cost
A1: 9 — Cloud infrastructure cost per tenant
A2: The 17 REQUIRED_DEPLOYMENT_COMPONENTS from saas-deployment-blueprints.js across the 4 SAAS_DEPLOYMENT_MODELS. ₹ per month, per tenant, volume-independent.
A4: Deployment component | B4: Tier | C4: shared_multi_tenant | D4: dedicated_tenant_data_plane | E4: dedicated_environment | F4: customer_managed_private | G4: Note
A5: tenant_namespace | C5: 0 | D5: 0 | E5: 0 | F5: 0 | G5: Logical only; no standalone infrastructure charge.
A6: app_partition | C6: 1200 | D6: 2600 | E6: 22000 | F6: 0 | G6: Share of the app fleet; dedicated ASG in dedicated_environment.
A7: data_partition | C7: 400 | D7: 1200 | E7: 3000 | F7: 0 | G7: Schema/partition overhead and per-tenant object prefixes.
A8: database_isolation | C8: 2500 | D8: 32000 | E8: 55000 | F8: 0 | G8: Shared RDS+RLS allocation vs a dedicated Multi-AZ instance.
A9: decision_runtime | C9: 9000 | D9: 12000 | E9: 18000 | F9: 9000 | G9: ADR 0003: one ISOLATED Rust runtime per tenant. Never shared -> a true per-tenant floor even at zero volume.
A10: keys_secrets | C10: 700 | D10: 1100 | E10: 2200 | F10: 700 | G10: Per-tenant KMS CMKs + secret scopes.
A11: network_domain_certificates | C11: 600 | D11: 1400 | E11: 6500 | F11: 400 | G11: Routes, custom domain, TLS certificates, WAF share.
A12: storage_worm | C12: 0 | D12: 0 | E12: 0 | F12: 0 | G12: Driven by the retention model below, not a flat fee.
A13: queue_workers | C13: 900 | D13: 1800 | E13: 7000 | F13: 0 | G13: Per-tenant queues and worker capacity floor.
A14: integrations | C14: 500 | D14: 900 | E14: 2500 | F14: 500 | G14: NAT/egress, allowlists, provider connection floor.
A15: monitoring_siem | C15: 1800 | D15: 3200 | E15: 9000 | F15: 2500 | G15: Log ingest and retention. Usually underestimated.
A16: backups_pitr_dr | C16: 1500 | D16: 4500 | E16: 16000 | F16: 0 | G16: PITR window, cross-AZ/region copies, restore tests.
... A21: portability_exit | C21: 300 | D21: 600 | E21: 1500 | F21: 600 | G21: Export tooling and exit rehearsal capacity.
A22: Subtotal — fixed ₹ per month | C22: =SUM(C5:C21) | D22: =SUM(D5:D21) | E22: =SUM(E5:E21) | F22: =SUM(F5:F21)
A24: Variable ₹ per 1,000 applications | C24: 1100 | D24: 1400 | E24: 1900 | F24: 150 | G24: Marginal compute, DB IOPS, egress and log ingest. Excludes retained storage (below).
A26: Selected deployment model
A27: Selected model | C27: ='1_Inputs'!$B$13
A28: Model index | C28: ='1_Inputs'!$B$52
A29: Fixed cloud ₹/month (selected) | C29: =INDEX($C$22:$F$22,$C$28)
A30: Variable cloud ₹ per 1,000 apps (selected) | C30: =INDEX($C$24:$F$24,$C$28)
A33: Retained-evidence storage — this cost COMPOUNDS
A34: RBI/PMLA retention means documents, V-CIP recordings, statements and the audit hash chain accumulate. Storage cost rises every year even at flat volume, and servicing adds a monthly statement stream for the whole life of every loan.
A36: MB retained per dropped application | C36: 8 | G36: Docs and bureau reports pulled on files that never funded — still retained.
A37: MB retained per funded loan (origination) | C37: 45 | G37: Dominated by the V-CIP recording and the signed contract packet.
A38: MB retained per active loan-year (servicing) | C38: 6 | G38: Statements, notices, receipts, CIC submissions and collections evidence.
A39: Retention years | C39: 8 | G39: Model the longest applicable obligation, not the shortest.
A40: ₹ per GB-month (blended hot→archive) | C40: 1.2 | G40: Blended across S3 Standard, IA and Glacier with Object Lock.
A41: Annual applications started | C41: ='1_Inputs'!$B$19*12
A42: Annual funded loans | C42: =$C$41*'7_Cost_Origination'!$B$9
A43: Active loans (from the book model) | C43: ='12_Tenant_PnL'!$B$19
A44: GB added per year | C44: =(($C$41-$C$42)*$C$36+$C$42*$C$37+$C$43*$C$38)/1024
A46: Year | B46: Cumulative GB retained | C46: Storage ₹ per year | D46: Storage ₹ per month
A47: 1 | B47: =$C$44*A47 | C47: =B47*$C$40*12 | D47: =C47/12
A48: 2 | B48: =$C$44*A48 | C48: =B48*$C$40*12 | D48: =C48/12
A49: 3 | B49: =$C$44*A49 | C49: =B49*$C$40*12 | D49: =C49/12
A50: 4 | B50: =$C$44*A50 | C50: =B50*$C$40*12 | D50: =C50/12
A51: 5 | B51: =$C$44*A51 | C51: =B51*$C$40*12 | D51: =C51/12
A52: 6 | B52: =$C$44*A52 | C52: =B52*$C$40*12 | D52: =C52/12
A53: 7 | B53: =$C$44*A53 | C53: =B53*$C$40*12 | D53: =C53/12
A54: 8 | B54: =$C$44*A54 | C54: =B54*$C$40*12 | D54: =C54/12
A56: Year 1 storage ₹/year | C56: =C47
A57: Year 8 storage ₹/year | C57: =C54
A58: Multiple, year 1 → final year | C58: =IFERROR(C54/C47,0) | G58: Price a multi-year contract against the AVERAGE of these years, not year 1.

Sheet 10_Governance_Cost
A1: 10 — Governance, compliance and regulatory cost
A2: Platform-level fixed cost that exists because we are a compliance-first lending platform. It must be allocated; the basis materially changes which tenants look profitable.
A4: Governance / regulatory cost item | B4: ₹ per year (platform) | C4: Note
A5: VAPT and application security testing | B5: 800000 | C5: Annual + per-major-release retest.
A6: ISO 27001 + SOC 2 Type II certification | B6: 1400000 | C6: Audit fees, tooling and internal effort.
A7: RBI IS / system audit support | B7: 600000 | C7: Evidence packs and auditor response for regulated tenants.
A8: DPDP compliance, consent manager and DPO | B8: 1800000 | C8: Digital Personal Data Protection Act obligations.
A9: Compliance officer + regulatory change tracking | B9: 3600000 | C9: RBI Digital Lending Directions change absorption.
A10: Model governance, validation, bias and drift | B10: 2400000 | C10: DEC-4 provenance + kill-switch operation.
A11: Audit hash chain and evidence retention tooling | B11: 600000 | C11: INV-8/INV-12 replayability infrastructure.
A12: Regulatory reporting ops (CIC/CKYC/FIU/CERSAI) | B12: 2000000 | C12: Submission, acknowledgement and reconciliation runs.
A13: Business continuity and DR drills | B13: 500000 | C13: Documented restore and failover rehearsals.
A14: Cyber and professional indemnity insurance | B14: 900000 | C14: Scales with tenant count and data volume.
A15: TOTAL platform governance cost ₹/year | B15: =SUM(B5:B14)
A17: Allocation to this tenant
A18: Live tenants on platform | B18: ='1_Inputs'!$B$9 | C18: More tenants = lower fixed cost each. Early tenants are structurally expensive.
A19: Platform annual funded loans (all tenants) | B19: ='1_Inputs'!$B$10 | C19: Denominator for volume-weighted allocation.
A20: This tenant annual funded loans | B20: ='9_Cloud_Cost'!$C$42 | C20: From the funnel and volume inputs.
A21: Equal-share allocation ₹/yr | B21: =IFERROR($B$15/$B$18,0) | C21: Compliance effort is largely per-tenant, not per-loan.
A22: Volume-weighted allocation ₹/yr | B22: =IFERROR($B$15*$B$20/$B$19,0) | C22: Reporting and monitoring effort scales with loan count.
A23: Allocation basis | B23: ='1_Inputs'!$B$15 | C23: Blended 50/50 is the recommended default — neither pure basis is honest alone.
A24: Allocated governance cost ₹/yr | B24: =IF($B$23="Equal per tenant",$B$21,IF($B$23="Volume weighted",$B$22,0.5*$B$21+0.5*$B$22))
A26: Direct regulatory operating cost caused by this tenant
A27: Direct regulatory ops ₹/month | B27: 18000 | C27: Tenant-specific report runs, submissions, regulator queries and evidence packs. The reporting RAILS themselves are priced as recurring drivers R15-R22 on sheet 3.
A28: Direct regulatory ₹ per 1,000 funded loans | B28: 4500 | C28: Submission, acknowledgement and reconciliation effort that scales with volume.
A29: Direct regulatory cost ₹/yr | B29: =$B$27*12+$B$28*$B$20/1000
A31: TOTAL governance + regulatory ₹/yr for this tenant | B31: =$B$24+$B$29

Sheet 11_Service_Cost
A1: 11 — Service, support and onboarding cost
A2: Human cost of running the tenant. Onboarding is the most commonly under-recovered line in lending SaaS.
A4: # | B4: Support tier | C4: ₹ per month | D4: Included scope
A5: 1 | B5: Standard | C5: 35000 | D5: Business-hours L1/L2, shared queue, 8-hour P1 response, quarterly review.
A6: 2 | B6: Enhanced | C6: 90000 | D6: Extended-hours L1/L2/L3, named CSM, 2-hour P1 response, monthly review, 4 policy config changes/quarter.
A7: 3 | B7: Dedicated | C7: 240000 | D7: 24x7 dedicated pod, 30-minute P1 response, embedded solution engineer, unlimited policy config changes.
A9: # | B9: Deployment model | C9: Implementation cost ₹ (one time) | D9: Note
A10: 1 | B10: shared_multi_tenant | C10: 400000 | D10: Provision into the shared plane; tenant config, policy bundle, entitlements, UAT.
A11: 2 | B11: dedicated_tenant_data_plane | C11: 900000 | D11: Adds dedicated database provisioning, isolation evidence and restore rehearsal.
A12: 3 | B12: dedicated_environment | C12: 1800000 | D12: Full dedicated environment build, network, domains, DR design and acceptance.
A13: 4 | B13: customer_managed_private | C13: 2500000 | D13: Customer-managed install: their infra, our runbooks — heaviest coordination cost.
A16: Selected for this deal
B17: Selected support tier | C17: ='1_Inputs'!$B$14
B18: Support ₹/month | C18: =INDEX($C$5:$C$7,'1_Inputs'!$B$53)
B19: Implementation cost ₹ | C19: =INDEX($C$10:$C$13,'1_Inputs'!$B$52)
B20: Admission / due-diligence cost ₹ (INT-ADM-*) | C20: ='3_RateCard_Recurring'!$L$55 | D20: Entity, authority, representative, domain and contract due diligence at admission.
B21: TOTAL onboarding cost ₹ (one time) | C21: =$C$19+$C$20
B22: Contract term (months) | C22: ='1_Inputs'!$B$8
B23: Onboarding amortised ₹/yr | C23: =IFERROR($C$21/$C$22*12,0)
B24: Onboarding recovered by fee? | C24: =IF('1_Inputs'!$B$31>=$C$21,"Yes","No — shortfall") | D24: =IFERROR('1_Inputs'!$B$31-$C$21,0)

Sheet 12_Tenant_PnL
A1: 12 — Tenant P&L (annual)
A2: Full bottom-up build across origination, the servicing book, collections, recurring subscriptions and platform cost. Pass-through appears in both cost and revenue — margin is earned on the handling markup only.
A4: Origination volume
A5: Monthly applications started | B5: ='1_Inputs'!$B$19
A6: Annual applications started | B6: =$B$5*12
A7: Decisioned rate | B7: ='7_Cost_Origination'!$B$10
A8: Annual decisioned applications | B8: =$B$6*$B$7
A9: Funded rate | B9: ='7_Cost_Origination'!$B$9
A10: Annual funded loans | B10: =$B$6*$B$9
A11: Average ticket (₹) | B11: ='7_Cost_Origination'!$B$7
A12: Annual disbursement (₹) | B12: =$B$10*$B$11 | C12: The denominator the tenant's CFO thinks in.
A14: The book — servicing economics depend on STOCK, not flow
A15: Book maturity | B15: ='1_Inputs'!$B$21 | C15: Year 1 = ramping. Steady state = originations equal closures.
A16: Effective life (years) | B16: ='8_Cost_Servicing'!$B$8 | C16: Contractual tenor after prepayment and foreclosure.
A17: Steady-state active loans | B17: =$B$10*$B$16 | C17: At equilibrium the book holds one full effective life of originations.
A18: Year-1 average active loans | B18: =$B$10*MIN($B$16,1)/2 | C18: Loans accumulate through the year, so the average is roughly half.
A19: ACTIVE LOANS (selected) | B19: =IF($B$15="Steady state",$B$17,$B$18)
A20: Servicing ramp factor | B20: =IF($B$15="Steady state",1,MIN(1,0.5/MAX($B$16,0.0001))) | C20: At steady state each year incurs one full lifetime of servicing across the book, because closures equal originations.
A22: Cost
A23: Origination external — platform-borne | B23: ='7_Cost_Origination'!$J$53*$B$6 | C23: Absorbed inside the platform fee. Vendor price rises hit margin directly.
A24: Origination external — pass-through | B24: ='7_Cost_Origination'!$J$54*$B$6 | C24: Rebilled at cost + markup. Usually the largest single cost line.
A25: Servicing + collections — platform-borne | B25: ='8_Cost_Servicing'!$I$46*$B$10*$B$20 | C25: The loan-lifetime cost tail. Absent from an origination-only model — and often larger than origination.
A26: Servicing + collections — pass-through | B26: ='8_Cost_Servicing'!$I$47*$B$10*$B$20
A27: Recurring subscriptions — platform-borne | B27: ='3_RateCard_Recurring'!$L$44 | C27: Scales with branches, devices, seats, partners and feeds — NOT with loan volume.
A28: Recurring subscriptions — pass-through | B28: ='3_RateCard_Recurring'!$L$43
A29: Cloud — fixed | B29: ='9_Cloud_Cost'!$C$29*12 | C29: Volume-independent. Includes the per-tenant isolated decision runtime (ADR 0003).
A30: Cloud — variable | B30: ='9_Cloud_Cost'!$C$30*$B$6/1000
A31: Cloud — retained storage (year 1) | B31: ='9_Cloud_Cost'!$C$56 | C31: Rises every year of the contract — see sheet 9.
A32: Governance + regulatory | B32: ='10_Governance_Cost'!$B$31
A33: Support | B33: ='11_Service_Cost'!$C$18*12
A34: Onboarding amortised | B34: ='11_Service_Cost'!$C$23
A35: TOTAL COST | B35: =SUM($B$23:$B$34)
A36: Total PASS-THROUGH cost | B36: =$B$24+$B$26+$B$28 | C36: Rebilled at cost plus the handling markup.
A37: Total cost excluding pass-through | B37: =$B$35-$B$36 | C37: The cost base the platform, origination and servicing fees must actually cover.
A39: Revenue
A40: Platform fee | B40: ='1_Inputs'!$B$27*12 | C40: Fixed. Recovers the per-tenant cost floor.
A41: Per-decisioned-application fee | B41: ='1_Inputs'!$B$28*$B$8 | C41: Shares funnel risk: you get paid for work done on files that do not fund.
A42: Per-funded-loan fee | B42: ='1_Inputs'!$B$29*$B$10 | C42: Origination fee.
A43: LMS fee on the active book | B43: ='1_Inputs'!$B$30*$B$19*12 | C43: The annuity. This is what makes a lending SaaS a good business — and what an origination-only model misses.
A44: Pass-through recovery | B44: =$B$36*(1+'1_Inputs'!$B$26)
A45: Onboarding fee amortised | B45: =IFERROR('1_Inputs'!$B$31/'1_Inputs'!$B$8*12,0)
A46: TOTAL REVENUE | B46: =SUM($B$40:$B$45)
A48: Margin
A49: Gross profit | B49: =$B$46-$B$35
A50: Gross margin % | B50: =IFERROR($B$49/$B$46,0)
A51: Software margin % (pass-through stripped at cost) | B51: =IFERROR(($B$46-$B$36-$B$37)/($B$46-$B$36),0) | C51: Strips rebilled cost from both sides but keeps the handling markup as earned margin. Manage the deal to this line.
A52: Revenue per funded loan (₹) | B52: =IFERROR($B$46/$B$10,0)
A53: Cost per funded loan (₹) | B53: =IFERROR($B$35/$B$10,0)
A54: Contribution per funded loan (₹) | B54: =$B$52-$B$53
A55: Effective cost to tenant (bps of disbursement) | B55: =IFERROR($B$46/$B$12*10000,0) | C55: Quote this to a CFO. Small-ticket journeys look alarming here — that is real, not a modelling artefact.
A56: Revenue per active loan per month (₹) | B56: =IFERROR($B$43/MAX($B$19,1)/12,0)
A57: Cost per active loan per month (₹) | B57: ='8_Cost_Servicing'!$I$48 | C57: If this exceeds the line above, every month a loan stays on the book destroys value.
A59: Break-even
A60: Annual fixed cost (₹) | B60: =$B$29+$B$31+$B$32+$B$33+$B$34+$B$27+$B$28 | C60: Incurred whether the tenant originates one loan or one hundred thousand.
A61: of which truly volume-independent (₹) | B61: =$B$29+$B$33+$B$34+$B$27+$B$28 | C61: Storage and the volume-weighted part of governance do scale — sheet 15 recomputes both.
A62: Variable cost per application (₹) | B62: =IFERROR(($B$35-$B$60)/$B$6,0)
A63: Recurring pass-through recovery (volume-independent) | B63: =$B$28*(1+'1_Inputs'!$B$26) | C63: Recurring cost is fixed, so the revenue that recovers it is fixed too. Keeping this on the variable side would overstate margin at high volume and understate it at low volume.
A64: Fixed revenue per year (₹) | B64: =$B$40+$B$45+$B$63
A65: Revenue per application (₹) | B65: =IFERROR(($B$46-$B$64)/$B$6,0)
A66: Contribution per application (₹) | B66: =$B$65-$B$62
A67: Break-even annual applications | B67: =IFERROR(MAX(0,($B$60-$B$64)/$B$66),0)
A68: Break-even MONTHLY applications | B68: =$B$67/12 | C68: Below this the deal loses money at the quoted price. Make it a contractual minimum.
A69: Headroom vs. plan volume | B69: =IF($B$67<=0,"n/a — fixed fees already cover fixed cost",TEXT($B$6/$B$67,"0.00")&"x") | C69: Under 1.0x = loss-making. 'n/a' means the platform fee alone carries the fixed base.

Sheet 13_Price_Card
A1: 13 — Price card and margin solve
A2: Solves for the per-funded-loan fee that hits the target gross margin, then states the quote.
A4: Margin solve
A5: Target gross margin % | B5: ='1_Inputs'!$B$25
A6: Total cost ₹/yr | B6: ='12_Tenant_PnL'!$B$35
A7: Required total revenue ₹/yr | B7: =IFERROR($B$6/(1-$B$5),0)
A8: Revenue already fixed (platform + onboarding + pass-through + LMS) | B8: ='12_Tenant_PnL'!$B$40+'12_Tenant_PnL'!$B$45+'12_Tenant_PnL'!$B$44+'12_Tenant_PnL'!$B$43
A9: Revenue from per-decisioned-application fee | B9: ='12_Tenant_PnL'!$B$41
A10: REQUIRED fee per funded loan ₹ | B10: =IFERROR(MAX(0,($B$7-$B$8-$B$9)/'12_Tenant_PnL'!$B$10),0) | C10: The floor the deal desk must not go below without approval.
A11: Current fee per funded loan ₹ | B11: ='1_Inputs'!$B$29
A12: Gap ₹ per funded loan | B12: =$B$10-$B$11
A13: Verdict | B13: =IF($B$12<=0,"AT OR ABOVE TARGET MARGIN","BELOW TARGET — raise a fee, raise the platform fee, or change journey mix")
A15: Servicing fee sanity check | B15: =IF('12_Tenant_PnL'!$B$56>='12_Tenant_PnL'!$B$57,"LMS fee covers servicing cost","LMS FEE BELOW SERVICING COST — the book loses money every month") | C15: Independent of origination margin. A deal can look profitable at origination and still bleed on the book.
A17: The quote
A18: Tenant | B18: ='1_Inputs'!$B$6
A19: Journey priced | B19: ='1_Inputs'!$B$18 | C19: Quote each journey separately — costs differ by orders of magnitude.
A20: Deployment model | B20: ='1_Inputs'!$B$13
A21: Support tier | B21: ='1_Inputs'!$B$14
A22: Platform fee ₹/month | B22: ='1_Inputs'!$B$27
A23: Fee per decisioned application ₹ | B23: ='1_Inputs'!$B$28
A24: Fee per funded loan ₹ | B24: ='1_Inputs'!$B$29
A25: LMS fee per active loan per month ₹ | B25: ='1_Inputs'!$B$30
A26: Pass-through handling markup | B26: ='1_Inputs'!$B$26 | C26: Bureau, KYC, AA, eSign, payout, NACH and reporting rails rebilled at cost + this markup, itemised monthly.
A27: One-time onboarding fee ₹ | B27: ='1_Inputs'!$B$31
A28: Minimum committed monthly applications | B28: =CEILING('12_Tenant_PnL'!$B$68,100) | C28: Contractual floor. Without it the tenant's funnel risk becomes your loss.
A29: Effective cost to tenant (bps of disbursement) | B29: ='12_Tenant_PnL'!$B$55
A30: Resulting gross margin % | B30: ='12_Tenant_PnL'!$B$50
A31: Resulting software margin % | B31: ='12_Tenant_PnL'!$B$51 | C31: Manage the deal to this line, not the blended margin above.

Sheet 14_Journey_Economics
A1: 14 — Full-lifetime economics across all 21 journeys
A2: Origination, servicing and collections for every journey at the current rate cards, funnel and lifetime profile. This is the sheet that decides packaging.
A4: # | B4: Journey | C4: Archetype | D4: Funnel preset | E4: Avg ticket ₹ | F4: Funded rate | G4: Eff. life (yrs) | H4: Origination ₹/app | I4: Origination ₹/funded loan | J4: Servicing ₹/loan (life) | K4: Collections ₹/loan (life) | L4: TOTAL lifetime ₹/loan | M4: ₹ per active loan-month | N4: Total as bps | O4: Apps per funded loan
A5: 1 | B5: personal_loan | C5: unsecured_term | D5: Digital_Unsecured | E5: ='4_Journey_Units_LOS'!C$6 | F5: =INDEX('6_Funnel_And_Lifetime'!$C$11:$G$11,MATCH($D5,'6_Funnel_And_Lifetime'!$C$4:$G$4,0)) | G5: ='6_Funnel_And_Lifetime'!$F$63 | H5: =SUMPRODUCT('4_Journey_Units_LOS'!C$8:C$45,'2_RateCard_Unit'!$I$5:$I$42,INDEX('6_Funnel_And_Lifetime'!$C$20:$G$57,0,MATCH($D5,'6_Funnel_And_Lifetime'!$C$4:$G$4,0)),INDEX('2_RateCard_Unit'!$F$5:$H$42,0,'1_Inputs'!$B$54)) | I5: =IFERROR(H5/F5,0) | J5: =SUMPRODUCT('5_Journey_Units_Service'!C$6:C$21,'6_Funnel_And_Lifetime'!C$104:C$119,'2_RateCard_Unit'!$I$43:$I$58,INDEX('2_RateCard_Unit'!$F$43:$H$58,0,'1_Inputs'!$B$54)) | K5: =SUMPRODUCT('6_Funnel_And_Lifetime'!C$124:C$132,'2_RateCard_Unit'!$I$59:$I$67,INDEX('2_RateCard_Unit'!$F$59:$H$67,0,'1_Inputs'!$B$54)) | L5: =I5+J5+K5 | M5: =IFERROR((J5+K5)/('6_Funnel_And_Lifetime'!$E$63),0) | N5: =IFERROR(L5/E5*10000,0) | O5: =IFERROR(1/F5,0)
A6: 2 | B6: co_lending_programme | C6: co_lending | D6: Digital_Unsecured | E6: ='4_Journey_Units_LOS'!D$6 | F6: =INDEX('6_Funnel_And_Lifetime'!$C$11:$G$11,MATCH($D6,'6_Funnel_And_Lifetime'!$C$4:$G$4,0)) | G6: ='6_Funnel_And_Lifetime'!$F$64 | H6: =SUMPRODUCT('4_Journey_Units_LOS'!D$8:D$45,'2_RateCard_Unit'!$I$5:$I$42,INDEX('6_Funnel_And_Lifetime'!$C$20:$G$57,0,MATCH($D6,'6_Funnel_And_Lifetime'!$C$4:$G$4,0)),INDEX('2_RateCard_Unit'!$F$5:$H$42,0,'1_Inputs'!$B$54)) | I6: =IFERROR(H6/F6,0) | J6: =SUMPRODUCT('5_Journey_Units_Service'!D$6:D$21,'6_Funnel_And_Lifetime'!D$104:D$119,'2_RateCard_Unit'!$I$43:$I$58,INDEX('2_RateCard_Unit'!$F$43:$H$58,0,'1_Inputs'!$B$54)) | K6: =SUMPRODUCT('6_Funnel_And_Lifetime'!D$124:D$132,'2_RateCard_Unit'!$I$59:$I$67,INDEX('2_RateCard_Unit'!$F$59:$H$67,0,'1_Inputs'!$B$54)) | L6: =I6+J6+K6 | M6: =IFERROR((J6+K6)/('6_Funnel_And_Lifetime'!$E$64),0) | N6: =IFERROR(L6/E6*10000,0) | O6: =IFERROR(1/F6,0)
A7: 3 | B7: msme_working_capital | C7: revolving_working_capital | D7: MSME_Business | E7: ='4_Journey_Units_LOS'!E$6 | F7: =INDEX('6_Funnel_And_Lifetime'!$C$11:$G$11,MATCH($D7,'6_Funnel_And_Lifetime'!$C$4:$G$4,0)) | G7: ='6_Funnel_And_Lifetime'!$F$65 | H7: =SUMPRODUCT('4_Journey_Units_LOS'!E$8:E$45,'2_RateCard_Unit'!$I$5:$I$42,INDEX('6_Funnel_And_Lifetime'!$C$20:$G$57,0,MATCH($D7,'6_Funnel_And_Lifetime'!$C$4:$G$4,0)),INDEX('2_RateCard_Unit'!$F$5:$H$42,0,'1_Inputs'!$B$54)) | I7: =IFERROR(H7/F7,0) | J7: =SUMPRODUCT('5_Journey_Units_Service'!E$6:E$21,'6_Funnel_And_Lifetime'!E$104:E$119,'2_RateCard_Unit'!$I$43:$I$58,INDEX('2_RateCard_Unit'!$F$43:$H$58,0,'1_Inputs'!$B$54)) | K7: =SUMPRODUCT('6_Funnel_And_Lifetime'!E$124:E$132,'2_RateCard_Unit'!$I$59:$I$67,INDEX('2_RateCard_Unit'!$F$59:$H$67,0,'1_Inputs'!$B$54)) | L7: =I7+J7+K7 | M7: =IFERROR((J7+K7)/('6_Funnel_And_Lifetime'!$E$65),0) | N7: =IFERROR(L7/E7*10000,0) | O7: =IFERROR(1/F7,0)
A8: 4 | B8: msme_term_loan | C8: business_term | D8: MSME_Business | E8: ='4_Journey_Units_LOS'!F$6 | F8: =INDEX('6_Funnel_And_Lifetime'!$C$11:$G$11,MATCH($D8,'6_Funnel_And_Lifetime'!$C$4:$G$4,0)) | G8: ='6_Funnel_And_Lifetime'!$F$66 | H8: =SUMPRODUCT('4_Journey_Units_LOS'!F$8:F$45,'2_RateCard_Unit'!$I$5:$I$42,INDEX('6_Funnel_And_Lifetime'!$C$20:$G$57,0,MATCH($D8,'6_Funnel_And_Lifetime'!$C$4:$G$4,0)),INDEX('2_RateCard_Unit'!$F$5:$H$42,0,'1_Inputs'!$B$54)) | I8: =IFERROR(H8/F8,0) | J8: =SUMPRODUCT('5_Journey_Units_Service'!F$6:F$21,'6_Funnel_And_Lifetime'!F$104:F$119,'2_RateCard_Unit'!$I$43:$I$58,INDEX('2_RateCard_Unit'!$F$43:$H$58,0,'1_Inputs'!$B$54)) | K8: =SUMPRODUCT('6_Funnel_And_Lifetime'!F$124:F$132,'2_RateCard_Unit'!$I$59:$I$67,INDEX('2_RateCard_Unit'!$F$59:$H$67,0,'1_Inputs'!$B$54)) | L8: =I8+J8+K8 | M8: =IFERROR((J8+K8)/('6_Funnel_And_Lifetime'!$E$66),0) | N8: =IFERROR(L8/E8*10000,0) | O8: =IFERROR(1/F8,0)
A9: 5 | B9: professional_practice_loan | C9: business_term | D9: MSME_Business | E9: ='4_Journey_Units_LOS'!G$6 | F9: =INDEX('6_Funnel_And_Lifetime'!$C$11:$G$11,MATCH($D9,'6_Funnel_And_Lifetime'!$C$4:$G$4,0)) | G9: ='6_Funnel_And_Lifetime'!$F$67 | H9: =SUMPRODUCT('4_Journey_Units_LOS'!G$8:G$45,'2_RateCard_Unit'!$I$5:$I$42,INDEX('6_Funnel_And_Lifetime'!$C$20:$G$57,0,MATCH($D9,'6_Funnel_And_Lifetime'!$C$4:$G$4,0)),INDEX('2_RateCard_Unit'!$F$5:$H$42,0,'1_Inputs'!$B$54)) | I9: =IFERROR(H9/F9,0) | J9: =SUMPRODUCT('5_Journey_Units_Service'!G$6:G$21,'6_Funnel_And_Lifetime'!G$104:G$119,'2_RateCard_Unit'!$I$43:$I$58,INDEX('2_RateCard_Unit'!$F$43:$H$58,0,'1_Inputs'!$B$54)) | K9: =SUMPRODUCT('6_Funnel_And_Lifetime'!G$124:G$132,'2_RateCard_Unit'!$I$59:$I$67,INDEX('2_RateCard_Unit'!$F$59:$H$67,0,'1_Inputs'!$B$54)) | L9: =I9+J9+K9 | M9: =IFERROR((J9+K9)/('6_Funnel_And_Lifetime'!$E$67),0) | N9: =IFERROR(L9/E9*10000,0) | O9: =IFERROR(1/F9,0)
A10: 6 | B10: secured_business_loan | C10: property_secured | D10: Secured_HighTouch | E10: ='4_Journey_Units_LOS'!H$6 | F10: =INDEX('6_Funnel_And_Lifetime'!$C$11:$G$11,MATCH($D10,'6_Funnel_And_Lifetime'!$C$4:$G$4,0)) | G10: ='6_Funnel_And_Lifetime'!$F$68 | H10: =SUMPRODUCT('4_Journey_Units_LOS'!H$8:H$45,'2_RateCard_Unit'!$I$5:$I$42,INDEX('6_Funnel_And_Lifetime'!$C$20:$G$57,0,MATCH($D10,'6_Funnel_And_Lifetime'!$C$4:$G$4,0)),INDEX('2_RateCard_Unit'!$F$5:$H$42,0,'1_Inputs'!$B$54)) | I10: =IFERROR(H10/F10,0) | J10: =SUMPRODUCT('5_Journey_Units_Service'!H$6:H$21,'6_Funnel_And_Lifetime'!H$104:H$119,'2_RateCard_Unit'!$I$43:$I$58,INDEX('2_RateCard_Unit'!$F$43:$H$58,0,'1_Inputs'!$B$54)) | K10: =SUMPRODUCT('6_Funnel_And_Lifetime'!H$124:H$132,'2_RateCard_Unit'!$I$59:$I$67,INDEX('2_RateCard_Unit'!$F$59:$H$67,0,'1_Inputs'!$B$54)) | L10: =I10+J10+K10 | M10: =IFERROR((J10+K10)/('6_Funnel_And_Lifetime'!$E$68),0) | N10: =IFERROR(L10/E10*10000,0) | O10: =IFERROR(1/F10,0)
A11: 7 | B11: loan_against_property | C11: property_secured | D11: Secured_HighTouch | E11: ='4_Journey_Units_LOS'!I$6 | F11: =INDEX('6_Funnel_And_Lifetime'!$C$11:$G$11,MATCH($D11,'6_Funnel_And_Lifetime'!$C$4:$G$4,0)) | G11: ='6_Funnel_And_Lifetime'!$F$69 | H11: =SUMPRODUCT('4_Journey_Units_LOS'!I$8:I$45,'2_RateCard_Unit'!$I$5:$I$42,INDEX('6_Funnel_And_Lifetime'!$C$20:$G$57,0,MATCH($D11,'6_Funnel_And_Lifetime'!$C$4:$G$4,0)),INDEX('2_RateCard_Unit'!$F$5:$H$42,0,'1_Inputs'!$B$54)) | I11: =IFERROR(H11/F11,0) | J11: =SUMPRODUCT('5_Journey_Units_Service'!I$6:I$21,'6_Funnel_And_Lifetime'!I$104:I$119,'2_RateCard_Unit'!$I$43:$I$58,INDEX('2_RateCard_Unit'!$F$43:$H$58,0,'1_Inputs'!$B$54)) | K11: =SUMPRODUCT('6_Funnel_And_Lifetime'!I$124:I$132,'2_RateCard_Unit'!$I$59:$I$67,INDEX('2_RateCard_Unit'!$F$59:$H$67,0,'1_Inputs'!$B$54)) | L11: =I11+J11+K11 | M11: =IFERROR((J11+K11)/('6_Funnel_And_Lifetime'!$E$69),0) | N11: =IFERROR(L11/E11*10000,0) | O11: =IFERROR(1/F11,0)
A12: 8 | B12: home_loan | C12: property_secured | D12: Secured_HighTouch | E12: ='4_Journey_Units_LOS'!J$6 | F12: =INDEX('6_Funnel_And_Lifetime'!$C$11:$G$11,MATCH($D12,'6_Funnel_And_Lifetime'!$C$4:$G$4,0)) | G12: ='6_Funnel_And_Lifetime'!$F$70 | H12: =SUMPRODUCT('4_Journey_Units_LOS'!J$8:J$45,'2_RateCard_Unit'!$I$5:$I$42,INDEX('6_Funnel_And_Lifetime'!$C$20:$G$57,0,MATCH($D12,'6_Funnel_And_Lifetime'!$C$4:$G$4,0)),INDEX('2_RateCard_Unit'!$F$5:$H$42,0,'1_Inputs'!$B$54)) | I12: =IFERROR(H12/F12,0) | J12: =SUMPRODUCT('5_Journey_Units_Service'!J$6:J$21,'6_Funnel_And_Lifetime'!J$104:J$119,'2_RateCard_Unit'!$I$43:$I$58,INDEX('2_RateCard_Unit'!$F$43:$H$58,0,'1_Inputs'!$B$54)) | K12: =SUMPRODUCT('6_Funnel_And_Lifetime'!J$124:J$132,'2_RateCard_Unit'!$I$59:$I$67,INDEX('2_RateCard_Unit'!$F$59:$H$67,0,'1_Inputs'!$B$54)) | L12: =I12+J12+K12 | M12: =IFERROR((J12+K12)/('6_Funnel_And_Lifetime'!$E$70),0) | N12: =IFERROR(L12/E12*10000,0) | O12: =IFERROR(1/F12,0)
A13: 9 | B13: equipment_machinery_finance | C13: asset_finance | D13: MSME_Business | E13: ='4_Journey_Units_LOS'!K$6 | F13: =INDEX('6_Funnel_And_Lifetime'!$C$11:$G$11,MATCH($D13,'6_Funnel_And_Lifetime'!$C$4:$G$4,0)) | G13: ='6_Funnel_And_Lifetime'!$F$71 | H13: =SUMPRODUCT('4_Journey_Units_LOS'!K$8:K$45,'2_RateCard_Unit'!$I$5:$I$42,INDEX('6_Funnel_And_Lifetime'!$C$20:$G$57,0,MATCH($D13,'6_Funnel_And_Lifetime'!$C$4:$G$4,0)),INDEX('2_RateCard_Unit'!$F$5:$H$42,0,'1_Inputs'!$B$54)) | I13: =IFERROR(H13/F13,0) | J13: =SUMPRODUCT('5_Journey_Units_Service'!K$6:K$21,'6_Funnel_And_Lifetime'!K$104:K$119,'2_RateCard_Unit'!$I$43:$I$58,INDEX('2_RateCard_Unit'!$F$43:$H$58,0,'1_Inputs'!$B$54)) | K13: =SUMPRODUCT('6_Funnel_And_Lifetime'!K$124:K$132,'2_RateCard_Unit'!$I$59:$I$67,INDEX('2_RateCard_Unit'!$F$59:$H$67,0,'1_Inputs'!$B$54)) | L13: =I13+J13+K13 | M13: =IFERROR((J13+K13)/('6_Funnel_And_Lifetime'!$E$71),0) | N13: =IFERROR(L13/E13*10000,0) | O13: =IFERROR(1/F13,0)
A14: 10 | B14: green_equipment_finance | C14: asset_finance | D14: MSME_Business | E14: ='4_Journey_Units_LOS'!L$6 | F14: =INDEX('6_Funnel_And_Lifetime'!$C$11:$G$11,MATCH($D14,'6_Funnel_And_Lifetime'!$C$4:$G$4,0)) | G14: ='6_Funnel_And_Lifetime'!$F$72 | H14: =SUMPRODUCT('4_Journey_Units_LOS'!L$8:L$45,'2_RateCard_Unit'!$I$5:$I$42,INDEX('6_Funnel_And_Lifetime'!$C$20:$G$57,0,MATCH($D14,'6_Funnel_And_Lifetime'!$C$4:$G$4,0)),INDEX('2_RateCard_Unit'!$F$5:$H$42,0,'1_Inputs'!$B$54)) | I14: =IFERROR(H14/F14,0) | J14: =SUMPRODUCT('5_Journey_Units_Service'!L$6:L$21,'6_Funnel_And_Lifetime'!L$104:L$119,'2_RateCard_Unit'!$I$43:$I$58,INDEX('2_RateCard_Unit'!$F$43:$H$58,0,'1_Inputs'!$B$54)) | K14: =SUMPRODUCT('6_Funnel_And_Lifetime'!L$124:L$132,'2_RateCard_Unit'!$I$59:$I$67,INDEX('2_RateCard_Unit'!$F$59:$H$67,0,'1_Inputs'!$B$54)) | L14: =I14+J14+K14 | M14: =IFERROR((J14+K14)/('6_Funnel_And_Lifetime'!$E$72),0) | N14: =IFERROR(L14/E14*10000,0) | O14: =IFERROR(1/F14,0)
A15: 11 | B15: personal_vehicle_loan | C15: asset_finance | D15: Digital_Unsecured | E15: ='4_Journey_Units_LOS'!M$6 | F15: =INDEX('6_Funnel_And_Lifetime'!$C$11:$G$11,MATCH($D15,'6_Funnel_And_Lifetime'!$C$4:$G$4,0)) | G15: ='6_Funnel_And_Lifetime'!$F$73 | H15: =SUMPRODUCT('4_Journey_Units_LOS'!M$8:M$45,'2_RateCard_Unit'!$I$5:$I$42,INDEX('6_Funnel_And_Lifetime'!$C$20:$G$57,0,MATCH($D15,'6_Funnel_And_Lifetime'!$C$4:$G$4,0)),INDEX('2_RateCard_Unit'!$F$5:$H$42,0,'1_Inputs'!$B$54)) | I15: =IFERROR(H15/F15,0) | J15: =SUMPRODUCT('5_Journey_Units_Service'!M$6:M$21,'6_Funnel_And_Lifetime'!M$104:M$119,'2_RateCard_Unit'!$I$43:$I$58,INDEX('2_RateCard_Unit'!$F$43:$H$58,0,'1_Inputs'!$B$54)) | K15: =SUMPRODUCT('6_Funnel_And_Lifetime'!M$124:M$132,'2_RateCard_Unit'!$I$59:$I$67,INDEX('2_RateCard_Unit'!$F$59:$H$67,0,'1_Inputs'!$B$54)) | L15: =I15+J15+K15 | M15: =IFERROR((J15+K15)/('6_Funnel_And_Lifetime'!$E$73),0) | N15: =IFERROR(L15/E15*10000,0) | O15: =IFERROR(1/F15,0)
A16: 12 | B16: commercial_vehicle_finance | C16: asset_finance | D16: MSME_Business | E16: ='4_Journey_Units_LOS'!N$6 | F16: =INDEX('6_Funnel_And_Lifetime'!$C$11:$G$11,MATCH($D16,'6_Funnel_And_Lifetime'!$C$4:$G$4,0)) | G16: ='6_Funnel_And_Lifetime'!$F$74 | H16: =SUMPRODUCT('4_Journey_Units_LOS'!N$8:N$45,'2_RateCard_Unit'!$I$5:$I$42,INDEX('6_Funnel_And_Lifetime'!$C$20:$G$57,0,MATCH($D16,'6_Funnel_And_Lifetime'!$C$4:$G$4,0)),INDEX('2_RateCard_Unit'!$F$5:$H$42,0,'1_Inputs'!$B$54)) | I16: =IFERROR(H16/F16,0) | J16: =SUMPRODUCT('5_Journey_Units_Service'!N$6:N$21,'6_Funnel_And_Lifetime'!N$104:N$119,'2_RateCard_Unit'!$I$43:$I$58,INDEX('2_RateCard_Unit'!$F$43:$H$58,0,'1_Inputs'!$B$54)) | K16: =SUMPRODUCT('6_Funnel_And_Lifetime'!N$124:N$132,'2_RateCard_Unit'!$I$59:$I$67,INDEX('2_RateCard_Unit'!$F$59:$H$67,0,'1_Inputs'!$B$54)) | L16: =I16+J16+K16 | M16: =IFERROR((J16+K16)/('6_Funnel_And_Lifetime'!$E$74),0) | N16: =IFERROR(L16/E16*10000,0) | O16: =IFERROR(1/F16,0)
A17: 13 | B17: gold_loan | C17: gold_custody | D17: Field_Group | E17: ='4_Journey_Units_LOS'!O$6 | F17: =INDEX('6_Funnel_And_Lifetime'!$C$11:$G$11,MATCH($D17,'6_Funnel_And_Lifetime'!$C$4:$G$4,0)) | G17: ='6_Funnel_And_Lifetime'!$F$75 | H17: =SUMPRODUCT('4_Journey_Units_LOS'!O$8:O$45,'2_RateCard_Unit'!$I$5:$I$42,INDEX('6_Funnel_And_Lifetime'!$C$20:$G$57,0,MATCH($D17,'6_Funnel_And_Lifetime'!$C$4:$G$4,0)),INDEX('2_RateCard_Unit'!$F$5:$H$42,0,'1_Inputs'!$B$54)) | I17: =IFERROR(H17/F17,0) | J17: =SUMPRODUCT('5_Journey_Units_Service'!O$6:O$21,'6_Funnel_And_Lifetime'!O$104:O$119,'2_RateCard_Unit'!$I$43:$I$58,INDEX('2_RateCard_Unit'!$F$43:$H$58,0,'1_Inputs'!$B$54)) | K17: =SUMPRODUCT('6_Funnel_And_Lifetime'!O$124:O$132,'2_RateCard_Unit'!$I$59:$I$67,INDEX('2_RateCard_Unit'!$F$59:$H$67,0,'1_Inputs'!$B$54)) | L17: =I17+J17+K17 | M17: =IFERROR((J17+K17)/('6_Funnel_And_Lifetime'!$E$75),0) | N17: =IFERROR(L17/E17*10000,0) | O17: =IFERROR(1/F17,0)
A18: 14 | B18: education_loan | C18: priority_term | D18: Secured_HighTouch | E18: ='4_Journey_Units_LOS'!P$6 | F18: =INDEX('6_Funnel_And_Lifetime'!$C$11:$G$11,MATCH($D18,'6_Funnel_And_Lifetime'!$C$4:$G$4,0)) | G18: ='6_Funnel_And_Lifetime'!$F$76 | H18: =SUMPRODUCT('4_Journey_Units_LOS'!P$8:P$45,'2_RateCard_Unit'!$I$5:$I$42,INDEX('6_Funnel_And_Lifetime'!$C$20:$G$57,0,MATCH($D18,'6_Funnel_And_Lifetime'!$C$4:$G$4,0)),INDEX('2_RateCard_Unit'!$F$5:$H$42,0,'1_Inputs'!$B$54)) | I18: =IFERROR(H18/F18,0) | J18: =SUMPRODUCT('5_Journey_Units_Service'!P$6:P$21,'6_Funnel_And_Lifetime'!P$104:P$119,'2_RateCard_Unit'!$I$43:$I$58,INDEX('2_RateCard_Unit'!$F$43:$H$58,0,'1_Inputs'!$B$54)) | K18: =SUMPRODUCT('6_Funnel_And_Lifetime'!P$124:P$132,'2_RateCard_Unit'!$I$59:$I$67,INDEX('2_RateCard_Unit'!$F$59:$H$67,0,'1_Inputs'!$B$54)) | L18: =I18+J18+K18 | M18: =IFERROR((J18+K18)/('6_Funnel_And_Lifetime'!$E$76),0) | N18: =IFERROR(L18/E18*10000,0) | O18: =IFERROR(1/F18,0)
A19: 15 | B19: agriculture_allied_finance | C19: seasonal_field | D19: Field_Group | E19: ='4_Journey_Units_LOS'!Q$6 | F19: =INDEX('6_Funnel_And_Lifetime'!$C$11:$G$11,MATCH($D19,'6_Funnel_And_Lifetime'!$C$4:$G$4,0)) | G19: ='6_Funnel_And_Lifetime'!$F$77 | H19: =SUMPRODUCT('4_Journey_Units_LOS'!Q$8:Q$45,'2_RateCard_Unit'!$I$5:$I$42,INDEX('6_Funnel_And_Lifetime'!$C$20:$G$57,0,MATCH($D19,'6_Funnel_And_Lifetime'!$C$4:$G$4,0)),INDEX('2_RateCard_Unit'!$F$5:$H$42,0,'1_Inputs'!$B$54)) | I19: =IFERROR(H19/F19,0) | J19: =SUMPRODUCT('5_Journey_Units_Service'!Q$6:Q$21,'6_Funnel_And_Lifetime'!Q$104:Q$119,'2_RateCard_Unit'!$I$43:$I$58,INDEX('2_RateCard_Unit'!$F$43:$H$58,0,'1_Inputs'!$B$54)) | K19: =SUMPRODUCT('6_Funnel_And_Lifetime'!Q$124:Q$132,'2_RateCard_Unit'!$I$59:$I$67,INDEX('2_RateCard_Unit'!$F$59:$H$67,0,'1_Inputs'!$B$54)) | L19: =I19+J19+K19 | M19: =IFERROR((J19+K19)/('6_Funnel_And_Lifetime'!$E$77),0) | N19: =IFERROR(L19/E19*10000,0) | O19: =IFERROR(1/F19,0)
A20: 16 | B20: microfinance_group_lending | C20: group_field | D20: Field_Group | E20: ='4_Journey_Units_LOS'!R$6 | F20: =INDEX('6_Funnel_And_Lifetime'!$C$11:$G$11,MATCH($D20,'6_Funnel_And_Lifetime'!$C$4:$G$4,0)) | G20: ='6_Funnel_And_Lifetime'!$F$78 | H20: =SUMPRODUCT('4_Journey_Units_LOS'!R$8:R$45,'2_RateCard_Unit'!$I$5:$I$42,INDEX('6_Funnel_And_Lifetime'!$C$20:$G$57,0,MATCH($D20,'6_Funnel_And_Lifetime'!$C$4:$G$4,0)),INDEX('2_RateCard_Unit'!$F$5:$H$42,0,'1_Inputs'!$B$54)) | I20: =IFERROR(H20/F20,0) | J20: =SUMPRODUCT('5_Journey_Units_Service'!R$6:R$21,'6_Funnel_And_Lifetime'!R$104:R$119,'2_RateCard_Unit'!$I$43:$I$58,INDEX('2_RateCard_Unit'!$F$43:$H$58,0,'1_Inputs'!$B$54)) | K20: =SUMPRODUCT('6_Funnel_And_Lifetime'!R$124:R$132,'2_RateCard_Unit'!$I$59:$I$67,INDEX('2_RateCard_Unit'!$F$59:$H$67,0,'1_Inputs'!$B$54)) | L20: =I20+J20+K20 | M20: =IFERROR((J20+K20)/('6_Funnel_And_Lifetime'!$E$78),0) | N20: =IFERROR(L20/E20*10000,0) | O20: =IFERROR(1/F20,0)
A21: 17 | B21: consumer_durable_finance | C21: merchant_pos | D21: POS_Instant | E21: ='4_Journey_Units_LOS'!S$6 | F21: =INDEX('6_Funnel_And_Lifetime'!$C$11:$G$11,MATCH($D21,'6_Funnel_And_Lifetime'!$C$4:$G$4,0)) | G21: ='6_Funnel_And_Lifetime'!$F$79 | H21: =SUMPRODUCT('4_Journey_Units_LOS'!S$8:S$45,'2_RateCard_Unit'!$I$5:$I$42,INDEX('6_Funnel_And_Lifetime'!$C$20:$G$57,0,MATCH($D21,'6_Funnel_And_Lifetime'!$C$4:$G$4,0)),INDEX('2_RateCard_Unit'!$F$5:$H$42,0,'1_Inputs'!$B$54)) | I21: =IFERROR(H21/F21,0) | J21: =SUMPRODUCT('5_Journey_Units_Service'!S$6:S$21,'6_Funnel_And_Lifetime'!S$104:S$119,'2_RateCard_Unit'!$I$43:$I$58,INDEX('2_RateCard_Unit'!$F$43:$H$58,0,'1_Inputs'!$B$54)) | K21: =SUMPRODUCT('6_Funnel_And_Lifetime'!S$124:S$132,'2_RateCard_Unit'!$I$59:$I$67,INDEX('2_RateCard_Unit'!$F$59:$H$67,0,'1_Inputs'!$B$54)) | L21: =I21+J21+K21 | M21: =IFERROR((J21+K21)/('6_Funnel_And_Lifetime'!$E$79),0) | N21: =IFERROR(L21/E21*10000,0) | O21: =IFERROR(1/F21,0)
A22: 18 | B22: invoice_discounting | C22: trade_receivables | D22: MSME_Business | E22: ='4_Journey_Units_LOS'!T$6 | F22: =INDEX('6_Funnel_And_Lifetime'!$C$11:$G$11,MATCH($D22,'6_Funnel_And_Lifetime'!$C$4:$G$4,0)) | G22: ='6_Funnel_And_Lifetime'!$F$80 | H22: =SUMPRODUCT('4_Journey_Units_LOS'!T$8:T$45,'2_RateCard_Unit'!$I$5:$I$42,INDEX('6_Funnel_And_Lifetime'!$C$20:$G$57,0,MATCH($D22,'6_Funnel_And_Lifetime'!$C$4:$G$4,0)),INDEX('2_RateCard_Unit'!$F$5:$H$42,0,'1_Inputs'!$B$54)) | I22: =IFERROR(H22/F22,0) | J22: =SUMPRODUCT('5_Journey_Units_Service'!T$6:T$21,'6_Funnel_And_Lifetime'!T$104:T$119,'2_RateCard_Unit'!$I$43:$I$58,INDEX('2_RateCard_Unit'!$F$43:$H$58,0,'1_Inputs'!$B$54)) | K22: =SUMPRODUCT('6_Funnel_And_Lifetime'!T$124:T$132,'2_RateCard_Unit'!$I$59:$I$67,INDEX('2_RateCard_Unit'!$F$59:$H$67,0,'1_Inputs'!$B$54)) | L22: =I22+J22+K22 | M22: =IFERROR((J22+K22)/('6_Funnel_And_Lifetime'!$E$80),0) | N22: =IFERROR(L22/E22*10000,0) | O22: =IFERROR(1/F22,0)
A23: 19 | B23: purchase_order_finance | C23: trade_receivables | D23: MSME_Business | E23: ='4_Journey_Units_LOS'!U$6 | F23: =INDEX('6_Funnel_And_Lifetime'!$C$11:$G$11,MATCH($D23,'6_Funnel_And_Lifetime'!$C$4:$G$4,0)) | G23: ='6_Funnel_And_Lifetime'!$F$81 | H23: =SUMPRODUCT('4_Journey_Units_LOS'!U$8:U$45,'2_RateCard_Unit'!$I$5:$I$42,INDEX('6_Funnel_And_Lifetime'!$C$20:$G$57,0,MATCH($D23,'6_Funnel_And_Lifetime'!$C$4:$G$4,0)),INDEX('2_RateCard_Unit'!$F$5:$H$42,0,'1_Inputs'!$B$54)) | I23: =IFERROR(H23/F23,0) | J23: =SUMPRODUCT('5_Journey_Units_Service'!U$6:U$21,'6_Funnel_And_Lifetime'!U$104:U$119,'2_RateCard_Unit'!$I$43:$I$58,INDEX('2_RateCard_Unit'!$F$43:$H$58,0,'1_Inputs'!$B$54)) | K23: =SUMPRODUCT('6_Funnel_And_Lifetime'!U$124:U$132,'2_RateCard_Unit'!$I$59:$I$67,INDEX('2_RateCard_Unit'!$F$59:$H$67,0,'1_Inputs'!$B$54)) | L23: =I23+J23+K23 | M23: =IFERROR((J23+K23)/('6_Funnel_And_Lifetime'!$E$81),0) | N23: =IFERROR(L23/E23*10000,0) | O23: =IFERROR(1/F23,0)
A24: 20 | B24: supply_chain_finance | C24: trade_receivables | D24: MSME_Business | E24: ='4_Journey_Units_LOS'!V$6 | F24: =INDEX('6_Funnel_And_Lifetime'!$C$11:$G$11,MATCH($D24,'6_Funnel_And_Lifetime'!$C$4:$G$4,0)) | G24: ='6_Funnel_And_Lifetime'!$F$82 | H24: =SUMPRODUCT('4_Journey_Units_LOS'!V$8:V$45,'2_RateCard_Unit'!$I$5:$I$42,INDEX('6_Funnel_And_Lifetime'!$C$20:$G$57,0,MATCH($D24,'6_Funnel_And_Lifetime'!$C$4:$G$4,0)),INDEX('2_RateCard_Unit'!$F$5:$H$42,0,'1_Inputs'!$B$54)) | I24: =IFERROR(H24/F24,0) | J24: =SUMPRODUCT('5_Journey_Units_Service'!V$6:V$21,'6_Funnel_And_Lifetime'!V$104:V$119,'2_RateCard_Unit'!$I$43:$I$58,INDEX('2_RateCard_Unit'!$F$43:$H$58,0,'1_Inputs'!$B$54)) | K24: =SUMPRODUCT('6_Funnel_And_Lifetime'!V$124:V$132,'2_RateCard_Unit'!$I$59:$I$67,INDEX('2_RateCard_Unit'!$F$59:$H$67,0,'1_Inputs'!$B$54)) | L24: =I24+J24+K24 | M24: =IFERROR((J24+K24)/('6_Funnel_And_Lifetime'!$E$82),0) | N24: =IFERROR(L24/E24*10000,0) | O24: =IFERROR(1/F24,0)
A25: 21 | B25: trade_finance_workflow | C25: trade_receivables | D25: MSME_Business | E25: ='4_Journey_Units_LOS'!W$6 | F25: =INDEX('6_Funnel_And_Lifetime'!$C$11:$G$11,MATCH($D25,'6_Funnel_And_Lifetime'!$C$4:$G$4,0)) | G25: ='6_Funnel_And_Lifetime'!$F$83 | H25: =SUMPRODUCT('4_Journey_Units_LOS'!W$8:W$45,'2_RateCard_Unit'!$I$5:$I$42,INDEX('6_Funnel_And_Lifetime'!$C$20:$G$57,0,MATCH($D25,'6_Funnel_And_Lifetime'!$C$4:$G$4,0)),INDEX('2_RateCard_Unit'!$F$5:$H$42,0,'1_Inputs'!$B$54)) | I25: =IFERROR(H25/F25,0) | J25: =SUMPRODUCT('5_Journey_Units_Service'!W$6:W$21,'6_Funnel_And_Lifetime'!W$104:W$119,'2_RateCard_Unit'!$I$43:$I$58,INDEX('2_RateCard_Unit'!$F$43:$H$58,0,'1_Inputs'!$B$54)) | K25: =SUMPRODUCT('6_Funnel_And_Lifetime'!W$124:W$132,'2_RateCard_Unit'!$I$59:$I$67,INDEX('2_RateCard_Unit'!$F$59:$H$67,0,'1_Inputs'!$B$54)) | L25: =I25+J25+K25 | M25: =IFERROR((J25+K25)/('6_Funnel_And_Lifetime'!$E$83),0) | N25: =IFERROR(L25/E25*10000,0) | O25: =IFERROR(1/F25,0)
B27: Cheapest lifetime cost per funded loan | C27: =INDEX($B$5:$B$25,MATCH(MIN(L5:L25),L5:L25,0)) | L27: =MIN(L5:L25)
B28: Most expensive lifetime cost per funded loan | C28: =INDEX($B$5:$B$25,MATCH(MAX(L5:L25),L5:L25,0)) | L28: =MAX(L5:L25)
B29: Spread (max / min) | L29: =IFERROR(MAX(L5:L25)/MIN(L5:L25),0)
B30: Servicing + collections as a share of lifetime cost | L30: =IFERROR(SUM(J5:K25)/SUM(L5:L25),0) | M30: If this is large, an origination-only price is structurally wrong.
B31: Worst affordability (highest bps) | C31: =INDEX($B$5:$B$25,MATCH(MAX(N5:N25),N5:N25,0)) | N31: =MAX(N5:N25)
B33: Column N is the affordability test. A journey whose whole-life cost runs to hundreds of bps of the loan cannot carry a full-stack verification and servicing chain — it needs a cheaper check set and a lighter servicing playbook, not a discount.

Sheet 15_Sensitivity
A1: 15 — Volume sensitivity
A2: Same price card, varying monthly application volume. Governance, storage and the active book are recomputed at each volume. Recurring subscriptions are held constant — they follow branches and seats, not loans.
A4: Monthly applications | B4: Annual applications | C4: Annual funded loans | D4: Active loans | E4: Governance ₹/yr | F4: Storage ₹/yr | G4: Total cost ₹/yr | H4: Total revenue ₹/yr | I4: Gross profit ₹/yr | J4: Blended margin % | K4: Software margin % | L4: Cost per funded loan ₹ | M4: Effective bps | N4: Verdict
A5: 250 | B5: =A5*12 | C5: =B5*'12_Tenant_PnL'!$B$9 | D5: =C5*IF('1_Inputs'!$B$21="Steady state",'12_Tenant_PnL'!$B$16,MIN('12_Tenant_PnL'!$B$16,1)/2) | E5: =IF('1_Inputs'!$B$15="Equal per tenant",'10_Governance_Cost'!$B$21,IF('1_Inputs'!$B$15="Volume weighted",IFERROR('10_Governance_Cost'!$B$15*C5/'1_Inputs'!$B$10,0),0.5*'10_Governance_Cost'!$B$21+0.5*IFERROR('10_Governance_Cost'!$B$15*C5/'1_Inputs'!$B$10,0)))+'10_Governance_Cost'!$B$27*12+'10_Governance_Cost'!$B$28*C5/1000 | F5: =((B5-C5)*'9_Cloud_Cost'!$C$36+C5*'9_Cloud_Cost'!$C$37+D5*'9_Cloud_Cost'!$C$38)/1024*'9_Cloud_Cost'!$C$40*12 | G5: ='12_Tenant_PnL'!$B$61+E5+F5+'12_Tenant_PnL'!$B$62*B5 | H5: ='12_Tenant_PnL'!$B$64+'12_Tenant_PnL'!$B$65*B5 | I5: =H5-G5 | J5: =IFERROR(I5/H5,0) | K5: =IFERROR(I5/(H5-IFERROR('12_Tenant_PnL'!$B$36/'12_Tenant_PnL'!$B$6,0)*B5),0) | L5: =IFERROR(G5/C5,0) | M5: =IFERROR(H5/(C5*'12_Tenant_PnL'!$B$11)*10000,0) | N5: =IF(I5<=0,"LOSS",IF(I5<'12_Tenant_PnL'!$B$61+E5,"Sub-scale","Scaled"))
A6: 500 | B6: =A6*12 | C6: =B6*'12_Tenant_PnL'!$B$9 | D6: =C6*IF('1_Inputs'!$B$21="Steady state",'12_Tenant_PnL'!$B$16,MIN('12_Tenant_PnL'!$B$16,1)/2) | E6: =IF('1_Inputs'!$B$15="Equal per tenant",'10_Governance_Cost'!$B$21,IF('1_Inputs'!$B$15="Volume weighted",IFERROR('10_Governance_Cost'!$B$15*C6/'1_Inputs'!$B$10,0),0.5*'10_Governance_Cost'!$B$21+0.5*IFERROR('10_Governance_Cost'!$B$15*C6/'1_Inputs'!$B$10,0)))+'10_Governance_Cost'!$B$27*12+'10_Governance_Cost'!$B$28*C6/1000 | F6: =((B6-C6)*'9_Cloud_Cost'!$C$36+C6*'9_Cloud_Cost'!$C$37+D6*'9_Cloud_Cost'!$C$38)/1024*'9_Cloud_Cost'!$C$40*12 | G6: ='12_Tenant_PnL'!$B$61+E6+F6+'12_Tenant_PnL'!$B$62*B6 | H6: ='12_Tenant_PnL'!$B$64+'12_Tenant_PnL'!$B$65*B6 | I6: =H6-G6 | J6: =IFERROR(I6/H6,0) | K6: =IFERROR(I6/(H6-IFERROR('12_Tenant_PnL'!$B$36/'12_Tenant_PnL'!$B$6,0)*B6),0) | L6: =IFERROR(G6/C6,0) | M6: =IFERROR(H6/(C6*'12_Tenant_PnL'!$B$11)*10000,0) | N6: =IF(I6<=0,"LOSS",IF(I6<'12_Tenant_PnL'!$B$61+E6,"Sub-scale","Scaled"))
A7: 1000 | B7: =A7*12 | C7: =B7*'12_Tenant_PnL'!$B$9 | D7: =C7*IF('1_Inputs'!$B$21="Steady state",'12_Tenant_PnL'!$B$16,MIN('12_Tenant_PnL'!$B$16,1)/2) | E7: =IF('1_Inputs'!$B$15="Equal per tenant",'10_Governance_Cost'!$B$21,IF('1_Inputs'!$B$15="Volume weighted",IFERROR('10_Governance_Cost'!$B$15*C7/'1_Inputs'!$B$10,0),0.5*'10_Governance_Cost'!$B$21+0.5*IFERROR('10_Governance_Cost'!$B$15*C7/'1_Inputs'!$B$10,0)))+'10_Governance_Cost'!$B$27*12+'10_Governance_Cost'!$B$28*C7/1000 | F7: =((B7-C7)*'9_Cloud_Cost'!$C$36+C7*'9_Cloud_Cost'!$C$37+D7*'9_Cloud_Cost'!$C$38)/1024*'9_Cloud_Cost'!$C$40*12 | G7: ='12_Tenant_PnL'!$B$61+E7+F7+'12_Tenant_PnL'!$B$62*B7 | H7: ='12_Tenant_PnL'!$B$64+'12_Tenant_PnL'!$B$65*B7 | I7: =H7-G7 | J7: =IFERROR(I7/H7,0) | K7: =IFERROR(I7/(H7-IFERROR('12_Tenant_PnL'!$B$36/'12_Tenant_PnL'!$B$6,0)*B7),0) | L7: =IFERROR(G7/C7,0) | M7: =IFERROR(H7/(C7*'12_Tenant_PnL'!$B$11)*10000,0) | N7: =IF(I7<=0,"LOSS",IF(I7<'12_Tenant_PnL'!$B$61+E7,"Sub-scale","Scaled"))
A8: 2500 | B8: =A8*12 | C8: =B8*'12_Tenant_PnL'!$B$9 | D8: =C8*IF('1_Inputs'!$B$21="Steady state",'12_Tenant_PnL'!$B$16,MIN('12_Tenant_PnL'!$B$16,1)/2) | E8: =IF('1_Inputs'!$B$15="Equal per tenant",'10_Governance_Cost'!$B$21,IF('1_Inputs'!$B$15="Volume weighted",IFERROR('10_Governance_Cost'!$B$15*C8/'1_Inputs'!$B$10,0),0.5*'10_Governance_Cost'!$B$21+0.5*IFERROR('10_Governance_Cost'!$B$15*C8/'1_Inputs'!$B$10,0)))+'10_Governance_Cost'!$B$27*12+'10_Governance_Cost'!$B$28*C8/1000 | F8: =((B8-C8)*'9_Cloud_Cost'!$C$36+C8*'9_Cloud_Cost'!$C$37+D8*'9_Cloud_Cost'!$C$38)/1024*'9_Cloud_Cost'!$C$40*12 | G8: ='12_Tenant_PnL'!$B$61+E8+F8+'12_Tenant_PnL'!$B$62*B8 | H8: ='12_Tenant_PnL'!$B$64+'12_Tenant_PnL'!$B$65*B8 | I8: =H8-G8 | J8: =IFERROR(I8/H8,0) | K8: =IFERROR(I8/(H8-IFERROR('12_Tenant_PnL'!$B$36/'12_Tenant_PnL'!$B$6,0)*B8),0) | L8: =IFERROR(G8/C8,0) | M8: =IFERROR(H8/(C8*'12_Tenant_PnL'!$B$11)*10000,0) | N8: =IF(I8<=0,"LOSS",IF(I8<'12_Tenant_PnL'!$B$61+E8,"Sub-scale","Scaled"))
A9: 5000 | B9: =A9*12 | C9: =B9*'12_Tenant_PnL'!$B$9 | D9: =C9*IF('1_Inputs'!$B$21="Steady state",'12_Tenant_PnL'!$B$16,MIN('12_Tenant_PnL'!$B$16,1)/2) | E9: =IF('1_Inputs'!$B$15="Equal per tenant",'10_Governance_Cost'!$B$21,IF('1_Inputs'!$B$15="Volume weighted",IFERROR('10_Governance_Cost'!$B$15*C9/'1_Inputs'!$B$10,0),0.5*'10_Governance_Cost'!$B$21+0.5*IFERROR('10_Governance_Cost'!$B$15*C9/'1_Inputs'!$B$10,0)))+'10_Governance_Cost'!$B$27*12+'10_Governance_Cost'!$B$28*C9/1000 | F9: =((B9-C9)*'9_Cloud_Cost'!$C$36+C9*'9_Cloud_Cost'!$C$37+D9*'9_Cloud_Cost'!$C$38)/1024*'9_Cloud_Cost'!$C$40*12 | G9: ='12_Tenant_PnL'!$B$61+E9+F9+'12_Tenant_PnL'!$B$62*B9 | H9: ='12_Tenant_PnL'!$B$64+'12_Tenant_PnL'!$B$65*B9 | I9: =H9-G9 | J9: =IFERROR(I9/H9,0) | K9: =IFERROR(I9/(H9-IFERROR('12_Tenant_PnL'!$B$36/'12_Tenant_PnL'!$B$6,0)*B9),0) | L9: =IFERROR(G9/C9,0) | M9: =IFERROR(H9/(C9*'12_Tenant_PnL'!$B$11)*10000,0) | N9: =IF(I9<=0,"LOSS",IF(I9<'12_Tenant_PnL'!$B$61+E9,"Sub-scale","Scaled"))
A10: 10000 | B10: =A10*12 | C10: =B10*'12_Tenant_PnL'!$B$9 | D10: =C10*IF('1_Inputs'!$B$21="Steady state",'12_Tenant_PnL'!$B$16,MIN('12_Tenant_PnL'!$B$16,1)/2) | E10: =IF('1_Inputs'!$B$15="Equal per tenant",'10_Governance_Cost'!$B$21,IF('1_Inputs'!$B$15="Volume weighted",IFERROR('10_Governance_Cost'!$B$15*C10/'1_Inputs'!$B$10,0),0.5*'10_Governance_Cost'!$B$21+0.5*IFERROR('10_Governance_Cost'!$B$15*C10/'1_Inputs'!$B$10,0)))+'10_Governance_Cost'!$B$27*12+'10_Governance_Cost'!$B$28*C10/1000 | F10: =((B10-C10)*'9_Cloud_Cost'!$C$36+C10*'9_Cloud_Cost'!$C$37+D10*'9_Cloud_Cost'!$C$38)/1024*'9_Cloud_Cost'!$C$40*12 | G10: ='12_Tenant_PnL'!$B$61+E10+F10+'12_Tenant_PnL'!$B$62*B10 | H10: ='12_Tenant_PnL'!$B$64+'12_Tenant_PnL'!$B$65*B10 | I10: =H10-G10 | J10: =IFERROR(I10/H10,0) | K10: =IFERROR(I10/(H10-IFERROR('12_Tenant_PnL'!$B$36/'12_Tenant_PnL'!$B$6,0)*B10),0) | L10: =IFERROR(G10/C10,0) | M10: =IFERROR(H10/(C10*'12_Tenant_PnL'!$B$11)*10000,0) | N10: =IF(I10<=0,"LOSS",IF(I10<'12_Tenant_PnL'!$B$61+E10,"Sub-scale","Scaled"))
A11: 25000 | B11: =A11*12 | C11: =B11*'12_Tenant_PnL'!$B$9 | D11: =C11*IF('1_Inputs'!$B$21="Steady state",'12_Tenant_PnL'!$B$16,MIN('12_Tenant_PnL'!$B$16,1)/2) | E11: =IF('1_Inputs'!$B$15="Equal per tenant",'10_Governance_Cost'!$B$21,IF('1_Inputs'!$B$15="Volume weighted",IFERROR('10_Governance_Cost'!$B$15*C11/'1_Inputs'!$B$10,0),0.5*'10_Governance_Cost'!$B$21+0.5*IFERROR('10_Governance_Cost'!$B$15*C11/'1_Inputs'!$B$10,0)))+'10_Governance_Cost'!$B$27*12+'10_Governance_Cost'!$B$28*C11/1000 | F11: =((B11-C11)*'9_Cloud_Cost'!$C$36+C11*'9_Cloud_Cost'!$C$37+D11*'9_Cloud_Cost'!$C$38)/1024*'9_Cloud_Cost'!$C$40*12 | G11: ='12_Tenant_PnL'!$B$61+E11+F11+'12_Tenant_PnL'!$B$62*B11 | H11: ='12_Tenant_PnL'!$B$64+'12_Tenant_PnL'!$B$65*B11 | I11: =H11-G11 | J11: =IFERROR(I11/H11,0) | K11: =IFERROR(I11/(H11-IFERROR('12_Tenant_PnL'!$B$36/'12_Tenant_PnL'!$B$6,0)*B11),0) | L11: =IFERROR(G11/C11,0) | M11: =IFERROR(H11/(C11*'12_Tenant_PnL'!$B$11)*10000,0) | N11: =IF(I11<=0,"LOSS",IF(I11<'12_Tenant_PnL'!$B$61+E11,"Sub-scale","Scaled"))
A12: 50000 | B12: =A12*12 | C12: =B12*'12_Tenant_PnL'!$B$9 | D12: =C12*IF('1_Inputs'!$B$21="Steady state",'12_Tenant_PnL'!$B$16,MIN('12_Tenant_PnL'!$B$16,1)/2) | E12: =IF('1_Inputs'!$B$15="Equal per tenant",'10_Governance_Cost'!$B$21,IF('1_Inputs'!$B$15="Volume weighted",IFERROR('10_Governance_Cost'!$B$15*C12/'1_Inputs'!$B$10,0),0.5*'10_Governance_Cost'!$B$21+0.5*IFERROR('10_Governance_Cost'!$B$15*C12/'1_Inputs'!$B$10,0)))+'10_Governance_Cost'!$B$27*12+'10_Governance_Cost'!$B$28*C12/1000 | F12: =((B12-C12)*'9_Cloud_Cost'!$C$36+C12*'9_Cloud_Cost'!$C$37+D12*'9_Cloud_Cost'!$C$38)/1024*'9_Cloud_Cost'!$C$40*12 | G12: ='12_Tenant_PnL'!$B$61+E12+F12+'12_Tenant_PnL'!$B$62*B12 | H12: ='12_Tenant_PnL'!$B$64+'12_Tenant_PnL'!$B$65*B12 | I12: =H12-G12 | J12: =IFERROR(I12/H12,0) | K12: =IFERROR(I12/(H12-IFERROR('12_Tenant_PnL'!$B$36/'12_Tenant_PnL'!$B$6,0)*B12),0) | L12: =IFERROR(G12/C12,0) | M12: =IFERROR(H12/(C12*'12_Tenant_PnL'!$B$11)*10000,0) | N12: =IF(I12<=0,"LOSS",IF(I12<'12_Tenant_PnL'!$B$61+E12,"Sub-scale","Scaled"))
A14: How to read this table:
A16: 1. Both gross PROFIT (column I) and margin (columns J and K) RISE with volume, and both asymptote. That is the classic fixed-base shape: the per-tenant floor — the isolated decision runtime (ADR 0003), the allocated compliance base, the support tier and the whole RECURRING class — is incurred at any volume and does not shrink.
A17: 2. Below the break-even row this tenant LOSES money at the quoted price. The cause is almost never the per-loan fee; it is that the fixed base was sized for a bigger book. Recurring cost in particular follows branches, devices, seats and partners, so a small branch-heavy tenant can carry a larger fixed base than a much bigger digital one.
A18: 3. The CEILING on blended margin (column J) is set by pass-through mix, not by inefficiency. Rebilled bureau, KYC, eSign, NACH and reporting-rail cost carries only the handling markup, so it permanently dilutes the blended percentage however efficient the platform becomes. Software margin (column K) is the real measure — manage to it, and never set a commission or an OKR on column J.
A19: 4. 'Sub-scale' means gross profit does not yet exceed this tenant's own fixed cost — the deal works on paper but leaves no room for the unmodelled human cost of a real customer relationship.
A21: The commercial conclusion: the platform fee, not the per-loan fee, is what makes a small tenant safe to sign. Size it against the quantity drivers on sheet 1, not against the tenant's expected loan volume.

Sheet 16_Coverage_Map
A1: 16 — Integration coverage map
A2: Every one of the 115 INT-* integrations in platform-module-integration-api-map.md and exactly how this model treats it. Nothing is silently omitted; anything not priced by a driver states where it is absorbed instead.
A4: INT ID | B4: Module | C4: Capability | D4: Treatment | E4: Priced driver(s) | F4: If not priced — where it is absorbed
A5: INT-CUS-01 | B5: Customer channels & CRM | C5: Registration and contact verification | D5: Priced driver | E5: D01
A6: INT-CUS-02 | B6: Customer channels & CRM | C6: Lead capture and dedupe | D6: Priced driver | E6: D02
A7: INT-CUS-03 | B7: Customer channels & CRM | C7: Branch/partner acquisition | D7: Priced driver | E7: R03
A8: INT-CUS-04 | B8: Customer channels & CRM | C8: Document collection | D8: Priced driver | E8: D03
A9: INT-CUS-05 | B9: Customer channels & CRM | C9: Government documents | D9: Priced driver | E9: D04
A10: INT-CUS-06 | B10: Customer channels & CRM | C10: Mobile/field channel | D10: Priced driver | E10: R01
A11: INT-CUS-07 | B11: Customer channels & CRM | C11: Offline field work | D11: Priced driver | E11: D36
A12: INT-CUS-08 | B12: Customer channels & CRM | C12: Language/accessibility | D12: Priced driver | E12: R04
A13: INT-LOS-01 | B13: Loan origination | C13: Applicant identity | D13: Priced driver | E13: D06, D07
A14: INT-LOS-02 | B14: Loan origination | C14: KYC reuse/registration | D14: Priced driver | E14: D08
A15: INT-LOS-03 | B15: Loan origination | C15: Remote KYC | D15: Priced driver | E15: D09, D10
A16: INT-LOS-04 | B16: Loan origination | C16: Business/KYB | D16: Priced driver | E16: D12, D13
... A29: INT-LOS-17 | B29: Loan origination | C29: Customer delivery | D29: Priced driver | E29: D27
A30: INT-RSK-01 | B30: Decision / risk / AML | C30: Eligibility/pricing facts | D30: Internal | F30: fact assembly from feeds already priced individually
A31: INT-RSK-02 | B31: Decision / risk / AML | C31: Screening/CDD | D31: Internal | F31: screening execution priced at D11 and S10
A32: INT-RSK-03 | B32: Decision / risk / AML | C32: Transaction monitoring | D32: Internal | F32: transaction monitoring evaluation is internal compute
A33: INT-RSK-04 | B33: Decision / risk / AML | C33: Fraud intelligence | D33: Internal | F33: consortium lookup priced at D05
A34: INT-RSK-05 | B34: Decision / risk / AML | C34: Model operations | D34: Priced driver | E34: R06
A35: INT-RSK-06 | B35: Decision / risk / AML | C35: Reference data | D35: Priced driver | E35: R05
A36: INT-RSK-07 | B36: Decision / risk / AML | C36: Foundation-model and agent runtime | D36: Priced driver | E36: D26
A37: INT-RSK-08 | B37: Decision / risk / AML | C37: Agent knowledge and retrieval | D37: Priced driver | E37: D38, R07
A38: INT-LWS-01 | B38: Lending workspaces | C38: Staff authority/routing | D38: Priced driver | E38: R08
A39: INT-LWS-02 | B39: Lending workspaces | C39: Authentication/provisioning | D39: Priced driver | E39: R09
A40: INT-LWS-03 | B40: Lending workspaces | C40: Task/escalation | D40: Priced driver | E40: R10
A41: INT-LWS-04 | B41: Lending workspaces | C41: Evidence/committees | D41: Priced driver | E41: R11
A42: INT-LWS-05 | B42: Lending workspaces | C42: External work orders | D42: Priced driver | E42: R12
A43: INT-LWS-06 | B43: Lending workspaces | C43: Complaints/Ombudsman | D43: Priced driver | E43: R13
A44: INT-LWS-07 | B44: Lending workspaces | C44: Court/regulator tasks | D44: Priced driver | E44: R14
A45: INT-LWS-08 | B45: Lending workspaces | C45: Workflow workers | D45: Cloud sheet | F45: queue_workers component
A46: INT-LMS-01 | B46: Loan management | C46: Account boarding/posting | D46: Priced driver | E46: S01
A47: INT-LMS-02 | B47: Loan management | C47: Mandates | D47: Priced driver | E47: D35
A48: INT-LMS-03 | B48: Loan management | C48: Scheduled collection | D48: Priced driver | E48: S02, S03
A49: INT-LMS-04 | B49: Loan management | C49: Receipt/reconciliation | D49: Priced driver | E49: S04
A50: INT-LMS-05 | B50: Loan management | C50: Refunds/payouts | D50: Priced driver | E50: S12
A51: INT-LMS-06 | B51: Loan management | C51: Servicing notices | D51: Priced driver | E51: S05
A52: INT-LMS-07 | B52: Loan management | C52: Statements/vault | D52: Priced driver | E52: S06
A53: INT-LMS-08 | B53: Loan management | C53: Credit furnishing | D53: Priced driver | E53: S07
A54: INT-LMS-09 | B54: Loan management | C54: Ongoing KYC/risk | D54: Priced driver | E54: S08, S09, S10
A55: INT-LMS-10 | B55: Loan management | C55: Insurance/collateral | D55: Priced driver | E55: S11
A56: INT-LMS-11 | B56: Loan management | C56: Restructure/transfer | D56: Priced driver | E56: S13
A57: INT-LMS-12 | B57: Loan management | C57: Closure/release | D57: Priced driver | E57: S14
... A66: INT-COLAT-01 | B66: Collateral | C66: Asset verification | D66: Priced driver | E66: D37
A67: INT-COLAT-02 | B67: Collateral | C67: Valuation | D67: Priced at origination | F67: valuation is D21; revaluation is S11
A68: INT-COLAT-03 | B68: Collateral | C68: Legal/title | D68: Priced at origination | F68: legal/title is D22
A69: INT-COLAT-04 | B69: Collateral | C69: Security registry | D69: Priced driver | E69: S15
A70: INT-COLAT-05 | B70: Collateral | C70: Insurance | D70: Priced at origination | F70: insurance bind is D31; renewal is S11
A71: INT-COLAT-06 | B71: Collateral | C71: Custody | D71: Priced driver | E71: S16
A72: INT-COLAT-07 | B72: Collateral | C72: Repossession/yard | D72: Priced driver | E72: C09
A73: INT-FIN-01 | B73: Finance & accounting | C73: CBS/GL | D73: Priced driver | E73: R23
A74: INT-FIN-02 | B74: Finance & accounting | C74: Bank reconciliation | D74: Priced driver | E74: R24
A75: INT-FIN-03 | B75: Finance & accounting | C75: Rail settlement | D75: Priced driver | E75: R25
A76: INT-FIN-04 | B76: Finance & accounting | C76: Escrow/co-lender | D76: Priced driver | E76: R26
A77: INT-FIN-05 | B77: Finance & accounting | C77: GST/e-invoice | D77: Priced driver | E77: R27
A78: INT-FIN-06 | B78: Finance & accounting | C78: TDS/Income Tax | D78: Priced driver | E78: R28
A79: INT-FIN-07 | B79: Finance & accounting | C79: Treasury/ALM | D79: Priced driver | E79: R29
A80: INT-FIN-08 | B80: Finance & accounting | C80: Vendor/partner payables | D80: Priced driver | E80: R30
A81: INT-REG-01 | B81: Regulatory reporting | C81: CKYCRR | D81: Priced driver | E81: R15
A82: INT-REG-02 | B82: Regulatory reporting | C82: CIC furnishing | D82: Priced driver | E82: R16
... A95: INT-PRT-06 | B95: Partner / LSP | C95: Oversight/SLA | D95: Priced driver | E95: R34
A96: INT-PLT-01 | B96: Platform | C96: Workforce identity | D96: Governance sheet | F96: our own workforce identity, not the tenant's
A97: INT-PLT-02 | B97: Platform | C97: Secrets/crypto | D97: Cloud sheet | F97: keys_secrets component
A98: INT-PLT-03 | B98: Platform | C98: Security monitoring | D98: Cloud sheet | F98: monitoring_siem component
A99: INT-PLT-04 | B99: Platform | C99: Evidence/time | D99: Priced driver | E99: R21
A100: INT-PLT-05 | B100: Platform | C100: Database | D100: Cloud sheet | F100: database_isolation component
A101: INT-PLT-06 | B101: Platform | C101: Events/jobs | D101: Cloud sheet | F101: queue_workers component
A102: INT-PLT-07 | B102: Platform | C102: API management | D102: Cloud sheet | F102: network_domain_certificates component
A103: INT-PLT-08 | B103: Platform | C103: Observability/support | D103: Service sheet | F103: observability, on-call, incident and SLA
A104: INT-PLT-09 | B104: Platform | C104: CDC/warehouse/lake | D104: Priced driver | E104: R35
A105: INT-PLT-10 | B105: Platform | C105: BI | D105: Priced driver | E105: R36
A106: INT-PLT-11 | B106: Platform | C106: Deployment/supply chain | D106: Governance sheet | F106: CI, signing, SBOM, scans, canary evidence
A107: INT-PLT-12 | B107: Platform | C107: Tenant billing | D107: Priced driver | E107: R37
A108: INT-PLT-13 | B108: Platform | C108: Device management | D108: Priced driver | E108: R02
A109: INT-PLT-14 | B109: Platform | C109: Portability/archive | D109: Cloud sheet | F109: portability_exit component
A110: INT-ADM-01 | B110: SaaS org admission | C110: Signup contact and invitations | D110: Priced driver | E110: A01
A111: INT-ADM-02 | B111: SaaS org admission | C111: Legal-entity and tax identity | D111: Priced driver | E111: A02
A112: INT-ADM-03 | B112: SaaS org admission | C112: Regulated-entity authority | D112: Priced driver | E112: A03
A113: INT-ADM-04 | B113: SaaS org admission | C113: Representative authority and signature | D113: Priced driver | E113: A04
A114: INT-ADM-05 | B114: SaaS org admission | C114: Corporate domain and contact assurance | D114: Priced driver | E114: A05
A115: INT-ADM-06 | B115: SaaS org admission | C115: Signup abuse and fraud defence | D115: Priced driver | E115: A06
A116: INT-ADM-07 | B116: SaaS org admission | C116: Contract and outsourcing due diligence | D116: Priced driver | E116: A07
A117: INT-ADM-08 | B117: SaaS org admission | C117: Subscription, invoicing and tax | D117: Priced driver | E117: R37
A118: INT-ADM-09 | B118: SaaS org admission | C118: Tenant infrastructure provisioning | D118: Cloud sheet | F118: all 17 provisioning components + onboarding
A119: INT-ADM-10 | B119: SaaS org admission | C119: Workforce federation and re-verification | D119: Governance sheet | F119: workforce federation and re-verification
B121: Total integrations in the map | D121: 115
B122: Carrying an explicit priced driver | D122: =COUNTIF($D$5:$D$119,"Priced driver")
B123: Absorbed by cloud / governance / service sheets or internal | D123: =115-COUNTIF($D$5:$D$119,"Priced driver")-COUNTIF($D$5:$D$119,"NOT COSTED")
B124: NOT COSTED (real gaps) | D124: =COUNTIF($D$5:$D$119,"NOT COSTED")
B126: Absorbed is not the same as free. A component in the cloud or governance sheet still costs money — it is just priced there as part of a bundle rather than metered per event. If any of those becomes separately billable by a vendor, promote it to its own driver on sheet 2 or 3.
